Workbook

Sheet 审阅导航
A2: 汽车访谈题库：2C与2B独立结构
A4: 2C按生活背景与本人经历展开；2B先交代受访者机构与市场背景，再讨论客户画像和成交。
A5: 2C仅保留消费者本人；商务/组织采购者移至2B独立模块，并按实际采购与使用经历触发。
A6: 2B按经销商、媒体、主机厂专家、商务/组织采购者分角色。每题只对具有相应职责和证据的对象出现。
A7: 2C共143个题卡；2B合并后共51个题卡。来源映射保留，不把合并视为删失原始资料。
A8: 2C明确设置“购车考虑因素”和“补贴与政策影响”；产品概念、价格、卖点等题目均增加材料触发条件。
A9: 先看两套目录，再分别审阅；黄色列可填确认状态及意见。原题、原追问和历史材料保留在末尾来源表。
A10: 原追问是来源审阅层，混合角色原文保留；执行时应按本表2C/2B口径调整，不直接全量拼接。
A11: 国家政策、历史价格及技术参数仍待项目核验；本次未修改网站。
A13: 顺序 | B13: 独立模块 | C13: 条目数 | D13: 已同意 | E13: 需修改 | F13: 待审阅 | G13: 模块任务 | H13: 执行说明
A14: C0 | B14: 2C-00 执行话术 | C14: =COUNTA('2C-00 执行话术'!A6:A8) -> 3 | D14: =COUNTIFS('2C-00 执行话术'!H6:H8,"同意") -> 3 | E14: =COUNTIFS('2C-00 执行话术'!H6:H8,"需修改") -> 0 | F14: =COUNTIFS('2C-00 执行话术'!H6:H8,"待审阅") -> 0 | G14: 开场、观察许可与收尾话术 | H14: 执行工具：开场置前，收尾置后
A15: C1 | B15: 2C-01 生活与车辆背景 | C15: =COUNTA('2C-01 生活与车辆背景'!A6:A19) -> 14 | D15: =COUNTIFS('2C-01 生活与车辆背景'!H6:H19,"同意") -> 13 | E15: =COUNTIFS('2C-01 生活与车辆背景'!H6:H19,"需修改") -> 0 | F15: =COUNTIFS('2C-01 生活与车辆背景'!H6:H19,"待审阅") -> 0 | G15: 开场建立消费者本人生活与车辆背景 | H15: 模块内按项目目标选题，不要求全部问完
A16: C2 | B16: 2C-02 场景与体验 | C16: =COUNTA('2C-02 场景与体验'!A6:A41) -> 36 | D16: =COUNTIFS('2C-02 场景与体验'!H6:H41,"同意") -> 34 | E16: =COUNTIFS('2C-02 场景与体验'!H6:H41,"需修改") -> 0 | F16: =COUNTIFS('2C-02 场景与体验'!H6:H41,"待审阅") -> 0 | G16: 还原真实场景、体验、痛点及本地条件 | H16: 模块内按项目目标选题，不要求全部问完
A17: C3 | B17: 2C-03 购买旅程与考虑因素 | C17: =COUNTA('2C-03 购买旅程与考虑因素'!A6:A28) -> 23 | D17: =COUNTIFS('2C-03 购买旅程与考虑因素'!H6:H28,"同意") -> 19 | E17: =COUNTIFS('2C-03 购买旅程与考虑因素'!H6:H28,"需修改") -> 0 | F17: =COUNTIFS('2C-03 购买旅程与考虑因素'!H6:H28,"待审阅") -> 0 | G17: 购车旅程、考虑因素、支付、补贴及政策影响 | H17: 模块内按项目目标选题，不要求全部问完
A18: C4 | B18: 2C-04 动力与补能 | C18: =COUNTA('2C-04 动力与补能'!A6:A25) -> 20 | D18: =COUNTIFS('2C-04 动力与补能'!H6:H25,"同意") -> 15 | E18: =COUNTIFS('2C-04 动力与补能'!H6:H25,"需修改") -> 0 | F18: =COUNTIFS('2C-04 动力与补能'!H6:H25,"待审阅") -> 0 | G18: 结合实际任务讨论动力与补能 | H18: 模块内按项目目标选题，不要求全部问完
A19: C5 | B19: 2C-05 产品与配置 | C19: =COUNTA('2C-05 产品与配置'!A6:A37) -> 32 | D19: =COUNTIFS('2C-05 产品与配置'!H6:H37,"同意") -> 25 | E19: =COUNTIFS('2C-05 产品与配置'!H6:H37,"需修改") -> 0 | F19: =COUNTIFS('2C-05 产品与配置'!H6:H37,"待审阅") -> 0 | G19: 明确材料后评价产品和配置 | H19: 模块内按项目目标选题，不要求全部问完
A20: C6 | B20: 2C-06 品牌与购买条件 | C20: =COUNTA('2C-06 品牌与购买条件'!A6:A20) -> 15 | D20: =COUNTIFS('2C-06 品牌与购买条件'!H6:H20,"同意") -> 15 | E20: =COUNTIFS('2C-06 品牌与购买条件'!H6:H20,"需修改") -> 0 | F20: =COUNTIFS('2C-06 品牌与购买条件'!H6:H20,"待审阅") -> 0 | G20: 品牌理解、价格取舍与购买条件 | H20: 模块内按项目目标选题，不要求全部问完
A21: B0 | B21: 2B-00 执行话术 | C21: =COUNTA('2B-00 执行话术'!A6:A7) -> 2 | D21: =COUNTIFS('2B-00 执行话术'!H6:H7,"同意") -> 2 | E21: =COUNTIFS('2B-00 执行话术'!H6:H7,"需修改") -> 0 | F21: =COUNTIFS('2B-00 执行话术'!H6:H7,"待审阅") -> 0 | G21: 开场参与说明与最后核对 | H21: 执行工具：开场置前，收尾置后
A22: B1 | B22: 2B-01 受访者与机构背景 | C22: =COUNTA('2B-01 受访者与机构背景'!A6:A7) -> 2 | D22: =COUNTIFS('2B-01 受访者与机构背景'!H6:H7,"同意") -> 2 | E22: =COUNTIFS('2B-01 受访者与机构背景'!H6:H7,"需修改") -> 0 | F22: =COUNTIFS('2B-01 受访者与机构背景'!H6:H7,"待审阅") -> 0 | G22: 确认受访者职责与机构范围 | H22: 受访者本人/机构背景；不是客户画像
A23: B2 | B23: 2B-02 品牌市场与政策 | C23: =COUNTA('2B-02 品牌市场与政策'!A6:A9) -> 4 | D23: =COUNTIFS('2B-02 品牌市场与政策'!H6:H9,"同意") -> 4 | E23: =COUNTIFS('2B-02 品牌市场与政策'!H6:H9,"需修改") -> 0 | F23: =COUNTIFS('2B-02 品牌市场与政策'!H6:H9,"待审阅") -> 0 | G23: 品牌、市场、销量、补贴与政策背景 | H23: 模块内按项目目标选题，不要求全部问完
A24: B3 | B24: 2B-03 客户画像与用途 | C24: =COUNTA('2B-03 客户画像与用途'!A6:A9) -> 4 | D24: =COUNTIFS('2B-03 客户画像与用途'!H6:H9,"同意") -> 2 | E24: =COUNTIFS('2B-03 客户画像与用途'!H6:H9,"需修改") -> 2 | F24: =COUNTIFS('2B-03 客户画像与用途'!H6:H9,"待审阅") -> 0 | G24: 客户画像、车辆关系与典型用途 | H24: 模块内按项目目标选题，不要求全部问完
A25: B4 | B25: 2B-04 成交与流失 | C25: =COUNTA('2B-04 成交与流失'!A6:A11) -> 6 | D25: =COUNTIFS('2B-04 成交与流失'!H6:H11,"同意") -> 6 | E25: =COUNTIFS('2B-04 成交与流失'!H6:H11,"需修改") -> 0 | F25: =COUNTIFS('2B-04 成交与流失'!H6:H11,"待审阅") -> 0 | G25: 购买触发、考虑因素、成交及流失 | H25: 模块内按项目目标选题，不要求全部问完
A26: B5 | B26: 2B-05 产品需求与方案 | C26: =COUNTA('2B-05 产品需求与方案'!A6:A16) -> 11 | D26: =COUNTIFS('2B-05 产品需求与方案'!H6:H16,"同意") -> 11 | E26: =COUNTIFS('2B-05 产品需求与方案'!H6:H16,"需修改") -> 0 | F26: =COUNTIFS('2B-05 产品需求与方案'!H6:H16,"待审阅") -> 0 | G26: 从客户反馈和专业证据评价产品 | H26: 模块内按项目目标选题，不要求全部问完
A27: B6 | B27: 2B-06 价格版型与盈利 | C27: =COUNTA('2B-06 价格版型与盈利'!A6:A9) -> 4 | D27: =COUNTIFS('2B-06 价格版型与盈利'!H6:H9,"同意") -> 4 | E27: =COUNTIFS('2B-06 价格版型与盈利'!H6:H9,"需修改") -> 0 | F27: =COUNTIFS('2B-06 价格版型与盈利'!H6:H9,"待审阅") -> 0 | G27: 预算、价格、金融和经销商盈利 | H27: 模块内按项目目标选题，不要求全部问完
A28: B7 | B28: 2B-07 渠道营销与服务 | C28: =COUNTA('2B-07 渠道营销与服务'!A6:A9) -> 4 | D28: =COUNTIFS('2B-07 渠道营销与服务'!H6:H9,"同意") -> 4 | E28: =COUNTIFS('2B-07 渠道营销与服务'!H6:H9,"需修改") -> 0 | F28: =COUNTIFS('2B-07 渠道营销与服务'!H6:H9,"待审阅") -> 0 | G28: 获客、传播、渠道与售后服务 | H28: 模块内按项目目标选题，不要求全部问完
A29: B8 | B29: 2B-08 品牌机会与策略 | C29: =COUNTA('2B-08 品牌机会与策略'!A6:A10) -> 5 | D29: =COUNTIFS('2B-08 品牌机会与策略'!H6:H10,"同意") -> 5 | E29: =COUNTIFS('2B-08 品牌机会与策略'!H6:H10,"需修改") -> 0 | F29: =COUNTIFS('2B-08 品牌机会与策略'!H6:H10,"待审阅") -> 0 | G29: 品牌形象、中国品牌与市场进入 | H29: 模块内按项目目标选题，不要求全部问完
A30: B9 | B30: 2B-09 商务与组织采购 | C30: =COUNTA('2B-09 商务与组织采购'!A6:A14) -> 9 | D30: =COUNTIFS('2B-09 商务与组织采购'!H6:H14,"同意") -> 9 | E30: =COUNTIFS('2B-09 商务与组织采购'!H6:H14,"需修改") -> 0 | F30: =COUNTIFS('2B-09 商务与组织采购'!H6:H14,"待审阅") -> 0 | G30: 商务与组织车辆的真实采购和使用 | H30: 模块内按项目目标选题，不要求全部问完
B32: 2C题卡合计 | C32: =SUM(C14:C20) -> 143 | D32: =SUM(D14:D20) -> 124 | E32: =SUM(E14:E20) -> 0 | F32: =SUM(F14:F20) -> 0
B33: 2B题卡合计 | C33: =SUM(C21:C30) -> 51 | D33: =SUM(D21:D30) -> 49 | E33: =SUM(E21:E30) -> 2 | F33: =SUM(F21:F30) -> 0
A36: FGD与IHV的执行差异
A37: FGD可按2C目录推进，先个人回答再讨论；IHV先背景与购买旅程，再沿真实看车动线串联场景、空间和补能任务。
A39: 2B按角色触发：经销商答客户与订单，媒体答传播和公开观察，主机厂专家答职责范围内的市场/产品证据，商务与组织采购者答本组织经历。

Sheet 2C-00 执行话术
A2: 2C-00 执行话术
A3: 3张题卡。2C：消费者本人及家庭的真实经历。黄色列供你填写；核心信息已回答就不重复问。
A5: 题卡编号 | B5: 子模块与适用方法 | C5: 研究目的与边界 | D5: 主问：按对象选用 | E5: 核心追问：覆盖信息 | F5: 触发条件与观察任务 | G5: 归并调整与来源 | H5: 确认状态 | I5: 你的修改意见
A6: Q-E0-01 | B6: C0 执行话术 核心信息 FGD：可用 IHV：可用 | C6: 明确参与许可、记录口径与结束核对，执行环节不计研究模块。 | D6: 车主：今天我们想了解您的真实出行与选车经历，没有标准答案。您可以不回答任何不愿谈的问题；开始前是否愿意参与？ 意向者：今天我们想了解您的真实出行与选车经历，没有标准答案。您可以不回答任何不愿谈的问题；开始前是否愿意参与？ | E6: 1. 说明研究目的、预计时长、资料用途与保密安排 2. 如需录音、拍照或观察，分别征求许可；拒绝不影响继续交流 3. 记录日期、地点、访问员、受访者代号与必要的样本信息 | F6: 按研究目的选用；有实际经历先谈经历，设想单独记录。 原追问4条：在“原追问审阅”按题卡编号筛选；详情保留在该表，不能把全部追问逐项念出。 | G6: 2C用户本人提纲：按生活背景—经历—选择—方案的顺序呈现。保留研究任务，按对象区分问法；同义主问合并，细节保留为按条件追问。 原编号题：5条；在“原题映射”按本题编号检索。 | H6: 同意
A7: Q-E0-02 | B7: C0 执行话术 按需选择 FGD：不适用 IHV：可用 | C7: 明确参与许可、记录口径与结束核对，执行环节不计研究模块。 | D7: 车主：在您愿意的范围内，能否带我们看看与日常出行和物品收纳有关的空间？ 意向者：在您愿意的范围内，能否带我们看看与日常出行和物品收纳有关的空间？ | E7: 1. 不进入不愿展示的区域 2. 只记录研究相关观察 3. 观察与解释分开 | F7: 仅IHV现场，征得观察许可。 原追问1条：在“原追问审阅”按题卡编号筛选；详情保留在该表，不能把全部追问逐项念出。 | G7: 2C用户本人提纲：按生活背景—经历—选择—方案的顺序呈现。保留研究任务，按对象区分问法；同义主问合并，细节保留为按条件追问。 原编号题：1条；在“原题映射”按本题编号检索。 | H7: 同意
A8: Q-E0-03 | B8: C0 执行话术 核心信息 FGD：可用 IHV：可用 | C8: 明确参与许可、记录口径与结束核对，执行环节不计研究模块。 | D8: 车主：还有什么重要情况没有谈到？如果只留下三条建议，您最希望我们记住什么？ 意向者：还有什么重要情况没有谈到？如果只留下三条建议，您最希望我们记住什么？ | E8: 1. 回到研究目的 2. 区分优先级 3. 核对是否误解 | F8: 按研究目的选用；有实际经历先谈经历，设想单独记录。 原追问1条：在“原追问审阅”按题卡编号筛选；详情保留在该表，不能把全部追问逐项念出。 | G8: 2C用户本人提纲：按生活背景—经历—选择—方案的顺序呈现。保留研究任务，按对象区分问法；同义主问合并，细节保留为按条件追问。 原编号题：4条；在“原题映射”按本题编号检索。 | H8: 同意

Sheet 2C-01 生活与车辆背景
A2: 2C-01 生活与车辆背景
A3: 14张题卡。2C：消费者本人及家庭的真实经历。黄色列供你填写；核心信息已回答就不重复问。
A5: 题卡编号 | B5: 子模块与适用方法 | C5: 研究目的与边界 | D5: 主问：按对象选用 | E5: 核心追问：覆盖信息 | F5: 触发条件与观察任务 | G5: 归并调整与来源 | H5: 确认状态 | I5: 你的修改意见
A6: Q-M1.1-01 | B6: C1 家庭／组织与生活背景 核心信息 FGD：可用 IHV：可用 | C6: 建立消费者本人、家庭与日常生活背景，作为后续用车场景的开场信息。 | D6: 车主：请简单介绍您的日常工作、共同生活的人，以及目前的生活安排。 意向者：请简单介绍您的日常工作、共同生活的人，以及目前的生活安排。 | E6: 1. 家庭成员年龄段与照护责任 2. 只记录与用车有关的信息，不要求透露不愿提供的隐私 | F6: 按研究目的选用；有实际经历先谈经历，设想单独记录。 原追问3条：在“原追问审阅”按题卡编号筛选；详情保留在该表，不能把全部追问逐项念出。 | G6: 按审阅意见删除商务/组织版本，只保留消费者本人开场。 原编号题：9条；在“原题映射”按本题编号检索。 | H6: 已按意见修改 | I6: 商务/组织是2B
A7: Q-M1.1-02 | B7: C1 家庭／组织与生活背景 按需选择 FGD：可用 IHV：可用 | C7: 开场建立生活与用车背景。识别生活阶段、照护与工作背景，为目标人群和出行需求分组。 不把背景描述单独解释为市场人群占比。 | D7: 车主：平时哪些兴趣或活动最占用您的时间？最近一次是怎么安排出行的？ 意向者：平时哪些兴趣或活动最占用您的时间？最近一次是怎么安排出行的？ | E7: 1. 带了什么人和物品 2. 是否需要接送、装载或远行 3. 哪些活动想参加却受出行条件限制 | F7: 按研究目的选用；有实际经历先谈经历，设想单独记录。 原追问1条：在“原追问审阅”按题卡编号筛选；详情保留在该表，不能把全部追问逐项念出。 | G7: 2C用户本人提纲：按生活背景—经历—选择—方案的顺序呈现。保留研究任务，按对象区分问法；同义主问合并，细节保留为按条件追问。 原编号题：4条；在“原题映射”按本题编号检索。 | H7: 同意
A8: Q-M1.1-04 | B8: C1 家庭／组织与生活背景 按需选择 FGD：可用 IHV：可用 | C8: 开场建立生活与用车背景。识别生活阶段、照护与工作背景，为目标人群和出行需求分组。 不把背景描述单独解释为市场人群占比。 | D8: 车主：未来三到五年，您预计生活或工作会有哪些变化，可能改变出行需要？ 意向者：未来三到五年，您预计生活或工作会有哪些变化，可能改变出行需要？ | E8: 1. 新增照护或工作责任 2. 居住变化 3. 哪些已经确定，哪些只是设想 | F8: 按研究目的选用；有实际经历先谈经历，设想单独记录。 原追问0条：在“原追问审阅”按题卡编号筛选；详情保留在该表，不能把全部追问逐项念出。 | G8: 2C用户本人提纲：按生活背景—经历—选择—方案的顺序呈现。保留研究任务，按对象区分问法；同义主问合并，细节保留为按条件追问。 原编号题：1条；在“原题映射”按本题编号检索。 | H8: 同意
A9: Q-M1.1-05 | B9: C1 家庭／组织与生活背景 按需选择 FGD：可用 IHV：可用 | C9: 开场建立生活与用车背景。识别生活阶段、照护与工作背景，为目标人群和出行需求分组。 不把背景描述单独解释为市场人群占比。 | D9: 车主：请介绍您在组织中的职责，以及这次公务或营运用车涉及的业务。 意向者：请介绍您在组织中的职责，以及这次公务或营运用车涉及的业务。 | E9: 1. 组织规模和服务对象 2. 车辆承担的工作 3. 本人参与使用、采购还是审批 | F9: 实际涉及公务、营运或机构采购；不因价格或级别推定商务用途。 原追问1条：在“原追问审阅”按题卡编号筛选；详情保留在该表，不能把全部追问逐项念出。 | G9: 2C用户本人提纲：按生活背景—经历—选择—方案的顺序呈现。保留研究任务，按对象区分问法；同义主问合并，细节保留为按条件追问。 原编号题：1条；在“原题映射”按本题编号检索。 | H9: 同意
A10: Q-M1.2-01 | B10: C1 车辆组合与分工 核心信息 FGD：可用 IHV：可用 | C10: 开场建立生活与用车背景。识别车辆组合与替代关系，明确新车承担的任务。 不把背景描述单独解释为市场人群占比。 | D10: 车主：目前家庭或组织有哪些车辆？各自负责什么出行任务？ 意向者：目前家庭有哪些车辆或交通方式？未来新增车辆希望补足什么任务？ | E10: 1. 车型、动力、购买时间 2. 没有车时使用什么交通方式 3. 是否有重复或无法覆盖的任务 | F10: 按研究目的选用；有实际经历先谈经历，设想单独记录。 原追问5条：在“原追问审阅”按题卡编号筛选；详情保留在该表，不能把全部追问逐项念出。 | G10: 2C用户本人提纲：按生活背景—经历—选择—方案的顺序呈现。保留研究任务，按对象区分问法；同义主问合并，细节保留为按条件追问。 原编号题：5条；在“原题映射”按本题编号检索。 | H10: 同意
A11: Q-M1.2-02 | B11: C1 车辆组合与分工 按需选择 FGD：可用 IHV：可用 | C11: 开场建立生活与用车背景。识别车辆组合与替代关系，明确新车承担的任务。 不把背景描述单独解释为市场人群占比。 | D11: 车主：回顾之前使用过的车辆，为什么发生了这些变化？ 意向者：过去家庭或您自己使用的车辆、交通方式发生过哪些变化？为什么？ | E11: 1. 首购、增购还是替换 2. 保留或淘汰原因 3. 不是追问所有车辆履历 | F11: 按研究目的选用；有实际经历先谈经历，设想单独记录。 原追问3条：在“原追问审阅”按题卡编号筛选；详情保留在该表，不能把全部追问逐项念出。 | G11: 2C用户本人提纲：按生活背景—经历—选择—方案的顺序呈现。保留研究任务，按对象区分问法；同义主问合并，细节保留为按条件追问。 原编号题：3条；在“原题映射”按本题编号检索。 | H11: 同意
A12: Q-M1.2-03 | B12: C1 车辆组合与分工 按需选择 FGD：可用 IHV：可用 | C12: 开场建立生活与用车背景。识别车辆组合与替代关系，明确新车承担的任务。 不把背景描述单独解释为市场人群占比。 | D12: 车主：如果增加或更换一辆车，现有车辆和其他交通方式会如何分工？ 意向者：如果增加或更换一辆车，现有车辆和其他交通方式会如何分工？ | E12: 1. 哪些任务会转移 2. 是否减少其他车辆 3. 工作与私人用途如何协调 | F12: 按研究目的选用；有实际经历先谈经历，设想单独记录。 原追问1条：在“原追问审阅”按题卡编号筛选；详情保留在该表，不能把全部追问逐项念出。 | G12: 2C用户本人提纲：按生活背景—经历—选择—方案的顺序呈现。保留研究任务，按对象区分问法；同义主问合并，细节保留为按条件追问。 原编号题：1条；在“原题映射”按本题编号检索。 | H12: 同意
A13: Q-M1.3-01 | B13: C1 使用者、乘员与决策角色 核心信息 FGD：可用 IHV：可用 | C13: 开场建立生活与用车背景。区分驾驶、乘坐、付款和决策角色，支持座位布局与决策沟通。 不把背景描述单独解释为市场人群占比。 | D13: 车主：平时谁负责驾驶，谁主要乘坐？不同出行任务会换人吗？ 意向者：平时谁负责驾驶，谁主要乘坐？不同出行任务会换人吗？ | E13: 1. 驾驶者与主要乘员是否同一人 2. 家人、同事、专职司机的分工 3. 谁很少开但经常坐 | F13: 按研究目的选用；有实际经历先谈经历，设想单独记录。 原追问5条：在“原追问审阅”按题卡编号筛选；详情保留在该表，不能把全部追问逐项念出。 | G13: 2C用户本人提纲：按生活背景—经历—选择—方案的顺序呈现。保留研究任务，按对象区分问法；同义主问合并，细节保留为按条件追问。 原编号题：7条；在“原题映射”按本题编号检索。 | H13: 同意
A14: Q-M1.3-02 | B14: C1 使用者、乘员与决策角色 按需选择 FGD：可用 IHV：可用 | C14: 开场建立生活与用车背景。区分驾驶、乘坐、付款和决策角色，支持座位布局与决策沟通。 不把背景描述单独解释为市场人群占比。 | D14: 车主：通常有哪些人一起出行，他们如何安排座位？ 意向者：通常有哪些人一起出行，他们如何安排座位？ | E14: 1. 人数、频次、儿童座椅或行动便利需求 2. 谁决定座位 3. 满员与日常的差别 | F14: 按研究目的选用；有实际经历先谈经历，设想单独记录。 原追问4条：在“原追问审阅”按题卡编号筛选；详情保留在该表，不能把全部追问逐项念出。 | G14: 2C用户本人提纲：按生活背景—经历—选择—方案的顺序呈现。保留研究任务，按对象区分问法；同义主问合并，细节保留为按条件追问。 原编号题：7条；在“原题映射”按本题编号检索。 | H14: 同意
A15: Q-M1.3-03 | B15: C1 使用者、乘员与决策角色 按需选择 FGD：可用 IHV：可用 | C15: 开场建立生活与用车背景。区分驾驶、乘坐、付款和决策角色，支持座位布局与决策沟通。 不把背景描述单独解释为市场人群占比。 | D15: 车主：选车、付款和最终决定分别由谁负责？ 意向者：选车、付款和最终决定分别由谁负责？ | E15: 1. 信息搜集者、影响者、否决者 2. 女性或长辈影响力按实际角色问，不预设差异 | F15: 按研究目的选用；有实际经历先谈经历，设想单独记录。 原追问7条：在“原追问审阅”按题卡编号筛选；详情保留在该表，不能把全部追问逐项念出。 | G15: 2C用户本人提纲：按生活背景—经历—选择—方案的顺序呈现。保留研究任务，按对象区分问法；同义主问合并，细节保留为按条件追问。 原编号题：9条；在“原题映射”按本题编号检索。 | H15: 同意
A16: Q-M1.3-04 | B16: C1 使用者、乘员与决策角色 按需选择 FGD：可用 IHV：可用 | C16: 开场建立生活与用车背景。区分驾驶、乘坐、付款和决策角色，支持座位布局与决策沟通。 不把背景描述单独解释为市场人群占比。 | D16: 车主：请还原一次车辆采购的审批过程。 意向者：请还原一次车辆采购的审批过程。 | E16: 1. 需求提出、预算、试用、审批、签单 2. 司机和乘员意见如何进入决策 3. 采购数量及节奏 | F16: 实际涉及公务、营运或机构采购；不因价格或级别推定商务用途。 原追问3条：在“原追问审阅”按题卡编号筛选；详情保留在该表，不能把全部追问逐项念出。 | G16: 2C用户本人提纲：按生活背景—经历—选择—方案的顺序呈现。保留研究任务，按对象区分问法；同义主问合并，细节保留为按条件追问。 原编号题：1条；在“原题映射”按本题编号检索。 | H16: 同意 | I16: 这个是采购吧，商务
A17: Q-M1.4-01 | B17: C1 品类意义与理想形象 按需选择 FGD：可用 IHV：可用 | C17: 开场建立生活与用车背景。理解品类意义、理想形象及社会评价，为定位提供依据。 不把背景描述单独解释为市场人群占比。 | D17: 车主：在您看来，这类车适合什么人、用来做什么？ 意向者：在您看来，这类车适合什么人、用来做什么？ | E17: 1. 与其他车身类别的区别 2. 功能、身份、社交含义 3. 先自由描述，不给褒贬标签 | F17: 按研究目的选用；有实际经历先谈经历，设想单独记录。 原追问5条：在“原追问审阅”按题卡编号筛选；详情保留在该表，不能把全部追问逐项念出。 | G17: 2C用户本人提纲：按生活背景—经历—选择—方案的顺序呈现。保留研究任务，按对象区分问法；同义主问合并，细节保留为按条件追问。 原编号题：3条；在“原题映射”按本题编号检索。 | H17: 同意
A18: Q-M1.4-02 | B18: C1 品类意义与理想形象 按需选择 FGD：可用 IHV：可用 | C18: 开场建立生活与用车背景。理解品类意义、理想形象及社会评价，为定位提供依据。 不把背景描述单独解释为市场人群占比。 | D18: 车主：如果用三个词描述适合您的理想车辆，您会选什么？ 意向者：如果用三个词描述适合您的理想车辆，您会选什么？ | E18: 1. 每个词对应一个真实场景 2. 只能保留一个时如何选 3. 家用与商务标准有何不同 | F18: 按研究目的选用；有实际经历先谈经历，设想单独记录。 原追问4条：在“原追问审阅”按题卡编号筛选；详情保留在该表，不能把全部追问逐项念出。 | G18: 2C用户本人提纲：按生活背景—经历—选择—方案的顺序呈现。保留研究任务，按对象区分问法；同义主问合并，细节保留为按条件追问。 原编号题：4条；在“原题映射”按本题编号检索。 | H18: 同意
A19: Q-M1.4-03 | B19: C1 品类意义与理想形象 按需选择 FGD：可用 IHV：可用 | C19: 开场建立生活与用车背景。理解品类意义、理想形象及社会评价，为定位提供依据。 不把背景描述单独解释为市场人群占比。 | D19: 车主：身边的人怎样看待这类车？哪些看法实际影响过您？ 意向者：身边的人怎样看待这类车？哪些看法实际影响过您？ | E19: 1. 亲身接触与听说区分 2. 圈层认可或顾虑 3. 是否改变候选或使用方式 | F19: 按研究目的选用；有实际经历先谈经历，设想单独记录。 原追问1条：在“原追问审阅”按题卡编号筛选；详情保留在该表，不能把全部追问逐项念出。 | G19: 2C用户本人提纲：按生活背景—经历—选择—方案的顺序呈现。保留研究任务，按对象区分问法；同义主问合并，细节保留为按条件追问。 原编号题：5条；在“原题映射”按本题编号检索。 | H19: 同意

Sheet 2C-02 场景与体验
A2: 2C-02 场景与体验
A3: 36张题卡。2C：消费者本人及家庭的真实经历。黄色列供你填写；核心信息已回答就不重复问。
A5: 题卡编号 | B5: 子模块与适用方法 | C5: 研究目的与边界 | D5: 主问：按对象选用 | E5: 核心追问：覆盖信息 | F5: 触发条件与观察任务 | G5: 归并调整与来源 | H5: 确认状态 | I5: 你的修改意见
A6: Q-M2.1-01 | B6: C2 高频使用场景 核心信息 FGD：可用 IHV：可用 | C6: 还原出行任务组合，为样本细分、车辆角色和场景覆盖提供依据，不直接推导配置。 | D6: 车主：请回顾最近一周的出行，从一个普通工作日开始讲起。 意向者：请回顾最近一周您实际怎样出行，包括使用其他车辆或交通方式的情况。 | E6: 1. 出行目的、交通方式、同行者及物品 2. 工作日与休息日差异；这一周是否典型 3. 购车前后变化或未来计划另列，说明依据 | F6: 按研究目的选用；有实际经历先谈经历，设想单独记录。 观察/活动：先还原实际出行，未来预期另列。FGD可个人先填时间线再讨论；IHV结合实际观察核对。 原追问4条：在“原追问审阅”按题卡编号筛选；详情保留在该表，不能把全部追问逐项念出。 | G6: 2C用户本人提纲：按生活背景—经历—选择—方案的顺序呈现。采用已讨论的M2样板；事实与设想分开，允许无困难，观察与产品方案分别执行。 原编号题：7条；在“原题映射”按本题编号检索。 | H6: 同意
A7: Q-M2.1-02 | B7: C2 高频使用场景 按需选择 FGD：可用 IHV：可用 | C7: 识别高频任务的强度与约束；与低频关键任务分开，支持场景优先级判断。 | D7: 车主：刚才这些出行中，哪一种发生最多？请具体讲一次。 意向者：刚才这些实际出行中，哪一种发生最多？ | E7: 1. 一周频次、单次里程及时长的范围 2. 估计值或记录值，堵车等造成的差异 3. 若未来用途不同，另记预计频次及依据 | F7: 按研究目的选用；有实际经历先谈经历，设想单独记录。 观察/活动：先还原实际出行，未来预期另列。FGD可个人先填时间线再讨论；IHV结合实际观察核对。 原追问5条：在“原追问审阅”按题卡编号筛选；详情保留在该表，不能把全部追问逐项念出。 | G7: 2C用户本人提纲：按生活背景—经历—选择—方案的顺序呈现。采用已讨论的M2样板；事实与设想分开，允许无困难，观察与产品方案分别执行。 原编号题：7条；在“原题映射”按本题编号检索。 | H7: 同意
A8: Q-M2.1-03 | B8: C2 高频使用场景 按需选择 FGD：可用 IHV：可用 | C8: 还原日常出行及频率，为高频场景和任务优先级提供证据。 | D8: 车主：车辆是否同时承担家庭、工作或营运任务？请各举一次。 意向者：车辆是否同时承担家庭、工作或营运任务？请各举一次。 | E8: 1. 任务冲突如何解决 2. 是否需要临时清理或调整座位 3. 主要与次要用途 | F8: 按研究目的选用；有实际经历先谈经历，设想单独记录。 原追问2条：在“原追问审阅”按题卡编号筛选；详情保留在该表，不能把全部追问逐项念出。 | G8: 2C用户本人提纲：按生活背景—经历—选择—方案的顺序呈现。保留研究任务，按对象区分问法；同义主问合并，细节保留为按条件追问。 原编号题：2条；在“原题映射”按本题编号检索。 | H8: 同意
A9: Q-M2.2-01 | B9: C2 关键与极端场景 核心信息 FGD：可用 IHV：可用 | C9: 识别低频但后果重大的任务，不以频次替代重要性。 | D9: 车主：有没有某次出行虽然不常发生，但对您特别重要？如果有，请讲讲。 意向者：有没有某次真实出行虽然不常发生，但对您特别重要？未来购车需要保留哪些能力？ | E9: 1. 具体任务、人员和时间压力 2. 最担心的后果 3. 与最高频场景分别记录 | F9: 按研究目的选用；有实际经历先谈经历，设想单独记录。 原追问1条：在“原追问审阅”按题卡编号筛选；详情保留在该表，不能把全部追问逐项念出。 | G9: 2C用户本人提纲：按生活背景—经历—选择—方案的顺序呈现。保留研究任务，按对象区分问法；同义主问合并，细节保留为按条件追问。 原编号题：3条；在“原题映射”按本题编号检索。 | H9: 同意
A10: Q-M2.2-02 | B10: C2 关键与极端场景 按需选择 FGD：可用 IHV：可用 | C10: 识别低频但后果重大的任务，不以频次替代重要性。 | D10: 车主：请回忆最近一次多人一起出行，完整讲讲从出发到结束的过程。 意向者：请回忆最近一次多人一起出行，完整讲讲从出发到结束的过程。 | E10: 1. 座位、行李、途中活动 2. 最顺利与最困难的环节 3. 原意向题先问真实经历再谈期待 | F10: 按研究目的选用；有实际经历先谈经历，设想单独记录。 原追问3条：在“原追问审阅”按题卡编号筛选；详情保留在该表，不能把全部追问逐项念出。 | G10: 2C用户本人提纲：按生活背景—经历—选择—方案的顺序呈现。保留研究任务，按对象区分问法；同义主问合并，细节保留为按条件追问。 原编号题：8条；在“原题映射”按本题编号检索。 | H10: 同意
A11: Q-M2.2-03 | B11: C2 关键与极端场景 按需选择 FGD：可用 IHV：可用 | C11: 识别低频但后果重大的任务，不以频次替代重要性。 | D11: 车主：您把什么样的行程算作长途？最近一次是如何计划和完成的？ 意向者：您把什么样的行程算作长途？最近一次是如何计划和完成的？ | E11: 1. 休息、补能、乘员活动 2. 是否改用别的交通方式 3. 有跨境经历再问通关和补能差异 | F11: 按研究目的选用；有实际经历先谈经历，设想单独记录。 【受访者确有跨境出行】通关、地图、网络、保险或补能是否改变行程安排？ 原追问5条：在“原追问审阅”按题卡编号筛选；详情保留在该表，不能把全部追问逐项念出。 | G11: 2C用户本人提纲：按生活背景—经历—选择—方案的顺序呈现。保留研究任务，按对象区分问法；同义主问合并，细节保留为按条件追问。 原编号题：3条；在“原题映射”按本题编号检索。 | H11: 同意
A12: Q-M2.2-04 | B12: C2 关键与极端场景 按需选择 FGD：可用 IHV：可用 | C12: 识别低频但后果重大的任务，不以频次替代重要性。 | D12: 车主：是否有过车辆不可用而改变行程的经历？如果有，请还原一次。 意向者：是否有过交通工具不可用而改变行程的经历？您当时怎样处理？ | E12: 1. 替代交通、额外费用、工作或接待损失 2. 恢复所需时间 3. 没有经历时记录无经历 | F12: 按研究目的选用；有实际经历先谈经历，设想单独记录。 原追问1条：在“原追问审阅”按题卡编号筛选；详情保留在该表，不能把全部追问逐项念出。 | G12: 2C用户本人提纲：按生活背景—经历—选择—方案的顺序呈现。保留研究任务，按对象区分问法；同义主问合并，细节保留为按条件追问。 原编号题：1条；在“原题映射”按本题编号检索。 | H12: 同意
A13: Q-M2.3-01 | B13: C2 乘员与装载 核心信息 FGD：可用 IHV：可用 | C13: 识别人、物和座椅之间的真实取舍，支持储物空间、装卸便利与座椅灵活性需求定义。 | D13: 车主：请讲最近一次带较多物品出行的经历，当时怎样安排人和物？ 意向者：请讲最近一次实际搬运或携带较多物品的经历，您使用什么交通方式，怎样完成？ | E13: 1. 物品形态/数量、同行人数、座椅状态 2. 装卸步骤、固定方式、装不下时的办法和代价 3. 频次；不是每位受访者都需回忆最大物品 | F13: 按研究目的选用；有实际经历先谈经历，设想单独记录。 【家用、有儿童或照护任务】儿童用品、推车或辅助器具如何装载？人员与物品冲突时怎样处理？ 【商务或营运】礼品、样品、展品或设备如何运输？包装与保管是否有特殊要求？ 观察/活动：IHV取得许可后，请演示日常装载或用现有物品说明；婴儿车仅在实际使用且物品可用时演示，不要求购买/搬来。概念评价另接M5，示卡编号不写死。 原追问5条：在“原追问审阅”按题卡编号筛选；详情保留在该表，不能把全部追问逐项念出。 | G13: 2C用户本人提纲：按生活背景—经历—选择—方案的顺序呈现。采用已讨论的M2样板；事实与设想分开，允许无困难，观察与产品方案分别执行。 原编号题：8条；在“原题映射”按本题编号检索。 | H13: 同意
A14: Q-M2.3-02 | B14: C2 乘员与装载 按需选择 FGD：可用 IHV：可用 | C14: 识别不同乘员进出车辆的操作障碍，为门开口、台阶、通道和座椅布局提供需求依据。 | D14: 车主：请回顾一次不同乘员上下车的过程，他们分别怎样进入和离开座位？ 意向者：请回顾您实际乘坐过的车辆，您和同行者怎样上下车？有哪些方便或不方便的地方？ | E14: 1. 仅对实际相关乘员问具体操作和是否需协助 2. 第三排题仅在实际车辆有第三排或项目测试第三排时展开 3. 先记录动作，再问本人感受；未在场乘员反馈标明转述 | F14: 按研究目的选用；有实际经历先谈经历，设想单独记录。 观察/活动：IHV在车辆静止且参与者愿意时观察；不要求儿童/行动不便者为测试重复困难动作。无实车时记录叙述证据，不声称实测。 原追问0条：在“原追问审阅”按题卡编号筛选；详情保留在该表，不能把全部追问逐项念出。 | G14: 2C用户本人提纲：按生活背景—经历—选择—方案的顺序呈现。采用已讨论的M2样板；事实与设想分开，允许无困难，观察与产品方案分别执行。 原编号题：1条；在“原题映射”按本题编号检索。 | H14: 同意
A15: Q-M2.3-03 | B15: C2 乘员与装载 按需选择 FGD：可用 IHV：可用 | C15: 识别人、物、座位与上下车操作的约束，支持空间需求定义。 | D15: 车主：您乘坐或驾驶时，什么样的坐姿最合适？ 意向者：在您实际驾驶或乘坐过的车辆中，怎样的坐姿适合您？请用具体体验说明。 | E15: 1. 视野、上下车、长途舒适性 2. 高低坐姿分别有什么体验 3. 驾驶与乘坐分开 | F15: 按研究目的选用；有实际经历先谈经历，设想单独记录。 原追问0条：在“原追问审阅”按题卡编号筛选；详情保留在该表，不能把全部追问逐项念出。 | G15: 2C用户本人提纲：按生活背景—经历—选择—方案的顺序呈现。保留研究任务，按对象区分问法；同义主问合并，细节保留为按条件追问。 原编号题：3条；在“原题映射”按本题编号检索。 | H15: 同意
A16: Q-M2.4-01 | B16: C2 停车、道路与气候 核心信息 FGD：可用 IHV：可用 | C16: 识别停车与进出车位的环境限制，支持外廓尺寸、转弯与开门空间需求；不预设大车必然不便。 | D16: 车主：您经常在哪里停车？请选一个常用地点，讲讲停车和离开的过程。 意向者：您目前出行涉及哪些停车安排？未来购车可用的停车地点，哪些已确认，哪些还不确定？ | E16: 1. 车位、通道、限高、转弯、开门与收费/寻找时间 2. 有困难再还原事件、后果与处理；允许顺利无困难 3. 尺寸实测、标牌、口述估计分开；购车影响另接M3.4 | F16: 按研究目的选用；有实际经历先谈经历，设想单独记录。 观察/活动：IHV取得许可后观察/测量；不为了研究驾驶车辆验证极限。当前停车条件与未来车型适配判断分开。 原追问7条：在“原追问审阅”按题卡编号筛选；详情保留在该表，不能把全部追问逐项念出。 | G16: 2C用户本人提纲：按生活背景—经历—选择—方案的顺序呈现。采用已讨论的M2样板；事实与设想分开，允许无困难，观察与产品方案分别执行。 原编号题：7条；在“原题映射”按本题编号检索。 | H16: 同意
A17: Q-M2.4-02 | B17: C2 停车、道路与气候 按需选择 FGD：可用 IHV：可用 | C17: 识别个人实际暴露的道路、停车与气候条件，支持适配需求。 | D17: 车主：常走的道路是什么样的？哪些路段最影响行驶和乘坐体验？ 意向者：常走的道路是什么样的？哪些路段最影响行驶和乘坐体验？ | E17: 1. 城市、高速、减速带、非铺装及坡道 2. 频次和具体问题 3. 不因道路良好跳过舒适性 | F17: 按研究目的选用；有实际经历先谈经历，设想单独记录。 原追问6条：在“原追问审阅”按题卡编号筛选；详情保留在该表，不能把全部追问逐项念出。 | G17: 2C用户本人提纲：按生活背景—经历—选择—方案的顺序呈现。保留研究任务，按对象区分问法；同义主问合并，细节保留为按条件追问。 原编号题：7条；在“原题映射”按本题编号检索。 | H17: 同意
... A26: Q-M2.5-05 | B26: C2 现有座舱与智驾使用 按需选择 FGD：可用 IHV：可用 | C26: 还原座舱操作任务、步骤和失败点，为交互改进提供依据。 | D26: 车主：车内不同乘员通常使用什么内容和设备？ 意向者：车内不同乘员通常使用什么内容和设备？ | E26: 1. 原装与自行安装 2. 前后排差异 3. 视频、音乐、工作等真实任务 | F26: 按研究目的选用；有实际经历先谈经历，设想单独记录。 【商务接待】后排乘员希望休息、工作还是娱乐？提供这些功能会不会干扰驾驶或交流？ 原追问8条：在“原追问审阅”按题卡编号筛选；详情保留在该表，不能把全部追问逐项念出。 | G26: 2C用户本人提纲：按生活背景—经历—选择—方案的顺序呈现。保留研究任务，按对象区分问法；同义主问合并，细节保留为按条件追问。 原编号题：8条；在“原题映射”按本题编号检索。 | H26: 同意
A27: Q-M2.5-06 | B27: C2 现有座舱与智驾使用 按需选择 FGD：可用 IHV：可用 | C27: 还原座舱操作任务、步骤和失败点，为交互改进提供依据。 | D27: 车主：车内哪些声音、灯光、材质或交互会让您觉得舒服、有氛围？哪些会让您不适或分心？ 意向者：车内哪些声音、灯光、材质或交互会让您觉得舒服、有氛围？哪些会让您不适或分心？ | E27: 1. 现有解决方式 2. 车内场景、使用频率 3. 哪些任务不需要上车 | F27: 按研究目的选用；有实际经历先谈经历，设想单独记录。 原追问4条：在“原追问审阅”按题卡编号筛选；详情保留在该表，不能把全部追问逐项念出。 | G27: 按审阅意见把“汽车氛围”改为可感知的声音、灯光、材质和交互。 原编号题：3条；在“原题映射”按本题编号检索。 | H27: 已按意见修改 | I27: 题目看不懂
A28: Q-M2.5-07 | B28: C2 现有座舱与智驾使用 按需选择 FGD：可用 IHV：可用 | C28: 还原座舱操作任务、步骤和失败点，为交互改进提供依据。 | D28: 车主：多人同时使用车内功能时，发生过怎样的情况？ 意向者：在实际乘坐经历中，多人同时使用车内功能时发生过什么？如果没有经历，未来需求另记。 | E28: 1. 音源、屏幕、温度或操作冲突 2. 最明显的事件 3. 如何协调 | F28: 按研究目的选用；有实际经历先谈经历，设想单独记录。 原追问3条：在“原追问审阅”按题卡编号筛选；详情保留在该表，不能把全部追问逐项念出。 | G28: 2C用户本人提纲：按生活背景—经历—选择—方案的顺序呈现。保留研究任务，按对象区分问法；同义主问合并，细节保留为按条件追问。 原编号题：4条；在“原题映射”按本题编号检索。 | H28: 同意
A29: Q-M2.5-08 | B29: C2 现有座舱与智驾使用 按需选择 FGD：可用 IHV：可用 | C29: 还原座舱操作任务、步骤和失败点，为交互改进提供依据。 | D29: 车主：哪些人使用现有车内系统时比较容易或困难？ 意向者：哪些人使用现有车内系统时比较容易或困难？ | E29: 1. 具体任务和失败步骤 2. 与经验、语言、身体条件的关系 3. 不预设女性或老人必然困难 | F29: 按研究目的选用；有实际经历先谈经历，设想单独记录。 原追问2条：在“原追问审阅”按题卡编号筛选；详情保留在该表，不能把全部追问逐项念出。 | G29: 2C用户本人提纲：按生活背景—经历—选择—方案的顺序呈现。保留研究任务，按对象区分问法；同义主问合并，细节保留为按条件追问。 原编号题：2条；在“原题映射”按本题编号检索。 | H29: 同意
A30: Q-M2.6-01 | B30: C2 痛点后果与替代办法 按需选择 FGD：可用 IHV：可用 | C30: 辨别满意来源、困难后果和替代办法，为需求排序提供依据。 | D30: 车主：回顾目前的出行或用车体验，最满意和最不满意的分别是什么？ 意向者：回顾目前的出行或用车体验，最满意和最不满意的分别是什么？ | E30: 1. 各举具体事件 2. 是否影响继续使用或下次选择 3. 先自发回答再补提示 | F30: 按研究目的选用；有实际经历先谈经历，设想单独记录。 原追问1条：在“原追问审阅”按题卡编号筛选；详情保留在该表，不能把全部追问逐项念出。 | G30: 2C用户本人提纲：按生活背景—经历—选择—方案的顺序呈现。保留研究任务，按对象区分问法；同义主问合并，细节保留为按条件追问。 原编号题：3条；在“原题映射”按本题编号检索。 | H30: 同意
A31: Q-M2.6-02 | B31: C2 痛点后果与替代办法 核心信息 FGD：可用 IHV：可用 | C31: 识别未满足需求的发生机制、影响及替代办法，为需求优先级提供证据，不把抱怨数量当市场发生率。 | D31: 车主：回顾刚才的出行，有没有您希望改善的地方？如果有，请选一件具体讲讲。 意向者：在您目前真实的出行中，有没有希望改善的地方？请用一次实际经历说明。 | E31: 1. 触发条件、发生频次、受影响者 2. 时间、费用、任务或感受上的后果 3. 已经采用的办法、成本、仍未解决的部分；什么改变才算解决 | F31: 按研究目的选用；有实际经历先谈经历，设想单独记录。 观察/活动：不强迫每人给痛点；使用困难、成交异议和售后处理分别标注。经销商只谈购买犹豫时转M3，不当作真实使用体验。 原追问4条：在“原追问审阅”按题卡编号筛选；详情保留在该表，不能把全部追问逐项念出。 | G31: 2C用户本人提纲：按生活背景—经历—选择—方案的顺序呈现。采用已讨论的M2样板；事实与设想分开，允许无困难，观察与产品方案分别执行。 原编号题：2条；在“原题映射”按本题编号检索。 | H31: 同意
A32: Q-M2.6-03 | B32: C2 痛点后果与替代办法 按需选择 FGD：可用 IHV：可用 | C32: 辨别满意来源、困难后果和替代办法，为需求排序提供依据。 | D32: 车主：车内操作有没有您希望改善的地方？如果有，请还原最近一次。 意向者：在实际体验过的车内操作中，有没有希望改善的地方？如果有，请还原一次。 | E32: 1. 步骤与结果 2. 替代方式 3. 达到什么水平就足够 4. 若前面已讲则核验不重问 | F32: 按研究目的选用；有实际经历先谈经历，设想单独记录。 原追问3条：在“原追问审阅”按题卡编号筛选；详情保留在该表，不能把全部追问逐项念出。 | G32: 2C用户本人提纲：按生活背景—经历—选择—方案的顺序呈现。保留研究任务，按对象区分问法；同义主问合并，细节保留为按条件追问。 原编号题：4条；在“原题映射”按本题编号检索。 | H32: 同意
A33: Q-M2.6-04 | B33: C2 痛点后果与替代办法 按需选择 FGD：可用 IHV：可用 | C33: 辨别满意来源、困难后果和替代办法，为需求排序提供依据。 | D33: 车主：现在使用的车辆或出行安排中，哪一项最让您觉得值得？ 意向者：现在使用的车辆或出行安排中，哪一项最让您觉得值得？ | E33: 1. 为什么值得 2. 经常使用还是关键时刻有用 3. 替代它需要什么 | F33: 按研究目的选用；有实际经历先谈经历，设想单独记录。 原追问0条：在“原追问审阅”按题卡编号筛选；详情保留在该表，不能把全部追问逐项念出。 | G33: 2C用户本人提纲：按生活背景—经历—选择—方案的顺序呈现。保留研究任务，按对象区分问法；同义主问合并，细节保留为按条件追问。 原编号题：1条；在“原题映射”按本题编号检索。 | H33: 同意
A34: Q-M2.7-01 | B34: C2 持有成本与服务体验 按需选择 FGD：可用 IHV：可用 | C34: 识别持有支出与服务负担，为总成本和服务方案提供依据。 | D34: 车主：请估算最近一个月或一年的用车支出，并说明计算口径。 意向者：请估算目前出行的费用，并说明未来购车后哪些支出最在意。 | E34: 1. 选择一个明确期间，按能源、停车、保险、保养维修等分别估算 2. 记录金额、币种、支付周期及账单或估计来源 3. 首购意向者记录当前交通支出，未来用车预算另列；不默认电车更省 | F34: 按研究目的选用；有实际经历先谈经历，设想单独记录。 原追问0条：在“原追问审阅”按题卡编号筛选；详情保留在该表，不能把全部追问逐项念出。 | G34: 2C用户本人提纲：按生活背景—经历—选择—方案的顺序呈现。保留研究任务，按对象区分问法；同义主问合并，细节保留为按条件追问。 原编号题：3条；在“原题映射”按本题编号检索。 | H34: 同意
A35: Q-M2.7-02 | B35: C2 持有成本与服务体验 按需选择 FGD：可用 IHV：可用 | C35: 识别持有支出与服务负担，为总成本和服务方案提供依据。 | D35: 车主：您实际比较过不同用车方案的花费吗？结果如何？ 意向者：您实际比较过不同交通或用车方案的花费吗？如果有，请说明口径；未来预计支出另外记录。 | E35: 1. 同里程与同期间口径 2. 是否包含车价、利息和折旧 3. 没有比较则不要求编节省数 | F35: 按研究目的选用；有实际经历先谈经历，设想单独记录。 原追问3条：在“原追问审阅”按题卡编号筛选；详情保留在该表，不能把全部追问逐项念出。 | G35: 2C用户本人提纲：按生活背景—经历—选择—方案的顺序呈现。保留研究任务，按对象区分问法；同义主问合并，细节保留为按条件追问。 原编号题：2条；在“原题映射”按本题编号检索。 | H35: 同意
A36: Q-M2.7-03 | B36: C2 持有成本与服务体验 按需选择 FGD：可用 IHV：可用 | C36: 识别持有支出与服务负担，为总成本和服务方案提供依据。 | D36: 车主：请回顾最近一次保养或维修，从预约到取车发生了什么？ 意向者：如果您过去有车辆保养或维修经历，请举最近一次；否则，您对未来服务有什么要求？ | E36: 1. 等待、距离、费用、沟通和替代车 2. 最不能接受的环节 3. 无经历记录未知 | F36: 按研究目的选用；有实际经历先谈经历，设想单独记录。 原追问2条：在“原追问审阅”按题卡编号筛选；详情保留在该表，不能把全部追问逐项念出。 | G36: 2C用户本人提纲：按生活背景—经历—选择—方案的顺序呈现。保留研究任务，按对象区分问法；同义主问合并，细节保留为按条件追问。 原编号题：1条；在“原题映射”按本题编号检索。 | H36: 同意
A37: Q-M2.7-04 | B37: C2 持有成本与服务体验 按需选择 FGD：可用 IHV：可用 | C37: 识别持有支出与服务负担，为总成本和服务方案提供依据。 | D37: 车主：车辆使用一段时间后，哪些部位变化最明显？ | E37: 1. 内饰磨损、异响、清洁、配饰与改装 2. 对品质或残值判断的影响 | F37: 仅有对应已购车/使用经历者。 原追问1条：在“原追问审阅”按题卡编号筛选；详情保留在该表，不能把全部追问逐项念出。 | G37: 2C用户本人提纲：按生活背景—经历—选择—方案的顺序呈现。保留研究任务，按对象区分问法；同义主问合并，细节保留为按条件追问。 原编号题：2条；在“原题映射”按本题编号检索。 | H37: 同意
A38: Q-M8.1-01 | B38: C2 基础设施与能源环境 核心信息 FGD：可用 IHV：可用 | C38: 识别地区与个体基础设施差异，为动力适配提供前提条件。 | D38: 车主：您实际熟悉的区域，停车、能源或补能条件怎样影响日常出行？ 意向者：您目前能够使用或已确认的停车、能源和补能条件有哪些？哪些还不清楚？ | E38: 1. 城市内差异 2. 私人/公共设施分开 3. 本人经历、客户转述、资料分别记录 | F38: 按研究目的选用；有实际经历先谈经历，设想单独记录。 原追问3条：在“原追问审阅”按题卡编号筛选；详情保留在该表，不能把全部追问逐项念出。 | G38: 2C用户本人提纲：按生活背景—经历—选择—方案的顺序呈现。地域条件、政策与工程事实需核验；个体经历、当地资料和受访者推测分别记录。 原编号题：2条；在“原题映射”按本题编号检索。 | H38: 同意
A39: Q-M8.3-01 | B39: C2 语言与数字生态 核心信息 FGD：可用 IHV：可用 | C39: 识别语言、地图、账户及内容服务的实际任务需求。 | D39: 车主：哪些语言、地图、内容或连接服务对实际用车最重要？ 意向者：哪些语言、地图、内容或连接服务对实际用车最重要？ | E39: 1. 由受访者自发指出 2. 目前替代办法 3. 对离线、账户、支付或混合语言的要求 | F39: 按研究目的选用；有实际经历先谈经历，设想单独记录。 原追问4条：在“原追问审阅”按题卡编号筛选；详情保留在该表，不能把全部追问逐项念出。 | G39: 2C用户本人提纲：按生活背景—经历—选择—方案的顺序呈现。地域条件、政策与工程事实需核验；个体经历、当地资料和受访者推测分别记录。 原编号题：2条；在“原题映射”按本题编号检索。 | H39: 同意
A40: Q-M8.3-02 | B40: C2 语言与数字生态 按需选择 FGD：可用 IHV：可用 | C40: 识别语言、地图、账户及内容服务的实际任务需求。 | D40: 车主：现有车内系统有哪些本地化不到位的地方？ 意向者：现有车内系统有哪些本地化不到位的地方？ | E40: 1. 原词/界面/具体任务 2. 翻译、地址、单位、语音和内容 3. 不假定每个市场问题相同 | F40: 按研究目的选用；有实际经历先谈经历，设想单独记录。 原追问0条：在“原追问审阅”按题卡编号筛选；详情保留在该表，不能把全部追问逐项念出。 | G40: 2C用户本人提纲：按生活背景—经历—选择—方案的顺序呈现。地域条件、政策与工程事实需核验；个体经历、当地资料和受访者推测分别记录。 原编号题：0条；在“原题映射”按本题编号检索。 本次补充的新题。 | H40: 同意
A41: Q-M2.6-05 | B41: C2 痛点后果与替代办法 按需选择 FGD：可用 IHV：可用 | C41: 辨别满意来源、困难后果和替代办法，为需求排序提供依据。 | D41: 车主：现有车辆在使用中有哪些让您觉得不方便、费时间或需要额外处理的问题？ 意向者：现有车辆在使用中有哪些让您觉得不方便、费时间或需要额外处理的问题？ | E41: 1. 用材、气味、噪声、整洁和乘员互动的具体表现 2. 本人感受与乘客反馈分开 3. 对接待或出行结果有何影响 | F41: 按研究目的选用；有实际经历先谈经历，设想单独记录。 原追问1条：在“原追问审阅”按题卡编号筛选；详情保留在该表，不能把全部追问逐项念出。 | G41: 按审阅意见改为日常语言，避免抽象的痛点表达。 原编号题：1条；在“原题映射”按本题编号检索。 | H41: 已按意见修改 | I41: 汽车氛围有点表述不清楚

Sheet 2C-03 购买旅程与考虑因素
A2: 2C-03 购买旅程与考虑因素
A3: 23张题卡。2C：消费者本人及家庭的真实经历。黄色列供你填写；核心信息已回答就不重复问。
A5: 题卡编号 | B5: 子模块与适用方法 | C5: 研究目的与边界 | D5: 主问：按对象选用 | E5: 核心追问：覆盖信息 | F5: 触发条件与观察任务 | G5: 归并调整与来源 | H5: 确认状态 | I5: 你的修改意见
A6: Q-M3.1-01 | B6: C3 触发事件与预算 核心信息 FGD：可用 IHV：可用 | C6: 区分购车触发、预算形成与实际支出，明确需求启动条件。 | D6: 车主：您上一辆车是什么车型、用了多久？ 最初是什么事情让您产生这次买车或换车的想法？ 意向者：您目前主要使用什么车、用了多久？ 最初是什么事情让您产生这次买车或换车的想法？ | E6: 1. 生活、工作或使用条件变化 2. 首购/增购/换购 3. 触发与最终选择分开 | F6: 按研究目的选用；有实际经历先谈经历，设想单独记录。 原追问7条：在“原追问审阅”按题卡编号筛选；详情保留在该表，不能把全部追问逐项念出。 | G6: 按审阅意见补充上一辆车或当前车辆及使用时长。 原编号题：7条；在“原题映射”按本题编号检索。 | H6: 已按意见修改 | I6: 上一辆车是什么车，用了多久，这信息可能要增加
A7: Q-M3.1-02 | B7: C3 触发事件与预算 按需选择 FGD：可用 IHV：可用 | C7: 区分购车触发、预算形成与实际支出，明确需求启动条件。 | D7: 车主：购车预算是怎样定下来的？后来有过变化吗？ 意向者：目前的购车预算怎样定下来的？哪些条件可能让它变化？ | E7: 1. 谁定预算 2. 金额、币种、是否含税费 3. 上调或下调的实际原因 | F7: 按研究目的选用；有实际经历先谈经历，设想单独记录。 原追问4条：在“原追问审阅”按题卡编号筛选；详情保留在该表，不能把全部追问逐项念出。 | G7: 2C用户本人提纲：按生活背景—经历—选择—方案的顺序呈现。保留研究任务，按对象区分问法；同义主问合并，细节保留为按条件追问。 原编号题：3条；在“原题映射”按本题编号检索。 | H7: 同意
A8: Q-M3.1-03 | B8: C3 触发事件与预算 按需选择 FGD：可用 IHV：可用 | C8: 区分购车触发、预算形成与实际支出，明确需求启动条件。 | D8: 车主：当时购车的实际落地支出是多少？请说明包括哪些费用。 | E8: 1. 记录币种、成交日期、车价、税费、保险和金融费用；已含项目不重复相加 2. 预算与实际支出有哪些差异，为什么 3. 如评价是否值得，另外记录判断依据，不与金额混成一个答案 | F8: 仅有对应已购车/使用经历者。 原追问3条：在“原追问审阅”按题卡编号筛选；详情保留在该表，不能把全部追问逐项念出。 | G8: 2C用户本人提纲：按生活背景—经历—选择—方案的顺序呈现。保留研究任务，按对象区分问法；同义主问合并，细节保留为按条件追问。 原编号题：3条；在“原题映射”按本题编号检索。 | H8: 同意
A9: Q-M3.2-01 | B9: C3 信息源与候选清单 核心信息 FGD：可用 IHV：可用 | C9: 还原信息来源与候选变化，为竞争范围和触点选择提供依据。 | D9: 车主：在本次选车过程中，您考虑过哪些车型？候选清单如何变化？ 意向者：在本次选车过程中，您考虑过哪些车型？候选清单如何变化？ | E9: 1. 最初与最后名单 2. 跨车身/动力/价格带 3. 没有考虑过的不强行评价 | F9: 按研究目的选用；有实际经历先谈经历，设想单独记录。 原追问7条：在“原追问审阅”按题卡编号筛选；详情保留在该表，不能把全部追问逐项念出。 | G9: 2C用户本人提纲：按生活背景—经历—选择—方案的顺序呈现。保留研究任务，按对象区分问法；同义主问合并，细节保留为按条件追问。 原编号题：11条；在“原题映射”按本题编号检索。 | H9: 同意
A10: Q-M3.2-02 | B10: C3 信息源与候选清单 按需选择 FGD：可用 IHV：可用 | C10: 还原信息来源与候选变化，为竞争范围和触点选择提供依据。 | D10: 车主：候选清单里最优先的一款是什么？为什么？ 意向者：候选清单里最优先的一款是什么？为什么？ | E10: 1. 是否后来改变排序 2. 具体吸引点 3. 品牌与产品因素分别记录 | F10: 按研究目的选用；有实际经历先谈经历，设想单独记录。 原追问4条：在“原追问审阅”按题卡编号筛选；详情保留在该表，不能把全部追问逐项念出。 | G10: 2C用户本人提纲：按生活背景—经历—选择—方案的顺序呈现。保留研究任务，按对象区分问法；同义主问合并，细节保留为按条件追问。 原编号题：4条；在“原题映射”按本题编号检索。 | H10: 同意
A11: Q-M3.2-03 | B11: C3 信息源与候选清单 按需选择 FGD：可用 IHV：可用 | C11: 还原信息来源与候选变化，为竞争范围和触点选择提供依据。 | D11: 车主：哪些信息来源真正影响了您的选车？请讲一次影响决定的信息。 意向者：哪些信息来源真正影响了您的选车？请讲一次影响决定的信息。 | E11: 1. 主动搜索、亲友、门店或媒体 2. 接触与信任分别记录 3. AI信息如实际使用再问 | F11: 按研究目的选用；有实际经历先谈经历，设想单独记录。 原追问4条：在“原追问审阅”按题卡编号筛选；详情保留在该表，不能把全部追问逐项念出。 | G11: 2C用户本人提纲：按生活背景—经历—选择—方案的顺序呈现。保留研究任务，按对象区分问法；同义主问合并，细节保留为按条件追问。 原编号题：6条；在“原题映射”按本题编号检索。 | H11: 同意
A12: Q-M3.2-04 | B12: C3 信息源与候选清单 按需选择 FGD：可用 IHV：可用 | C12: 还原信息来源与候选变化，为竞争范围和触点选择提供依据。 | D12: 车主：对您真正了解或体验过的候选车型，优缺点分别是什么？ 意向者：对您真正了解或体验过的候选车型，优缺点分别是什么？ | E12: 1. 体验来源 2. 逐车型比较同一维度 3. 未体验仅记录印象，不当实测 | F12: 按研究目的选用；有实际经历先谈经历，设想单独记录。 原追问13条：在“原追问审阅”按题卡编号筛选；详情保留在该表，不能把全部追问逐项念出。 | G12: 2C用户本人提纲：按生活背景—经历—选择—方案的顺序呈现。保留研究任务，按对象区分问法；同义主问合并，细节保留为按条件追问。 原编号题：20条；在“原题映射”按本题编号检索。 | H12: 同意
A13: Q-M3.3-01 | B13: C3 决策链与试驾 核心信息 FGD：可用 IHV：可用 | C13: 还原决策节点和体验验证，识别流程卡点与服务改进机会。 | D13: 车主：请按时间顺序还原从产生购车想法到当前阶段的关键节点。 意向者：请按时间顺序还原从产生购车想法到当前阶段的关键节点。 | E13: 1. 开始搜索、到店、试驾、决定、下单、交车 2. 未发生节点记录计划 3. 卡在哪一步 | F13: 按研究目的选用；有实际经历先谈经历，设想单独记录。 观察/活动：画购车时间轴，标已发生节点与未来计划；让受访者自行补充，主持人只核对遗漏。 原追问8条：在“原追问审阅”按题卡编号筛选；详情保留在该表，不能把全部追问逐项念出。 | G13: 2C用户本人提纲：按生活背景—经历—选择—方案的顺序呈现。保留研究任务，按对象区分问法；同义主问合并，细节保留为按条件追问。 原编号题：10条；在“原题映射”按本题编号检索。 | H13: 同意
A14: Q-M3.3-02 | B14: C3 决策链与试驾 按需选择 FGD：可用 IHV：可用 | C14: 还原决策节点和体验验证，识别流程卡点与服务改进机会。 | D14: 车主：到店看车或试驾时，您重点验证了什么？ 意向者：到店看车或试驾时，您重点验证了什么？ | E14: 1. 谁一起参与 2. 具体区域、功能或路段 3. 是否改变原有判断 4. 没试驾则问原因 | F14: 按研究目的选用；有实际经历先谈经历，设想单独记录。 原追问4条：在“原追问审阅”按题卡编号筛选；详情保留在该表，不能把全部追问逐项念出。 | G14: 2C用户本人提纲：按生活背景—经历—选择—方案的顺序呈现。保留研究任务，按对象区分问法；同义主问合并，细节保留为按条件追问。 原编号题：11条；在“原题映射”按本题编号检索。 | H14: 同意
A15: Q-M3.3-03 | B15: C3 决策链与试驾 按需选择 FGD：可用 IHV：可用 | C15: 还原决策节点和体验验证，识别流程卡点与服务改进机会。 | D15: 车主：您是怎样选择门店或购买渠道的？ 意向者：您是怎样选择门店或购买渠道的？ | E15: 1. 距离、服务、价格、口碑和网络覆盖 2. 选中与放弃的实际原因 | F15: 按研究目的选用；有实际经历先谈经历，设想单独记录。 原追问4条：在“原追问审阅”按题卡编号筛选；详情保留在该表，不能把全部追问逐项念出。 | G15: 2C用户本人提纲：按生活背景—经历—选择—方案的顺序呈现。保留研究任务，按对象区分问法；同义主问合并，细节保留为按条件追问。 原编号题：2条；在“原题映射”按本题编号检索。 | H15: 同意
A16: Q-M3.3-04 | B16: C3 决策链与试驾 按需选择 FGD：可用 IHV：可用 | C16: 还原决策节点和体验验证，识别流程卡点与服务改进机会。 | D16: 车主：请回顾一次购车服务经历，哪些环节影响了您的决定？ 意向者：在已经发生的看车或咨询过程中，哪些服务影响了您的判断？没有发生则记录尚未到店。 | E16: 1. 销售解释、试驾、承诺兑现 2. 是否改变候选、下单时间或品牌信任 | F16: 按研究目的选用；有实际经历先谈经历，设想单独记录。 原追问2条：在“原追问审阅”按题卡编号筛选；详情保留在该表，不能把全部追问逐项念出。 | G16: 2C用户本人提纲：按生活背景—经历—选择—方案的顺序呈现。保留研究任务，按对象区分问法；同义主问合并，细节保留为按条件追问。 原编号题：1条；在“原题映射”按本题编号检索。 | H16: 同意
A17: Q-M3.4-01 | B17: C3 购车考虑因素 按需选择 FGD：可用 IHV：可用 | C17: 识别消费者选车时的考虑因素及优先级，并为后续产品取舍提供依据。 | D17: 车主：选车时您最看重哪些因素？请先自由列出，再选最重要的三项。 意向者：选车时您最看重哪些因素？请先自由列出，再选最重要的三项。 | E17: 1. 每项需要达到什么程度 2. 是否存在一票否决项 3. 不要先把全部属性读给受访者 | F17: 按研究目的选用；有实际经历先谈经历，设想单独记录。 原追问6条：在“原追问审阅”按题卡编号筛选；详情保留在该表，不能把全部追问逐项念出。 | G17: 将原有权衡题明确命名为“购车考虑因素”，便于提纲生成时直接选用。 原编号题：5条；在“原题映射”按本题编号检索。 | H17: 已按意见修改
A18: Q-M3.4-02 | B18: C3 购车考虑因素与取舍 核心信息 FGD：可用 IHV：可用 | C18: 辨别决定因素、否决条件和真实妥协，避免把口头偏好等同选择。 | D18: 车主：最终选择这辆车最关键的原因是什么？ 意向者：目前最倾向的车型是哪个？哪些理由让它排在前面，哪些条件还没确认？ | E18: 1. 与最后仍在比较的备选相比，哪项差异最终起作用 2. 区分事前最重要因素与最后促成决定的事件 3. 意向者只谈目前排序和未确认条件，不追问已成交结果 | F18: 按研究目的选用；有实际经历先谈经历，设想单独记录。 原追问6条：在“原追问审阅”按题卡编号筛选；详情保留在该表，不能把全部追问逐项念出。 | G18: 2C用户本人提纲：按生活背景—经历—选择—方案的顺序呈现。保留研究任务，按对象区分问法；同义主问合并，细节保留为按条件追问。 原编号题：11条；在“原题映射”按本题编号检索。 | H18: 同意
... A27: Q-M8.2-01 | B27: C3 补贴与政策影响 核心信息 FGD：可用 IHV：可用 | C27: 区分政策知晓、资格、实际享受和决策影响，保留地区日期及核验来源。 | D27: 车主：您知道当地有哪些购车补贴、税费减免、牌照或用车优惠？这次是否实际申请或享受过？ 意向者：您知道当地有哪些购车补贴、税费减免、牌照或用车优惠？哪些会影响您的购车考虑？ | E27: 1. 政策名称、地区、时间与核验来源 2. 知晓、符合资格、实际享受分开 | F27: 先问自发认知；只有项目组已核验当地政策名称、适用车型和有效期后，才提示具体政策。 【已核验当地政策且受访者知晓】当时是否实际申请或享受过该政策？是否改变购买时间、预算或动力选择？ 原追问11条：在“原追问审阅”按题卡编号筛选；详情保留在该表，不能把全部追问逐项念出。 | G27: 补足2C补贴问题，并防止把历史政策当作当前事实。 原编号题：5条；在“原题映射”按本题编号检索。 | H27: 已按意见修改
A28: Q-M8.2-02 | B28: C3 补贴与政策影响 按需选择 FGD：可用 IHV：可用 | C28: 区分政策知晓、资格、实际享受和决策影响，保留地区日期及核验来源。 | D28: 车主：如果补贴或税费优惠增加、减少或取消，您的购车时间、预算、动力形式或车型选择会怎样变化？ 意向者：如果补贴或税费优惠增加、减少或取消，您的购车时间、预算、动力形式或车型选择会怎样变化？ | E28: 1. 前后期间、具体订单 2. 其他影响因素 3. 没有证据则记录为推测 | F28: 仅当受访者知晓或项目已提供经核验的政策情境时触发；记录实际影响和假设反应。 原追问0条：在“原追问审阅”按题卡编号筛选；详情保留在该表，不能把全部追问逐项念出。 | G28: 按审阅意见改为明确的补贴变化情境。 原编号题：0条；在“原题映射”按本题编号检索。 本次补充的新题。 | H28: 已按意见修改 | I28: 看不懂

Sheet 2C-04 动力与补能
A2: 2C-04 动力与补能
A3: 20张题卡。2C：消费者本人及家庭的真实经历。黄色列供你填写；核心信息已回答就不重复问。
A5: 题卡编号 | B5: 子模块与适用方法 | C5: 研究目的与边界 | D5: 主问：按对象选用 | E5: 核心追问：覆盖信息 | F5: 触发条件与观察任务 | G5: 归并调整与来源 | H5: 确认状态 | I5: 你的修改意见
A6: Q-M4.1-01 | B6: C4 动力理解与选择 核心信息 FGD：可用 IHV：可用 | C6: 理解动力认知及选择条件，区分事实限制与印象顾虑。 | D6: 车主：您知道哪些汽车动力形式？对燃油、混动、插混和纯电分别有什么理解？ 意向者：您知道哪些汽车动力形式？对燃油、混动、插混和纯电分别有什么理解？ | E6: 1. 先自发理解再解释技术 2. 选车流程中先定动力还是车型 3. 允许没有明确偏好 | F6: 按研究目的选用；有实际经历先谈经历，设想单独记录。 原追问6条：在“原追问审阅”按题卡编号筛选；详情保留在该表，不能把全部追问逐项念出。 | G6: 按审阅意见先测自发认知，再进入动力选择。 原编号题：11条；在“原题映射”按本题编号检索。 | H6: 已按意见修改 | I6: 要先问他，你知道哪些动力形式
A7: Q-M4.1-02 | B7: C4 动力理解与选择 按需选择 FGD：可用 IHV：可用 | C7: 理解动力认知及选择条件，区分事实限制与印象顾虑。 | D7: 车主：哪些具体原因让您考虑或放弃某种动力形式？ 意向者：哪些具体原因让您考虑或放弃某种动力形式？ | E7: 1. 真实使用条件、成本、信任、习惯 2. 已经经历与听说的风险分开 | F7: 按研究目的选用；有实际经历先谈经历，设想单独记录。 原追问4条：在“原追问审阅”按题卡编号筛选；详情保留在该表，不能把全部追问逐项念出。 | G7: 2C用户本人提纲：按生活背景—经历—选择—方案的顺序呈现。保留研究任务，按对象区分问法；同义主问合并，细节保留为按条件追问。 原编号题：7条；在“原题映射”按本题编号检索。 | H7: 同意
A8: Q-M4.1-03 | B8: C4 动力理解与选择 按需选择 FGD：可用 IHV：可用 | C8: 理解动力认知及选择条件，区分事实限制与印象顾虑。 | D8: 车主：您如何理解增程式动力？了解清楚后有哪些接受点和顾虑？ 意向者：您如何理解增程式动力？了解清楚后有哪些接受点和顾虑？ | E8: 1. 先记录原有认知 2. 主持人使用中性的已审核说明 3. 与自身任务相关而非技术偏好问答 | F8: 按研究目的选用；有实际经历先谈经历，设想单独记录。 原追问3条：在“原追问审阅”按题卡编号筛选；详情保留在该表，不能把全部追问逐项念出。 | G8: 2C用户本人提纲：按生活背景—经历—选择—方案的顺序呈现。保留研究任务，按对象区分问法；同义主问合并，细节保留为按条件追问。 原编号题：3条；在“原题映射”按本题编号检索。 | H8: 同意
A9: Q-M4.2-01 | B9: C4 实际补能条件 核心信息 FGD：可用 IHV：可用 | C9: 还原补能流程、设施条件及成本，支持补能服务与使用条件定义。 | D9: 车主：请描述您的充电习惯：通常剩余多少电会充、多久充一次、主要在哪里充？最近一次充电是怎样的？总体方便吗？ | E9: 1. 地点、频次、起止电量、车辆停留与本人等待 2. 日常家充/公共充电比例 3. 对行程影响 | F9: 实际充电题：有BEV/PHEV/增程充电经历。 原追问4条：在“原追问审阅”按题卡编号筛选；详情保留在该表，不能把全部追问逐项念出。 | G9: 按审阅意见重组为充电时点、频率、场所、最近一次经历和便利性。 原编号题：6条；在“原题映射”按本题编号检索。 | H9: 已按意见修改 | I9: 请你描述下你充电的i习惯（20%一看到就充电），充电的频率（每天），充电的场所（家or公司）？最近一次是怎样的？。。。要重新组织下语言，总体上是否方便
A10: Q-M4.2-02 | B10: C4 实际补能条件 按需选择 FGD：可用 IHV：可用 | C10: 还原补能流程、设施条件及成本，支持补能服务与使用条件定义。 | D10: 车主：您实际使用过公共快充吗？请讲最近一次经历。 | E10: 1. 找桩、排队、可用性、支付与充电结果 2. 担忧与实际故障区分 3. 未使用则问原因 | F10: 实际充电题：有BEV/PHEV/增程充电经历。 原追问2条：在“原追问审阅”按题卡编号筛选；详情保留在该表，不能把全部追问逐项念出。 | G10: 2C用户本人提纲：按生活背景—经历—选择—方案的顺序呈现。保留研究任务，按对象区分问法；同义主问合并，细节保留为按条件追问。 原编号题：3条；在“原题映射”按本题编号检索。 | H10: 同意
A11: Q-M4.2-03 | B11: C4 实际补能条件 按需选择 FGD：可用 IHV：可用 | C11: 还原补能流程、设施条件及成本，支持补能服务与使用条件定义。 | D11: 车主：实际充电时，哪些环节符合预期，哪些没有？如有问题，请讲一次。 | E11: 1. 最近一次、频率、温度或设备条件 2. 是否更换地点 3. 不先暗示过热或故障 | F11: 实际充电题：有BEV/PHEV/增程充电经历。 原追问0条：在“原追问审阅”按题卡编号筛选；详情保留在该表，不能把全部追问逐项念出。 | G11: 2C用户本人提纲：按生活背景—经历—选择—方案的顺序呈现。保留研究任务，按对象区分问法；同义主问合并，细节保留为按条件追问。 原编号题：4条；在“原题映射”按本题编号检索。 | H11: 同意
A12: Q-M4.2-04 | B12: C4 实际补能条件 核心信息 FGD：可用 IHV：可用 | C12: 还原补能流程、设施条件及成本，支持补能服务与使用条件定义。 | D12: 车主：您家、公司或其他日常停车地点是否可以安装充电桩？目前有哪些限制？ 意向者：您家、公司或其他日常停车地点是否可以安装充电桩？目前有哪些限制？ | E12: 1. 是否装桩 2. 车位、供电、许可和费用 3. 不清楚功率时允许未知，不把三相电当默认条件 | F12: 现有或未来有外接充电需求者均可问条件；油车/意向者不问从未发生的充电经历。未知条件记录待确认。 【具备安装意向或曾申请家充】是否需要停车场、物业或其他主体许可？申请过程怎样？不要预设所有公寓都限制安装。 观察/活动：IHV：在受访者愿意且安全的范围内观察停车与充电设施，不打开电气设备；参数只记能确认的内容。 原追问5条：在“原追问审阅”按题卡编号筛选；详情保留在该表，不能把全部追问逐项念出。 | G12: 按审阅意见使用家庭、公司等具体停车地点。 原编号题：8条；在“原题映射”按本题编号检索。 | H12: 已按意见修改 | I12: 您家、公司这些日常停车的地方是否可以安装充电桩？
A13: Q-M4.2-05 | B13: C4 实际补能条件 按需选择 FGD：可用 IHV：可用 | C13: 还原补能流程、设施条件及成本，支持补能服务与使用条件定义。 | D13: 车主：现有或了解过的交流充电方案，是否满足车辆停留期间的补能需要？ 意向者：现有或了解过的交流充电方案，是否满足车辆停留期间的补能需要？ | E13: 1. 已知车端接收能力、充电设施与供电条件；未知允许不答 2. 通常停车多久、起止电量或下一程所需里程 3. 不要求受访者自行换算功率、容量与充满时间；方案比较使用核验材料 | F13: 现有或未来有外接充电需求者均可问条件；油车/意向者不问从未发生的充电经历。未知条件记录待确认。 原追问4条：在“原追问审阅”按题卡编号筛选；详情保留在该表，不能把全部追问逐项念出。 | G13: 2C用户本人提纲：按生活背景—经历—选择—方案的顺序呈现。保留研究任务，按对象区分问法；同义主问合并，细节保留为按条件追问。 原编号题：6条；在“原题映射”按本题编号检索。 | H13: 同意
A14: Q-M4.2-06 | B14: C4 实际补能条件 按需选择 FGD：可用 IHV：可用 | C14: 还原补能流程、设施条件及成本，支持补能服务与使用条件定义。 | D14: 车主：请回顾最近一次加油或其他燃料补给的过程。 | E14: 1. 燃料种类、频次、距离、费用 2. 多燃料选择条件 3. 不默认乙醇普遍使用 | F14: 实际加油题：有ICE/HEV/PHEV/增程加油经历。 【市场确有多燃料选择且本人使用】是否在不同燃料之间切换？依据价格、可用性还是体验？ 原追问3条：在“原追问审阅”按题卡编号筛选；详情保留在该表，不能把全部追问逐项念出。 | G14: 2C用户本人提纲：按生活背景—经历—选择—方案的顺序呈现。保留研究任务，按对象区分问法；同义主问合并，细节保留为按条件追问。 原编号题：1条；在“原题映射”按本题编号检索。 | H14: 同意
A15: Q-M4.3-01 | B15: C4 续航与补能时间底线 核心信息 FGD：可用 IHV：可用 | C15: 连接行程、停车窗口和可用续航，提供技术取舍需求输入；不直接决定电气架构。 | D15: 车主：结合常见行程和最关键的一次远行，怎样的续航才够用？ 意向者：结合目前真实行程和已确定的未来任务，您期望怎样的续航？哪些要求还只是设想？ | E15: 1. 日常与极端需求分别记录 2. 可接受补能次数 3. 所说里程是实际可用还是标称 | F15: 按研究目的选用；有实际经历先谈经历，设想单独记录。 原追问6条：在“原追问审阅”按题卡编号筛选；详情保留在该表，不能把全部追问逐项念出。 | G15: 2C用户本人提纲：按生活背景—经历—选择—方案的顺序呈现。保留研究任务，按对象区分问法；同义主问合并，细节保留为按条件追问。 原编号题：8条；在“原题映射”按本题编号检索。 | H15: 同意
A16: Q-M4.3-02 | B16: C4 续航与补能时间底线 按需选择 FGD：可用 IHV：可用 | C16: 连接行程、停车窗口和可用续航，提供技术取舍需求输入；不直接决定电气架构。 | D16: 车主：您充电时一定要充满吗？一般会充到多少，例如80%、90%或100%？为什么？ 意向者：您充电时一定要充满吗？一般会充到多少，例如80%、90%或100%？为什么？ | E16: 1. 起止电量与下一次任务 2. 家充与途中补能分开 3. 可接受等待底线 | F16: 按研究目的选用；有实际经历先谈经历，设想单独记录。 原追问4条：在“原追问审阅”按题卡编号筛选；详情保留在该表，不能把全部追问逐项念出。 | G16: 按审阅意见改为具体充电上限习惯。 原编号题：3条；在“原题映射”按本题编号检索。 | H16: 已按意见修改 | I16: 你充电一定要冲到满吗？一般情况下冲到多少？90% 100%。。。这样问比较好，改一下
A17: Q-M4.3-03 | B17: C4 续航与补能时间底线 按需选择 FGD：可用 IHV：可用 | C17: 连接行程、停车窗口和可用续航，提供技术取舍需求输入；不直接决定电气架构。 | D17: 车主：对您来说，车辆实际续航至少达到多少才可以接受？低于多少会让您放弃购买？ 意向者：对您来说，车辆实际续航至少达到多少才可以接受？低于多少会让您放弃购买？ | E17: 1. 先说明实际差异 2. 选择理由与改变选择的临界点 3. 价格和续航取自本项目材料 | F17: 按研究目的选用；有实际经历先谈经历，设想单独记录。 需准备并核验：续航价格组合；缺材料时暂不执行方案评价。 原追问2条：在“原追问审阅”按题卡编号筛选；详情保留在该表，不能把全部追问逐项念出。 | G17: 按审阅意见改为可回答的续航底线。 原编号题：3条；在“原题映射”按本题编号检索。 | H17: 已按意见修改 | I17: 看不懂；我觉得可以问续航多少是底线之类的
A18: Q-M4.4-01 | B18: C4 智驾信任及使用边界 核心信息 FGD：可用 IHV：可用 | C18: 识别辅助驾驶任务、信任与接管边界，不将功能偏好当安全验证。 | D18: 车主：您了解或使用过哪些驾驶辅助功能？请分别说明。 意向者：您了解或体验过哪些驾驶辅助功能？哪些已经实际使用，哪些只是听说？ | E18: 1. 了解、试用、日常使用区分 2. 最近一次场景 3. 不用或关闭的原因 | F18: 按研究目的选用；有实际经历先谈经历，设想单独记录。 原追问6条：在“原追问审阅”按题卡编号筛选；详情保留在该表，不能把全部追问逐项念出。 | G18: 2C用户本人提纲：按生活背景—经历—选择—方案的顺序呈现。保留研究任务，按对象区分问法；同义主问合并，细节保留为按条件追问。 原编号题：7条；在“原题映射”按本题编号检索。 | H18: 同意
A19: Q-M4.4-02 | B19: C4 智驾信任及使用边界 按需选择 FGD：可用 IHV：可用 | C19: 识别辅助驾驶任务、信任与接管边界，不将功能偏好当安全验证。 | D19: 车主：哪些驾驶辅助任务最值得帮助您完成，哪些没有必要？ 意向者：哪些驾驶辅助任务最值得帮助您完成，哪些没有必要？ | E19: 1. 驾驶者与乘员分别回答 2. 频次、困难、信任及接管边界 3. 不将功能描述为自动驾驶 | F19: 按研究目的选用；有实际经历先谈经历，设想单独记录。 原追问5条：在“原追问审阅”按题卡编号筛选；详情保留在该表，不能把全部追问逐项念出。 | G19: 2C用户本人提纲：按生活背景—经历—选择—方案的顺序呈现。保留研究任务，按对象区分问法；同义主问合并，细节保留为按条件追问。 原编号题：6条；在“原题映射”按本题编号检索。 | H19: 同意
A20: Q-M4.4-03 | B20: C4 智驾信任及使用边界 按需选择 FGD：可用 IHV：可用 | C20: 识别辅助驾驶任务、信任与接管边界，不将功能偏好当安全验证。 | D20: 车主：什么条件下您愿意使用辅助驾驶，什么条件下会停止使用？ 意向者：什么条件下您愿意使用辅助驾驶，什么条件下会停止使用？ | E20: 1. 理解的责任边界 2. 失误和接管经历 3. 想象担忧与真实事件分开 | F20: 按研究目的选用；有实际经历先谈经历，设想单独记录。 原追问0条：在“原追问审阅”按题卡编号筛选；详情保留在该表，不能把全部追问逐项念出。 | G20: 2C用户本人提纲：按生活背景—经历—选择—方案的顺序呈现。保留研究任务，按对象区分问法；同义主问合并，细节保留为按条件追问。 原编号题：0条；在“原题映射”按本题编号检索。 本次补充的新题。 | H20: 同意
A21: Q-M4.4-04 | B21: C4 智驾信任及使用边界 按需选择 FGD：可用 IHV：可用 | C21: 识别辅助驾驶任务、信任与接管边界，不将功能偏好当安全验证。 | D21: 车主：对自动泊车，您最希望它解决什么问题？ 意向者：对自动泊车，您最希望它解决什么问题？ | E21: 1. 车位和场景 2. 速度、准确性、接管 3. 若评估付费须提供明确功能材料 | F21: 按研究目的选用；有实际经历先谈经历，设想单独记录。 原追问0条：在“原追问审阅”按题卡编号筛选；详情保留在该表，不能把全部追问逐项念出。 | G21: 2C用户本人提纲：按生活背景—经历—选择—方案的顺序呈现。保留研究任务，按对象区分问法；同义主问合并，细节保留为按条件追问。 原编号题：3条；在“原题映射”按本题编号检索。 | H21: 同意
A22: Q-M4.5-01 | B22: C4 安全与耐久期待 核心信息 FGD：可用 IHV：可用 | C22: 理解安全、健康与耐久认知和证据需求；不替代工程、医学或法规验证。 | D22: 车主：您在出行或选车时最关注什么安全问题？ 意向者：您在出行或选车时最关注什么安全问题？ | E22: 1. 影响哪位乘员、何种情境 2. 判断依据 3. 碰撞评级与功能的理解分别确认 | F22: 按研究目的选用；有实际经历先谈经历，设想单独记录。 原追问7条：在“原追问审阅”按题卡编号筛选；详情保留在该表，不能把全部追问逐项念出。 | G22: 2C用户本人提纲：按生活背景—经历—选择—方案的顺序呈现。保留研究任务，按对象区分问法；同义主问合并，细节保留为按条件追问。 原编号题：5条；在“原题映射”按本题编号检索。 | H22: 同意
A23: Q-M4.5-02 | B23: C4 安全与耐久期待 按需选择 FGD：可用 IHV：可用 | C23: 理解安全、健康与耐久认知和证据需求；不替代工程、医学或法规验证。 | D23: 车主：您怎样理解车内健康？哪些实际经历让您在意？ 意向者：您怎样理解车内健康？哪些实际经历让您在意？ | E23: 1. 空气、气味、材质或其他自发提及因素 2. 判断证据 3. 不要将偏好当医学结论 | F23: 按研究目的选用；有实际经历先谈经历，设想单独记录。 原追问9条：在“原追问审阅”按题卡编号筛选；详情保留在该表，不能把全部追问逐项念出。 | G23: 2C用户本人提纲：按生活背景—经历—选择—方案的顺序呈现。保留研究任务，按对象区分问法；同义主问合并，细节保留为按条件追问。 原编号题：9条；在“原题映射”按本题编号检索。 | H23: 同意
A24: Q-M4.5-03 | B24: C4 安全与耐久期待 按需选择 FGD：可用 IHV：可用 | C24: 理解安全、健康与耐久认知和证据需求；不替代工程、医学或法规验证。 | D24: 车主：您对电池保护、耐久或质保有什么了解和顾虑？ 意向者：您对电池保护、耐久或质保有什么了解和顾虑？ | E24: 1. 实际经历与宣传名词区分 2. 谁影响认知 3. 更需要什么证据或承诺 | F24: 按研究目的选用；有实际经历先谈经历，设想单独记录。 原追问0条：在“原追问审阅”按题卡编号筛选；详情保留在该表，不能把全部追问逐项念出。 | G24: 2C用户本人提纲：按生活背景—经历—选择—方案的顺序呈现。保留研究任务，按对象区分问法；同义主问合并，细节保留为按条件追问。 原编号题：2条；在“原题映射”按本题编号检索。 | H24: 同意
A25: Q-M4.5-04 | B25: C4 安全与耐久期待 按需选择 FGD：可用 IHV：可用 | C25: 理解安全、健康与耐久认知和证据需求；不替代工程、医学或法规验证。 | D25: 车主：车底或底盘通过性是否影响过您的出行或购车考虑？ 意向者：车底或底盘通过性是否影响过您的出行或购车考虑？ | E25: 1. 具体路段与是否发生磕碰 2. 实际损失与担忧区分 3. 电池相关追问仅适用车型 | F25: 按研究目的选用；有实际经历先谈经历，设想单独记录。 原追问1条：在“原追问审阅”按题卡编号筛选；详情保留在该表，不能把全部追问逐项念出。 | G25: 2C用户本人提纲：按生活背景—经历—选择—方案的顺序呈现。保留研究任务，按对象区分问法；同义主问合并，细节保留为按条件追问。 原编号题：4条；在“原题映射”按本题编号检索。 | H25: 同意

Sheet 2C-05 产品与配置
A2: 2C-05 产品与配置
A3: 32张题卡。2C：消费者本人及家庭的真实经历。黄色列供你填写；核心信息已回答就不重复问。
A5: 题卡编号 | B5: 子模块与适用方法 | C5: 研究目的与边界 | D5: 主问：按对象选用 | E5: 核心追问：覆盖信息 | F5: 触发条件与观察任务 | G5: 归并调整与来源 | H5: 确认状态 | I5: 你的修改意见
A6: Q-M5.1-01 | B6: C5 整体概念评价 核心信息 FGD：可用 IHV：可用 | C6: 检验概念理解、场景匹配与竞争差异。 | D6: 车主：看完这份产品概念，您的第一反应是什么？ 意向者：看完这份产品概念，您的第一反应是什么？ | E6: 1. 先独立回答 2. 理解成什么车、适合谁 3. 最吸引与最疑惑 4. 不给“全面领先”的暗示 | F6: 仅当项目已准备并展示完整产品概念材料后触发；未展示产品概念时整题不出现。 原追问0条：在“原追问审阅”按题卡编号筛选；详情保留在该表，不能把全部追问逐项念出。 | G6: 按审阅意见增加产品概念材料触发门槛。 原编号题：2条；在“原题映射”按本题编号检索。 | H6: 已按意见修改 | I6: 需要有产品概念才会这题，如果没有的话这题不出现，那么需要在哪里有trigger
A7: Q-M5.1-02 | B7: C5 整体概念评价 按需选择 FGD：可用 IHV：可用 | C7: 检验概念理解、场景匹配与竞争差异。 | D7: 车主：请把这个概念放到您刚才讲的关键场景中，哪些合适，哪些不合适？ 意向者：请把这个概念放到您刚才讲的关键场景中，哪些合适，哪些不合适？ | E7: 1. 场景前提 2. 替代现有方案的条件 3. 没覆盖的人或任务 | F7: 仅当项目已准备并展示完整产品概念材料后触发；未展示产品概念时整题不出现。 原追问0条：在“原追问审阅”按题卡编号筛选；详情保留在该表，不能把全部追问逐项念出。 | G7: 按审阅意见增加产品概念材料触发门槛。 原编号题：1条；在“原题映射”按本题编号检索。 | H7: 已按意见修改 | I7: 需要有产品概念才会这题，如果没有的话这题不出现，那么需要在哪里有trigger
A8: Q-M5.1-03 | B8: C5 整体概念评价 按需选择 FGD：可用 IHV：可用 | C8: 检验概念理解、场景匹配与竞争差异。 | D8: 车主：看完产品概念后，哪些内容最吸引您？哪些地方仍不清楚或需要改进？ 意向者：看完产品概念后，哪些内容最吸引您？哪些地方仍不清楚或需要改进？ | E8: 1. 对比依据一致 2. 不熟悉的竞品可跳过 3. 产品判断与品牌判断分开 | F8: 仅当项目已展示完整产品概念材料后触发；不再假设存在未展示的备选方案。 原追问0条：在“原追问审阅”按题卡编号筛选；详情保留在该表，不能把全部追问逐项念出。 | G8: 按审阅意见删除不存在的“备选方案”前提。 原编号题：2条；在“原题映射”按本题编号检索。 | H8: 已按意见修改 | I8: 备选方案？这个没有出现过，所以问题不对
A9: Q-M5.2-01 | B9: C5 外观轮廓、前脸与车尾 核心信息 FGD：可用 IHV：可用 | C9: 比较具体外观方案的偏好、排斥与取舍；各部位材料分开记录。 | D9: 车主：请比较这些整体车型轮廓方案，分别说说吸引和排斥您的地方，再选最适合的一款。 意向者：请比较这些整体车型轮廓方案，分别说说吸引和排斥您的地方，再选最适合的一款。 | E9: 1. 比例、形面和用途联想 2. 辨识度与前瞻感分别追问 3. 材料逐款编号 | F9: 按研究目的选用；有实际经历先谈经历，设想单独记录。 需准备并核验：外观方案图；缺材料时暂不执行方案评价。 观察/活动：按已记录的材料顺序逐一展示；先个人评价再相互比较，前脸和车尾独立记录。 原追问6条：在“原追问审阅”按题卡编号筛选；详情保留在该表，不能把全部追问逐项念出。 | G9: 按审阅意见将“体态”改为“车型轮廓”。 原编号题：4条；在“原题映射”按本题编号检索。 | H9: 已按意见修改 | I9: 体态不是这么说的，应该叫：车型轮廓
A10: Q-M5.2-02 | B10: C5 外观体态、前脸与车尾 按需选择 FGD：可用 IHV：可用 | C10: 比较具体外观方案的偏好、排斥与取舍；各部位材料分开记录。 | D10: 车主：请比较这些前脸方案，哪款更适合您的用车场景？ 意向者：请比较这些前脸方案，哪款更适合您的用车场景？ | E10: 1. 格栅、灯光与细节 2. 辨识度和耐看程度 3. 不把“大格栅”预设为高级 | F10: 按研究目的选用；有实际经历先谈经历，设想单独记录。 需准备并核验：外观方案图；缺材料时暂不执行方案评价。 原追问8条：在“原追问审阅”按题卡编号筛选；详情保留在该表，不能把全部追问逐项念出。 | G10: 2C用户本人提纲：按生活背景—经历—选择—方案的顺序呈现。实际经历与方案评价分开；按材料逐项评价，保留排斥理由和取舍，不把喜欢等同购买。 原编号题：6条；在“原题映射”按本题编号检索。 | H10: 同意
A11: Q-M5.2-03 | B11: C5 外观体态、前脸与车尾 按需选择 FGD：可用 IHV：可用 | C11: 比较具体外观方案的偏好、排斥与取舍；各部位材料分开记录。 | D11: 车主：请比较这些车尾方案，哪款更适合您？ 意向者：请比较这些车尾方案，哪款更适合您？ | E11: 1. 具体喜欢与不喜欢 2. 辨识度、功能联想 3. 车尾材料与前脸材料ID分开 | F11: 按研究目的选用；有实际经历先谈经历，设想单独记录。 需准备并核验：外观方案图；缺材料时暂不执行方案评价。 原追问8条：在“原追问审阅”按题卡编号筛选；详情保留在该表，不能把全部追问逐项念出。 | G11: 2C用户本人提纲：按生活背景—经历—选择—方案的顺序呈现。实际经历与方案评价分开；按材料逐项评价，保留排斥理由和取舍，不把喜欢等同购买。 原编号题：6条；在“原题映射”按本题编号检索。 | H11: 同意
A12: Q-M5.2-04 | B12: C5 外观体态、前脸与车尾 按需选择 FGD：可用 IHV：可用 | C12: 比较具体外观方案的偏好、排斥与取舍；各部位材料分开记录。 | D12: 车主：从车型轮廓、前脸和车尾来看，哪一部分最符合您的期待？哪一部分最需要调整？ 意向者：从车型轮廓、前脸和车尾来看，哪一部分最符合您的期待？哪一部分最需要调整？ | E12: 1. 造型与空间、价格、品牌等冲突 2. 先问过去真实取舍，再谈假设 | F12: 按研究目的选用；有实际经历先谈经历，设想单独记录。 原追问7条：在“原追问审阅”按题卡编号筛选；详情保留在该表，不能把全部追问逐项念出。 | G12: 按审阅意见改为清楚的整体外观评价。 原编号题：3条；在“原题映射”按本题编号检索。 | H12: 已按意见修改 | I12: 看不懂？这个题目很奇怪
A13: Q-M5.3-01 | B13: C5 内饰与CMF 核心信息 FGD：可用 IHV：可用 | C13: 识别内饰风格、色彩、材料与工艺的接受条件。 | D13: 车主：如果用几个形容词描述这套内饰，您会怎么说？为什么？ 意向者：如果用几个形容词描述这套内饰，您会怎么说？为什么？ | E13: 1. 偏好与排斥 2. 新颖和辨识度分别记录 3. 家庭/商务氛围不强迫二选一 | F13: 按研究目的选用；有实际经历先谈经历，设想单独记录。 需准备并核验：颜色/材料/工艺样板；缺材料时暂不执行方案评价。 原追问8条：在“原追问审阅”按题卡编号筛选；详情保留在该表，不能把全部追问逐项念出。 | G13: 按审阅意见采用形容词引导。 原编号题：8条；在“原题映射”按本题编号检索。 | H13: 已按意见修改 | I13: 用形容词来形容，你会怎么说
A14: Q-M5.3-02 | B14: C5 内饰与CMF 按需选择 FGD：可用 IHV：可用 | C14: 识别内饰风格、色彩、材料与工艺的接受条件。 | D14: 车主：请看这些颜色、材质与工艺方案，哪些适合您，哪些不能接受？ 意向者：请看这些颜色、材质与工艺方案，哪些适合您，哪些不能接受？ | E14: 1. 触感、清洁、耐用与品质判断 2. 实际样材与屏幕图像区别 3. 商务礼仪只在相关时追问 | F14: 按研究目的选用；有实际经历先谈经历，设想单独记录。 需准备并核验：颜色/材料/工艺样板；缺材料时暂不执行方案评价。 原追问4条：在“原追问审阅”按题卡编号筛选；详情保留在该表，不能把全部追问逐项念出。 | G14: 2C用户本人提纲：按生活背景—经历—选择—方案的顺序呈现。实际经历与方案评价分开；按材料逐项评价，保留排斥理由和取舍，不把喜欢等同购买。 原编号题：3条；在“原题映射”按本题编号检索。 | H14: 同意
A15: Q-M5.3-03 | B15: C5 内饰与CMF 按需选择 FGD：可用 IHV：可用 | C15: 识别内饰风格、色彩、材料与工艺的接受条件。 | D15: 车主：车身与内饰颜色，您分别偏好哪些、排斥哪些？ 意向者：车身与内饰颜色，您分别偏好哪些、排斥哪些？ | E15: 1. 实际选择经历 2. 原因 3. 吸热或文化禁忌以本人理解记录，不写成市场事实 | F15: 按研究目的选用；有实际经历先谈经历，设想单独记录。 需准备并核验：颜色/材料/工艺样板；缺材料时暂不执行方案评价。 原追问3条：在“原追问审阅”按题卡编号筛选；详情保留在该表，不能把全部追问逐项念出。 | G15: 2C用户本人提纲：按生活背景—经历—选择—方案的顺序呈现。实际经历与方案评价分开；按材料逐项评价，保留排斥理由和取舍，不把喜欢等同购买。 原编号题：7条；在“原题映射”按本题编号检索。 | H15: 同意
A16: Q-M5.4-01 | B16: C5 座椅空间与进出动线 按需选择 FGD：可用 IHV：可用 | C16: 在明确材料或实车下检验空间布局、动线和功能取舍。 | D16: 车主：按材料中的实际长宽高，把这辆车放到您常走的路线和停车地点，会遇到什么？ 意向者：按材料中的实际长宽高，把这辆车放到您常走的路线和停车地点，会遇到什么？ | E16: 1. 能否停入、转弯、开门与限高 2. 尺寸是否构成否决 3. 不由级别推算车长 | F16: 按研究目的选用；有实际经历先谈经历，设想单独记录。 需准备并核验：尺寸及座椅空间方案；缺材料时暂不执行方案评价。 原追问4条：在“原追问审阅”按题卡编号筛选；详情保留在该表，不能把全部追问逐项念出。 | G16: 2C用户本人提纲：按生活背景—经历—选择—方案的顺序呈现。实际经历与方案评价分开；按材料逐项评价，保留排斥理由和取舍，不把喜欢等同购买。 原编号题：6条；在“原题映射”按本题编号检索。 | H16: 同意
A17: Q-M5.4-02 | B17: C5 座椅空间与进出动线 核心信息 FGD：可用 IHV：可用 | C17: 在明确材料或实车下检验空间布局、动线和功能取舍。 | D17: 车主：这些座椅布局中，哪种最能完成您的日常和关键任务？ 意向者：这些座椅布局中，哪种最能完成您的日常和关键任务？ | E17: 1. 人数、座位角色、儿童座椅、行李 2. 四/六/七座仅在材料存在时比较 | F17: 按研究目的选用；有实际经历先谈经历，设想单独记录。 需准备并核验：尺寸及座椅空间方案；缺材料时暂不执行方案评价。 原追问5条：在“原追问审阅”按题卡编号筛选；详情保留在该表，不能把全部追问逐项念出。 | G17: 2C用户本人提纲：按生活背景—经历—选择—方案的顺序呈现。实际经历与方案评价分开；按材料逐项评价，保留排斥理由和取舍，不把喜欢等同购买。 原编号题：4条；在“原题映射”按本题编号检索。 | H17: 同意
A18: Q-M5.4-03 | B18: C5 座椅空间与进出动线 按需选择 FGD：可用 IHV：可用 | C18: 在明确材料或实车下检验空间布局、动线和功能取舍。 | D18: 车主：请比较这些后排进出方式，哪种更适合经常使用的人？ 意向者：请比较这些后排进出方式，哪种更适合经常使用的人？ | E18: 1. 过道、前移座椅、台阶和门开口 2. 操作步骤 3. 有样车才做实操 | F18: 按研究目的选用；有实际经历先谈经历，设想单独记录。 需准备并核验：尺寸及座椅空间方案；缺材料时暂不执行方案评价。 原追问2条：在“原追问审阅”按题卡编号筛选；详情保留在该表，不能把全部追问逐项念出。 | G18: 2C用户本人提纲：按生活背景—经历—选择—方案的顺序呈现。实际经历与方案评价分开；按材料逐项评价，保留排斥理由和取舍，不把喜欢等同购买。 原编号题：2条；在“原题映射”按本题编号检索。 | H18: 同意
A19: Q-M5.4-04 | B19: C5 座椅空间与进出动线 按需选择 FGD：可用 IHV：可用 | C19: 在明确材料或实车下检验空间布局、动线和功能取舍。 | D19: 车主：这些座椅和储物空间变化方式分别会在什么情境下使用？ 意向者：这些座椅和储物空间变化方式分别会在什么情境下使用？ | E19: 1. 实际物品或事件 2. 操作负担 3. 喜欢但不用与真正需要分开 | F19: 按研究目的选用；有实际经历先谈经历，设想单独记录。 需准备并核验：尺寸及座椅空间方案；缺材料时暂不执行方案评价。 原追问8条：在“原追问审阅”按题卡编号筛选；详情保留在该表，不能把全部追问逐项念出。 | G19: 2C用户本人提纲：按生活背景—经历—选择—方案的顺序呈现。实际经历与方案评价分开；按材料逐项评价，保留排斥理由和取舍，不把喜欢等同购买。 原编号题：7条；在“原题映射”按本题编号检索。 | H19: 同意
A20: Q-M5.4-05 | B20: C5 座椅空间与进出动线 按需选择 FGD：可用 IHV：可用 | C20: 在明确材料或实车下检验空间布局、动线和功能取舍。 | D20: 车主：这款尾门设计会怎样影响您的装载、取物或停靠？ 意向者：这款尾门设计会怎样影响您的装载、取物或停靠？ | E20: 1. 最深处物品、站位、后方空间 2. 坐立承重仅以核验材料为准 | F20: 按研究目的选用；有实际经历先谈经历，设想单独记录。 需准备并核验：尺寸及座椅空间方案；缺材料时暂不执行方案评价。 原追问6条：在“原追问审阅”按题卡编号筛选；详情保留在该表，不能把全部追问逐项念出。 | G20: 2C用户本人提纲：按生活背景—经历—选择—方案的顺序呈现。实际经历与方案评价分开；按材料逐项评价，保留排斥理由和取舍，不把喜欢等同购买。 原编号题：4条；在“原题映射”按本题编号检索。 | H20: 同意
A21: Q-M5.4-06 | B21: C5 座椅空间与进出动线 按需选择 FGD：可用 IHV：可用 | C21: 在明确材料或实车下检验空间布局、动线和功能取舍。 | D21: 车主：这组车门、导轨及侧窗方案，会怎样影响进出、视野或使用？ 意向者：这组车门、导轨及侧窗方案，会怎样影响进出、视野或使用？ | E21: 1. 第三排采光与视线 2. 喜欢/排斥原因 3. 外观与使用分别记录 | F21: 按研究目的选用；有实际经历先谈经历，设想单独记录。 需准备并核验：尺寸及座椅空间方案；缺材料时暂不执行方案评价。 原追问1条：在“原追问审阅”按题卡编号筛选；详情保留在该表，不能把全部追问逐项念出。 | G21: 2C用户本人提纲：按生活背景—经历—选择—方案的顺序呈现。实际经历与方案评价分开；按材料逐项评价，保留排斥理由和取舍，不把喜欢等同购买。 原编号题：1条；在“原题映射”按本题编号检索。 | H21: 同意
A22: Q-M5.4-07 | B22: C5 座椅空间与进出动线 按需选择 FGD：可用 IHV：可用 | C22: 在明确材料或实车下检验空间布局、动线和功能取舍。 | D22: 车主：这些车顶方案中，您倾向哪种？ 意向者：这些车顶方案中，您倾向哪种？ | E22: 1. 采光、遮阳、视野、空间和维护 2. 加装后总高度及停车限制 | F22: 按研究目的选用；有实际经历先谈经历，设想单独记录。 需准备并核验：尺寸及座椅空间方案；缺材料时暂不执行方案评价。 【项目包含车顶附件】加装后的总高度如何影响常用停车点？数值以已审核尺寸卡为准。 原追问7条：在“原追问审阅”按题卡编号筛选；详情保留在该表，不能把全部追问逐项念出。 | G22: 2C用户本人提纲：按生活背景—经历—选择—方案的顺序呈现。实际经历与方案评价分开；按材料逐项评价，保留排斥理由和取舍，不把喜欢等同购买。 原编号题：2条；在“原题映射”按本题编号检索。 | H22: 同意
A23: Q-M5.4-08 | B23: C5 座椅空间与进出动线 按需选择 FGD：可用 IHV：可用 | C23: 在明确材料或实车下检验空间布局、动线和功能取舍。 | D23: 车主：增加中央岛台等功能会改变车内通道，您怎样权衡？ 意向者：增加中央岛台等功能会改变车内通道，您怎样权衡？ | E23: 1. 谁会使用、频次、上下车 2. 功能价值与通道成本 3. 不预设“尊享” | F23: 按研究目的选用；有实际经历先谈经历，设想单独记录。 需准备并核验：尺寸及座椅空间方案；缺材料时暂不执行方案评价。 原追问3条：在“原追问审阅”按题卡编号筛选；详情保留在该表，不能把全部追问逐项念出。 | G23: 2C用户本人提纲：按生活背景—经历—选择—方案的顺序呈现。实际经历与方案评价分开；按材料逐项评价，保留排斥理由和取舍，不把喜欢等同购买。 原编号题：1条；在“原题映射”按本题编号检索。 | H23: 同意
A24: Q-M5.5-01 | B24: C5 座舱交互方案 核心信息 FGD：可用 IHV：可用 | C24: 比较交互方案与乘员任务的匹配，不以静态演示推断行驶安全。 | D24: 车主：比较这些屏幕布局，哪些更适合不同乘员的任务？ 意向者：比较这些屏幕布局，哪些更适合不同乘员的任务？ | E24: 1. 驾驶员、副驾、后排用途 2. 干扰或闲置 3. 不预设副驾娱乐“不专业” | F24: 按研究目的选用；有实际经历先谈经历，设想单独记录。 需准备并核验：交互原型及限制说明；缺材料时暂不执行方案评价。 原追问7条：在“原追问审阅”按题卡编号筛选；详情保留在该表，不能把全部追问逐项念出。 | G24: 2C用户本人提纲：按生活背景—经历—选择—方案的顺序呈现。实际经历与方案评价分开；按材料逐项评价，保留排斥理由和取舍，不把喜欢等同购买。 原编号题：4条；在“原题映射”按本题编号检索。 | H24: 同意
A25: Q-M5.5-02 | B25: C5 座舱交互方案 按需选择 FGD：可用 IHV：可用 | C25: 比较交互方案与乘员任务的匹配，不以静态演示推断行驶安全。 | D25: 车主：在这些按键与触控方案中，您希望哪些操作采用哪种方式？ 意向者：在这些按键与触控方案中，您希望哪些操作采用哪种方式？ | E25: 1. 驾驶与停车时区分 2. 常用操作、盲操和误触 3. 静止演示不等于行驶安全验证 | F25: 按研究目的选用；有实际经历先谈经历，设想单独记录。 需准备并核验：交互原型及限制说明；缺材料时暂不执行方案评价。 原追问0条：在“原追问审阅”按题卡编号筛选；详情保留在该表，不能把全部追问逐项念出。 | G25: 2C用户本人提纲：按生活背景—经历—选择—方案的顺序呈现。实际经历与方案评价分开；按材料逐项评价，保留排斥理由和取舍，不把喜欢等同购买。 原编号题：3条；在“原题映射”按本题编号检索。 | H25: 同意
... A36: Q-M5.7-04 | B36: C5 强制取舍与必选项 按需选择 FGD：可用 IHV：可用 | C36: 在清晰功能与预算约束下识别配置优先级；法规底线不进入删减交易。 | D36: 车主：有没有重要需求或功能是今天没有覆盖到的？ 意向者：有没有重要需求或功能是今天没有覆盖到的？ | E36: 1. 具体场景、现有解决方式 2. 与刚才保留项相比优先级 3. 不重复整套提问 | F36: 按研究目的选用；有实际经历先谈经历，设想单独记录。 原追问1条：在“原追问审阅”按题卡编号筛选；详情保留在该表，不能把全部追问逐项念出。 | G36: 2C用户本人提纲：按生活背景—经历—选择—方案的顺序呈现。实际经历与方案评价分开；按材料逐项评价，保留排斥理由和取舍，不把喜欢等同购买。 原编号题：1条；在“原题映射”按本题编号检索。 | H36: 同意
A37: Q-M5.6-07 | B37: C5 功能与配置组合 按需选择 FGD：可用 IHV：可用 | C37: 检验具体功能是否对应真实任务及使用条件，区分喜欢与需要。 | D37: 车主：在炎热或强日照环境下，车辆隔热和空调降温表现需要达到什么程度？ 意向者：在炎热或强日照环境下，车辆隔热和空调降温表现需要达到什么程度？ | E37: 1. 分别确认隔热玻璃、遮阳帘、座椅通风的作用 2. 先独立评价再排序，允许都不需要 3. 对应暴晒、行驶、前后排的具体需求 | F37: 按研究目的选用；有实际经历先谈经历，设想单独记录。 需准备并核验：热舒适配置说明；缺材料时暂不执行方案评价。 原追问2条：在“原追问审阅”按题卡编号筛选；详情保留在该表，不能把全部追问逐项念出。 | G37: 按审阅意见把“热舒适”改为隔热与空调降温。 原编号题：4条；在“原题映射”按本题编号检索。 | H37: 已按意见修改 | I37: 热舒适？这么说吗？这里是隔热吧，

Sheet 2C-06 品牌与购买条件
A2: 2C-06 品牌与购买条件
A3: 15张题卡。2C：消费者本人及家庭的真实经历。黄色列供你填写；核心信息已回答就不重复问。
A5: 题卡编号 | B5: 子模块与适用方法 | C5: 研究目的与边界 | D5: 主问：按对象选用 | E5: 核心追问：覆盖信息 | F5: 触发条件与观察任务 | G5: 归并调整与来源 | H5: 确认状态 | I5: 你的修改意见
A6: Q-M6.1-01 | B6: C6 自发品牌认知 核心信息 FGD：可用 IHV：可用 | C6: 区分品牌自发认知、提示认知及亲身体验，为品牌沟通提供依据。 | D6: 车主：不看品牌提示，您首先想到哪些相关汽车品牌？分别有什么印象？ 意向者：不看品牌提示，您首先想到哪些相关汽车品牌？分别有什么印象？ | E6: 1. 熟悉、了解与亲身体验区分 2. 自发再提示 3. 品牌印象不当市场事实 | F6: 按研究目的选用；有实际经历先谈经历，设想单独记录。 原追问7条：在“原追问审阅”按题卡编号筛选；详情保留在该表，不能把全部追问逐项念出。 | G6: 2C用户本人提纲：按生活背景—经历—选择—方案的顺序呈现。保留研究任务，按对象区分问法；同义主问合并，细节保留为按条件追问。 原编号题：2条；在“原题映射”按本题编号检索。 | H6: 同意
A7: Q-M6.1-02 | B7: C6 自发品牌认知 按需选择 FGD：可用 IHV：可用 | C7: 区分品牌自发认知、提示认知及亲身体验，为品牌沟通提供依据。 | D7: 车主：对您熟悉的品牌，您如何描述它们之间的差异？ 意向者：对您熟悉的品牌，您如何描述它们之间的差异？ | E7: 1. 功能、可靠性、身份、服务等由受访者自发提出 2. 避免“鄙视链”诱导 | F7: 按研究目的选用；有实际经历先谈经历，设想单独记录。 原追问13条：在“原追问审阅”按题卡编号筛选；详情保留在该表，不能把全部追问逐项念出。 | G7: 2C用户本人提纲：按生活背景—经历—选择—方案的顺序呈现。保留研究任务，按对象区分问法；同义主问合并，细节保留为按条件追问。 原编号题：12条；在“原题映射”按本题编号检索。 | H7: 同意
A8: Q-M6.1-03 | B8: C6 自发品牌认知 按需选择 FGD：可用 IHV：可用 | C8: 区分品牌自发认知、提示认知及亲身体验，为品牌沟通提供依据。 | D8: 车主：您信任或不信任某个品牌，主要依据什么？ 意向者：您信任或不信任某个品牌，主要依据什么？ | E8: 1. 经历、他人、信息来源 2. 哪些证据能改变判断 3. 中国品牌仅在项目目标相关时提示 | F8: 按研究目的选用；有实际经历先谈经历，设想单独记录。 原追问4条：在“原追问审阅”按题卡编号筛选；详情保留在该表，不能把全部追问逐项念出。 | G8: 2C用户本人提纲：按生活背景—经历—选择—方案的顺序呈现。保留研究任务，按对象区分问法；同义主问合并，细节保留为按条件追问。 原编号题：7条；在“原题映射”按本题编号检索。 | H8: 同意
A9: Q-M6.2-01 | B9: C6 品牌揭示后的评价变化 核心信息 FGD：可用 IHV：可用 | C9: 比较品牌揭示前后评价，识别品牌对产品判断的影响。 | D9: 车主：现在告诉您这份概念的品牌，您刚才的判断发生了什么变化？ 意向者：现在告诉您这份概念的品牌，您刚才的判断发生了什么变化？ | E9: 1. 明确记录揭示前后 2. 变好、变差或不变都可 3. 为什么 | F9: 按研究目的选用；有实际经历先谈经历，设想单独记录。 需准备并核验：品牌揭示材料；缺材料时暂不执行方案评价。 观察/活动：保存揭示前评价，再展示品牌并记录变化；不得用主持人口头评价暗示品牌水平。 原追问0条：在“原追问审阅”按题卡编号筛选；详情保留在该表，不能把全部追问逐项念出。 | G9: 2C用户本人提纲：按生活背景—经历—选择—方案的顺序呈现。保留研究任务，按对象区分问法；同义主问合并，细节保留为按条件追问。 原编号题：1条；在“原题映射”按本题编号检索。 | H9: 同意
A10: Q-M6.2-02 | B10: C6 品牌揭示后的评价变化 按需选择 FGD：可用 IHV：可用 | C10: 比较品牌揭示前后评价，识别品牌对产品判断的影响。 | D10: 车主：如果在您的家庭、工作或社交场景使用这个品牌，您有什么感受？ 意向者：如果在您的家庭、工作或社交场景使用这个品牌，您有什么感受？ | E10: 1. 请用具体人员和场合说明感受，允许没有影响 2. 如果同时存在公共服务或其他用途版本，仅在项目涉及且已展示核验材料时询问区隔需求 3. 不预设公共服务版本损害形象，不把用途关联当人群价值判断 | F10: 按研究目的选用；有实际经历先谈经历，设想单独记录。 需准备并核验：品牌揭示材料；缺材料时暂不执行方案评价。 【商务采购或接待】品牌是否需要满足客户、合作方或内部采购制度要求？请举例，不预设存在品牌层级。 原追问6条：在“原追问审阅”按题卡编号筛选；详情保留在该表，不能把全部追问逐项念出。 | G10: 2C用户本人提纲：按生活背景—经历—选择—方案的顺序呈现。保留研究任务，按对象区分问法；同义主问合并，细节保留为按条件追问。 原编号题：2条；在“原题映射”按本题编号检索。 | H10: 同意
A11: Q-M6.3-01 | B11: C6 价格与版型 核心信息 FGD：可用 IHV：可用 | C11: 理解报价、版型、月付及保障条款的接受理由；定性答案不推算市场最优价格。 | D11: 车主：在功能、版本和价格口径说明清楚后，您怎样看待这份报价？ 意向者：在功能、版本和价格口径说明清楚后，您怎样看待这份报价？ | E11: 1. 币种、落地/裸车、日期 2. 预算与比较对象 3. 不把回答解释为定量定价模型 | F11: 按研究目的选用；有实际经历先谈经历，设想单独记录。 需准备并核验：报价/版型/金融条款；缺材料时暂不执行方案评价。 原追问11条：在“原追问审阅”按题卡编号筛选；详情保留在该表，不能把全部追问逐项念出。 | G11: 2C用户本人提纲：按生活背景—经历—选择—方案的顺序呈现。保留研究任务，按对象区分问法；同义主问合并，细节保留为按条件追问。 原编号题：7条；在“原题映射”按本题编号检索。 | H11: 同意
A12: Q-M6.3-02 | B12: C6 价格与版型 按需选择 FGD：可用 IHV：可用 | C12: 理解报价、版型、月付及保障条款的接受理由；定性答案不推算市场最优价格。 | D12: 车主：这些版型之间的配置差异与价差，您会怎样选择？ 意向者：这些版型之间的配置差异与价差，您会怎样选择？ | E12: 1. 最低可接受版本 2. 升级原因 3. 放弃高配原因 4. 避免固定“30万港币”等旧项目数 | F12: 按研究目的选用；有实际经历先谈经历，设想单独记录。 需准备并核验：报价/版型/金融条款；缺材料时暂不执行方案评价。 原追问0条：在“原追问审阅”按题卡编号筛选；详情保留在该表，不能把全部追问逐项念出。 | G12: 2C用户本人提纲：按生活背景—经历—选择—方案的顺序呈现。保留研究任务，按对象区分问法；同义主问合并，细节保留为按条件追问。 原编号题：2条；在“原题映射”按本题编号检索。 | H12: 同意
A13: Q-M6.3-03 | B13: C6 价格与版型 按需选择 FGD：可用 IHV：可用 | C13: 理解报价、版型、月付及保障条款的接受理由；定性答案不推算市场最优价格。 | D13: 车主：在费用、期限、权益与退出条件清楚的情况下，您怎样看待这个月付方案？ 意向者：在费用、期限、权益与退出条件清楚的情况下，您怎样看待这个月付方案？ | E13: 1. 总支出与月付分别判断 2. 首付、尾款、保险和保养 3. 不把贷款与租赁混同 | F13: 按研究目的选用；有实际经历先谈经历，设想单独记录。 需准备并核验：报价/版型/金融条款；缺材料时暂不执行方案评价。 原追问2条：在“原追问审阅”按题卡编号筛选；详情保留在该表，不能把全部追问逐项念出。 | G13: 2C用户本人提纲：按生活背景—经历—选择—方案的顺序呈现。保留研究任务，按对象区分问法；同义主问合并，细节保留为按条件追问。 原编号题：2条；在“原题映射”按本题编号检索。 | H13: 同意
A14: Q-M6.3-04 | B14: C6 价格与版型 按需选择 FGD：可用 IHV：可用 | C14: 理解报价、版型、月付及保障条款的接受理由；定性答案不推算市场最优价格。 | D14: 车主：如果提供这份残值或回购保障，是否会改变您的考虑？ 意向者：如果提供这份残值或回购保障，是否会改变您的考虑？ | E14: 1. 具体比例、年限、车况和退出条款 2. 先自由顾虑后展示 3. 不默认60%/70%有效 | F14: 按研究目的选用；有实际经历先谈经历，设想单独记录。 需准备并核验：报价/版型/金融条款；缺材料时暂不执行方案评价。 原追问7条：在“原追问审阅”按题卡编号筛选；详情保留在该表，不能把全部追问逐项念出。 | G14: 2C用户本人提纲：按生活背景—经历—选择—方案的顺序呈现。保留研究任务，按对象区分问法；同义主问合并，细节保留为按条件追问。 原编号题：3条；在“原题映射”按本题编号检索。 | H14: 同意
A15: Q-M6.4-01 | B15: C6 购买顾虑与转化条件 核心信息 FGD：可用 IHV：可用 | C15: 识别购买考虑的剩余障碍与所需证据，意向不等于订单。 | D15: 车主：哪些条件满足后，您才会认真考虑购买目标车型？ 意向者：哪些条件满足后，您才会认真考虑购买目标车型？ | E15: 1. 当前主要障碍 2. 改善一个后是否仍有其他障碍 3. 购买意向与实际承诺分开 | F15: 按研究目的选用；有实际经历先谈经历，设想单独记录。 原追问3条：在“原追问审阅”按题卡编号筛选；详情保留在该表，不能把全部追问逐项念出。 | G15: 2C用户本人提纲：按生活背景—经历—选择—方案的顺序呈现。保留研究任务，按对象区分问法；同义主问合并，细节保留为按条件追问。 原编号题：7条；在“原题映射”按本题编号检索。 | H15: 同意
A16: Q-M6.4-02 | B16: C6 购买顾虑与转化条件 按需选择 FGD：可用 IHV：可用 | C16: 识别购买考虑的剩余障碍与所需证据，意向不等于订单。 | D16: 车主：在准备购买之前，您还需要确认什么？ 意向者：在准备购买之前，您还需要确认什么？ | E16: 1. 产品、品牌、服务、价格或使用条件 2. 向谁确认 3. 什么证据足够 | F16: 按研究目的选用；有实际经历先谈经历，设想单独记录。 原追问0条：在“原追问审阅”按题卡编号筛选；详情保留在该表，不能把全部追问逐项念出。 | G16: 2C用户本人提纲：按生活背景—经历—选择—方案的顺序呈现。保留研究任务，按对象区分问法；同义主问合并，细节保留为按条件追问。 原编号题：0条；在“原题映射”按本题编号检索。 本次补充的新题。 | H16: 同意
A17: Q-M6.4-03 | B17: C6 购买顾虑与转化条件 按需选择 FGD：可用 IHV：可用 | C17: 识别购买考虑的剩余障碍与所需证据，意向不等于订单。 | D17: 车主：对一个新进入市场的品牌，您需要看到什么才愿意考虑？ 意向者：对一个新进入市场的品牌，您需要看到什么才愿意考虑？ | E17: 1. 真实使用、服务承诺、口碑或试驾 2. 必须项与加分项 3. 不直接预设靠低价 | F17: 按研究目的选用；有实际经历先谈经历，设想单独记录。 原追问9条：在“原追问审阅”按题卡编号筛选；详情保留在该表，不能把全部追问逐项念出。 | G17: 2C用户本人提纲：按生活背景—经历—选择—方案的顺序呈现。保留研究任务，按对象区分问法；同义主问合并，细节保留为按条件追问。 原编号题：8条；在“原题映射”按本题编号检索。 | H17: 同意
... A20: Q-M6.5-03 | B20: C6 卖点表达理解 按需选择 FGD：可用 IHV：可用 | C20: 检验卖点理解、可信度和表达方式，不只收集喜欢程度。 | D20: 车主：如果向与您需求相近的人介绍这款产品，您会怎样用一句话说？ 意向者：如果向与您需求相近的人介绍这款产品，您会怎样用一句话说？ | E20: 1. 哪些词自然、哪些像广告 2. 是否准确反映已理解的产品 | F20: 按研究目的选用；有实际经历先谈经历，设想单独记录。 需准备并核验：卖点表达材料；缺材料时暂不执行方案评价。 原追问1条：在“原追问审阅”按题卡编号筛选；详情保留在该表，不能把全部追问逐项念出。 | G20: 2C用户本人提纲：按生活背景—经历—选择—方案的顺序呈现。保留研究任务，按对象区分问法；同义主问合并，细节保留为按条件追问。 原编号题：1条；在“原题映射”按本题编号检索。 | H20: 同意

Sheet 2B-00 执行话术
A2: 2B-00 执行话术
A3: 2张题卡。2B：渠道/专家的客户和市场证据。黄色列供你填写；核心信息已回答就不重复问。
A5: 题卡编号 | B5: 子模块与适用方法 | C5: 研究目的与边界 | D5: 主问：按对象选用 | E5: 核心追问：覆盖信息 | F5: 触发条件与观察任务 | G5: 归并调整与来源 | H5: 确认状态 | I5: 你的修改意见
A6: Q-E0-01 | B6: B0 客户/市场/专业证据 核心信息 经销商 媒体 主机厂专家 | C6: 明确参与许可、记录口径与结束核对，执行环节不计研究模块。 | D6: 经销商：今天我们想了解您在相关业务与市场中的经验。开始前先说明研究目的、记录方式和资料用途；您是否愿意参与？ 媒体：今天我们想了解您在相关业务与市场中的经验。开始前先说明研究目的、记录方式和资料用途；您是否愿意参与？ 主机厂专家：今天我们想了解您在相关业务与市场中的经验。开始前先说明研究目的、记录方式和资料用途；您是否愿意参与？ | E6: 1. 说明预计时长和资料用途；确认参与及录音等许可 2. 您可以不回答不方便分享的问题，商业数据可提供范围或说明未知 3. 职责与机构背景接下一模块，不在此重复介绍 | F6: 仅对熟悉该业务或有相关证据的经销商、媒体/主机厂专家询问；没有接触或数据可答未知。 原追问4条：在“原追问审阅”按题卡编号筛选；详情保留在该表，不能把全部追问逐项念出。 | G6: 2B渠道/专家提纲：本题回答对象是客户或市场，不能当成受访者自己的生活经历。保留研究任务，按对象区分问法；同义主问合并，细节保留为按条件追问。 原编号题：5条；在“原题映射”按本题编号检索。 | H6: 同意
A7: Q-E0-03 | B7: B0 客户/市场/专业证据 核心信息 经销商 媒体 主机厂专家 | C7: 明确参与许可、记录口径与结束核对，执行环节不计研究模块。 | D7: 经销商：还有什么重要情况没有谈到？如果只留下三条建议，您最希望我们记住什么？ 媒体：还有什么重要情况没有谈到？如果只留下三条建议，您最希望我们记住什么？ 主机厂专家：还有什么重要情况没有谈到？如果只留下三条建议，您最希望我们记住什么？ | E7: 1. 核对关键结论是否准确反映受访者意思 2. 区分有证据的观察与有待验证的建议 3. 确认是否有遗漏，不重复全套问题 | F7: 仅对熟悉该业务或有相关证据的经销商、媒体/主机厂专家询问；没有接触或数据可答未知。 原追问1条：在“原追问审阅”按题卡编号筛选；详情保留在该表，不能把全部追问逐项念出。 | G7: 2B渠道/专家提纲：本题回答对象是客户或市场，不能当成受访者自己的生活经历。保留研究任务，按对象区分问法；同义主问合并，细节保留为按条件追问。 原编号题：4条；在“原题映射”按本题编号检索。 | H7: 同意

Sheet 2B-01 受访者与机构背景
A2: 2B-01 受访者与机构背景
A3: 2张题卡。2B：渠道/专家的客户和市场证据。黄色列供你填写；核心信息已回答就不重复问。
A5: 题卡编号 | B5: 子模块与适用方法 | C5: 研究目的与边界 | D5: 主问：按对象选用 | E5: 核心追问：覆盖信息 | F5: 触发条件与观察任务 | G5: 归并调整与来源 | H5: 确认状态 | I5: 你的修改意见
A6: B-CTX-01 | B6: B1 职责与经验 核心信息 经销商 媒体 主机厂专家 | C6: 建立专业受访者及其机构背景，判断后续客户/市场观点的证据边界；这里不问消费者画像。 | D6: 经销商：请介绍您的职责、从业经验，以及目前实际负责的区域、品类或业务。 媒体：请介绍您的职责、从业经验，以及目前实际负责的区域、品类或业务。 主机厂专家：请介绍您的职责、从业经验，以及目前实际负责的区域、品类或业务。 | E6: 1. 受访者职责与直接参与的业务 2. 实际经验年限及近期接触范围 3. 不把本人职位当作对全部市场的了解 | F6: 所有专业受访者；按经销商、媒体、主机厂实际角色展开。 原追问4条：在“原追问审阅”按题卡编号筛选；详情保留在该表，不能把全部追问逐项念出。 | G6: 从原E0背景确认任务拆成职责、机构范围、证据边界三个开场任务；复用来源Q-E0-01。 原编号题：5条；在“原题映射”按本题编号检索。 | H6: 同意
A7: B-CTX-02 | B7: B1 机构与业务范围 核心信息 经销商 媒体 主机厂专家 | C7: 建立专业受访者及其机构背景，判断后续客户/市场观点的证据边界；这里不问消费者画像。 | D7: 经销商：请介绍您所在机构与本次研究相关的业务，以及您能够直接观察的范围。 媒体：请介绍您所在机构与本次研究相关的业务，以及您能够直接观察的范围。 主机厂专家：请介绍您所在机构与本次研究相关的业务，以及您能够直接观察的范围。 | E7: 1. 经销商：门店/集团、代理品牌、业务规模与服务区域 2. 媒体：平台、内容形式、受众和采访/试车范围 3. 主机厂专家：负责市场、产品或工程领域；不要求披露保密信息 | F7: 所有专业受访者；按经销商、媒体、主机厂实际角色展开。 原追问4条：在“原追问审阅”按题卡编号筛选；详情保留在该表，不能把全部追问逐项念出。 | G7: 从原E0背景确认任务拆成职责、机构范围、证据边界三个开场任务；复用来源Q-E0-01。 原编号题：5条；在“原题映射”按本题编号检索。 | H7: 同意

Sheet 2B-02 品牌市场与政策
A2: 2B-02 品牌市场与政策
A3: 4张题卡。2B：渠道/专家的客户和市场证据。黄色列供你填写；核心信息已回答就不重复问。
A5: 题卡编号 | B5: 子模块与适用方法 | C5: 研究目的与边界 | D5: 主问：按对象选用 | E5: 核心追问：覆盖信息 | F5: 触发条件与观察任务 | G5: 归并调整与来源 | H5: 确认状态 | I5: 你的修改意见
A6: B-MKT-01 | B6: B2 竞争格局与品牌表现 核心信息 经销商 媒体 主机厂专家 | C6: 了解目标品类竞争格局、主要品牌及近期变化。 | D6: 经销商：在您负责的区域，目标品类哪些品牌和车型卖得较好？近期有什么变化？ 媒体：从您的报道和观察看，目标品类的主要品牌、车型和竞争变化是什么？ 主机厂专家：在您负责的范围内，目标品类的竞争格局和近期变化是什么？ | E6: 1. 先说明地区、时间和品类口径 2. 区分销量事实、市场观察和个人判断 3. 举一至两个具体品牌或车型例子 | F6: 触发：受访者为经销商，且能够依据近期客户接触、订单、门店记录或售后案例回答。 触发：受访者为媒体，且其报道、试驾、受众调研或公开资料覆盖本议题；不要求回答订单、成交或企业内部数据。 触发：受访者为主机厂专家，且本题属于其市场、产品、工程或渠道职责范围；不要求披露保密信息。 原追问0条：在“原追问审阅”按题卡编号筛选；详情保留在该表，不能把全部追问逐项念出。 | G6: 合并来源题卡：Q-M7.1-01、Q-M7.1-02、Q-M7.1-03。按受访角色与可验证证据重写，减少重复。 原编号题：16条；在“原题映射”按本题编号检索。 | H6: 同意
A7: B-MKT-02 | B7: B2 市场规模与销量预测 核心信息 经销商 媒体 主机厂专家 | C7: 获得有口径的市场规模判断和预测假设。 | D7: 经销商：目标品类近期销量大致怎样？未来一至两年您预计如何变化？ 媒体：公开数据和行业信息显示，目标品类规模和增速怎样？哪些预测较可信？ 主机厂专家：在您负责的范围内，目标品类销量和未来趋势怎样？关键假设是什么？ | E7: 1. 明确数据来源、期间、单位与分母 2. 预测值与实际记录分开 3. 说明最大的不确定因素 | F7: 触发：受访者为经销商，且能够依据近期客户接触、订单、门店记录或售后案例回答。 触发：受访者为媒体，且其报道、试驾、受众调研或公开资料覆盖本议题；不要求回答订单、成交或企业内部数据。 触发：受访者为主机厂专家，且本题属于其市场、产品、工程或渠道职责范围；不要求披露保密信息。 原追问0条：在“原追问审阅”按题卡编号筛选；详情保留在该表，不能把全部追问逐项念出。 | G7: 合并来源题卡：Q-M7.6-01、Q-M7.6-02、Q-M7.6-03。按受访角色与可验证证据重写，减少重复。 原编号题：11条；在“原题映射”按本题编号检索。 | H7: 同意
A8: B-MKT-03 | B8: B2 政策、补贴与税费 核心信息 经销商 媒体 主机厂专家 | C8: 识别当地政策和补贴对需求、价格与动力选择的实际影响。 | D8: 经销商：当地哪些补贴、税费或牌照政策实际影响客户成交？请举订单例子。 媒体：哪些汽车补贴、税费或使用政策最影响市场讨论？依据哪些公开资料？ 主机厂专家：哪些政策影响产品规划或销量？实际影响和预期影响分别是什么？ | E8: 1. 政策名称、有效期和适用车型 2. 对购买时间、预算、动力和车型的影响 3. 政策认知与实际领取分开 | F8: 触发：受访者为经销商，且能够依据近期客户接触、订单、门店记录或售后案例回答。 触发：受访者为媒体，且其报道、试驾、受众调研或公开资料覆盖本议题；不要求回答订单、成交或企业内部数据。 触发：受访者为主机厂专家，且本题属于其市场、产品、工程或渠道职责范围；不要求披露保密信息。 仅在项目组核验政策名称、适用对象和有效期后提示具体政策。 原追问0条：在“原追问审阅”按题卡编号筛选；详情保留在该表，不能把全部追问逐项念出。 | G8: 合并来源题卡：Q-M8.2-01、Q-M8.2-02。按受访角色与可验证证据重写，减少重复。 原编号题：5条；在“原题映射”按本题编号检索。 | H8: 同意
A9: B-MKT-04 | B9: B2 基础设施与能源环境 按需选择 经销商 媒体 主机厂专家 | C9: 判断补能、道路和能源条件对市场发展的限制。 | D9: 经销商：客户最常提到哪些充电、加油或道路条件问题？ 媒体：公开报道和实地观察中，基础设施与能源条件的主要问题是什么？ 主机厂专家：哪些基础设施与能源条件限制了产品或市场发展？ | E9: 1. 说明地区与实际案例 2. 区分城市核心区和其他区域 3. 不按国家标签推定基础设施水平 | F9: 触发：受访者为经销商，且能够依据近期客户接触、订单、门店记录或售后案例回答。 触发：受访者为媒体，且其报道、试驾、受众调研或公开资料覆盖本议题；不要求回答订单、成交或企业内部数据。 触发：受访者为主机厂专家，且本题属于其市场、产品、工程或渠道职责范围；不要求披露保密信息。 原追问0条：在“原追问审阅”按题卡编号筛选；详情保留在该表，不能把全部追问逐项念出。 | G9: 合并来源题卡：Q-M8.1-01、Q-M8.1-02。按受访角色与可验证证据重写，减少重复。 原编号题：3条；在“原题映射”按本题编号检索。 | H9: 同意

Sheet 2B-03 客户画像与用途
A2: 2B-03 客户画像与用途
A3: 4张题卡。2B：渠道/专家的客户和市场证据。黄色列供你填写；核心信息已回答就不重复问。
A5: 题卡编号 | B5: 子模块与适用方法 | C5: 研究目的与边界 | D5: 主问：按对象选用 | E5: 核心追问：覆盖信息 | F5: 触发条件与观察任务 | G5: 归并调整与来源 | H5: 确认状态 | I5: 你的修改意见
A6: B-CUST-01 | B6: B3 核心客户画像 核心信息 经销商 媒体 主机厂专家 | C6: 建立购买目标车型客户的基本画像。 | D6: 经销商：您接触到的目标车型客户通常是什么年龄、职业和家庭阶段？为什么购买？ 媒体：如果您做过受众或用户研究，目标车型人群有哪些稳定特征？ 主机厂专家：现有研究中目标车型用户的核心特征是什么？ | E6: 1. 年龄、职业、家庭阶段与收入只记录可支持的信息 2. 客户原话、样本研究和推断分开 3. 避免用少数个案推断全国 | F6: 触发：受访者为经销商，且能够依据近期客户接触、订单、门店记录或售后案例回答。 触发：受访者为媒体，且其报道、试驾、受众调研或公开资料覆盖本议题；不要求回答订单、成交或企业内部数据。 触发：受访者为主机厂专家，且本题属于其市场、产品、工程或渠道职责范围；不要求披露保密信息。 原追问0条：在“原追问审阅”按题卡编号筛选；详情保留在该表，不能把全部追问逐项念出。 | G6: 合并来源题卡：Q-M1.1-01、Q-M1.1-02、Q-M1.1-04、Q-M1.1-05、Q-M7.2-01。按受访角色与可验证证据重写，减少重复。 原编号题：21条；在“原题映射”按本题编号检索。 | H6: 需修改 | I6: 主机厂的问法很奇怪
A7: B-CUST-02 | B7: B3 购车类型与车辆关系 按需选择 经销商 主机厂专家 | C7: 了解首购、增购、换购及家庭车辆分工。 | D7: 经销商：客户通常是首购、增购还是换购？增购或换购的主要理由是什么？ 主机厂专家：研究中客户通常是首购、增购还是换购？主要驱动分别是什么？ | E7: 1. 现有车辆及使用年限 2. 增购后的车辆分工 3. 换购的触发原因 | F7: 触发：受访者为经销商，且能够依据近期客户接触、订单、门店记录或售后案例回答。 触发：受访者为主机厂专家，且本题属于其市场、产品、工程或渠道职责范围；不要求披露保密信息。 原追问0条：在“原追问审阅”按题卡编号筛选；详情保留在该表，不能把全部追问逐项念出。 | G7: 合并来源题卡：Q-M1.2-01、Q-M1.2-02、Q-M1.2-03。按受访角色与可验证证据重写，减少重复。 原编号题：9条；在“原题映射”按本题编号检索。 | H7: 同意
A8: B-CUST-03 | B8: B3 驾驶者、乘员与决策者 按需选择 经销商 主机厂专家 | C8: 识别车辆使用角色和购买决策链。 | D8: 经销商：目标车型通常由谁开、谁乘坐、谁出钱、谁最终决定？ 主机厂专家：目标用户的驾驶、乘坐和购车决策角色通常如何分工？ | E8: 1. 驾驶者与付款者是否同一人 2. 家庭或组织中影响决策的人 3. 主要乘员和座位安排 | F8: 触发：受访者为经销商，且能够依据近期客户接触、订单、门店记录或售后案例回答。 触发：受访者为主机厂专家，且本题属于其市场、产品、工程或渠道职责范围；不要求披露保密信息。 原追问0条：在“原追问审阅”按题卡编号筛选；详情保留在该表，不能把全部追问逐项念出。 | G8: 合并来源题卡：Q-M1.3-01、Q-M1.3-02、Q-M1.3-03、Q-M1.3-04。按受访角色与可验证证据重写，减少重复。 原编号题：24条；在“原题映射”按本题编号检索。 | H8: 同意
A9: B-CUST-04 | B9: B3 典型用途与高频场景 核心信息 经销商 媒体 主机厂专家 | C9: 了解客户的主要用途、频率和关键任务。 | D9: 经销商：客户买这类车主要用来做什么？哪些场景最常见、最关键？ 媒体：如果有受众研究或采访，目标用户最常见的用途和关键场景是什么？ 主机厂专家：用户研究中目标车型的主要用途、高频场景和关键任务是什么？ | E9: 1. 工作日与周末分别说明 2. 日常高频与低频高后果场景分开 3. 给出具体客户或研究案例 | F9: 触发：受访者为经销商，且能够依据近期客户接触、订单、门店记录或售后案例回答。 触发：受访者为媒体，且其报道、试驾、受众调研或公开资料覆盖本议题；不要求回答订单、成交或企业内部数据。 触发：受访者为主机厂专家，且本题属于其市场、产品、工程或渠道职责范围；不要求披露保密信息。 原追问0条：在“原追问审阅”按题卡编号筛选；详情保留在该表，不能把全部追问逐项念出。 | G9: 合并来源题卡：Q-M2.1-01、Q-M2.1-02、Q-M2.1-03、Q-M2.2-01、Q-M2.2-02。按受访角色与可验证证据重写，减少重复。 原编号题：27条；在“原题映射”按本题编号检索。 | H9: 需修改 | I9: 主机厂的问法很奇怪

Sheet 2B-04 成交与流失
A2: 2B-04 成交与流失
A3: 6张题卡。2B：渠道/专家的客户和市场证据。黄色列供你填写；核心信息已回答就不重复问。
A5: 题卡编号 | B5: 子模块与适用方法 | C5: 研究目的与边界 | D5: 主问：按对象选用 | E5: 核心追问：覆盖信息 | F5: 触发条件与观察任务 | G5: 归并调整与来源 | H5: 确认状态 | I5: 你的修改意见
A6: B-SALE-01 | B6: B4 购买触发与考虑因素 核心信息 经销商 媒体 主机厂专家 | C6: 识别客户为何开始购车，以及最重要的选车因素。 | D6: 经销商：什么事情最容易触发客户购车？客户选车最看重哪三项因素？ 媒体：受众讨论中，哪些事件会触发购车，哪些因素最常被强调？ 主机厂专家：用户研究中主要购车触发和考虑因素是什么？ | E6: 1. 先自由列出再排序 2. 区分客户原话和专业解释 3. 按不同客户类型说明差异 | F6: 触发：受访者为经销商，且能够依据近期客户接触、订单、门店记录或售后案例回答。 触发：受访者为媒体，且其报道、试驾、受众调研或公开资料覆盖本议题；不要求回答订单、成交或企业内部数据。 触发：受访者为主机厂专家，且本题属于其市场、产品、工程或渠道职责范围；不要求披露保密信息。 原追问0条：在“原追问审阅”按题卡编号筛选；详情保留在该表，不能把全部追问逐项念出。 | G6: 合并来源题卡：Q-M3.1-01、Q-M3.4-01、Q-M7.2-02。按受访角色与可验证证据重写，减少重复。 原编号题：16条；在“原题映射”按本题编号检索。 | H6: 同意
A7: B-SALE-02 | B7: B4 候选车型与胜负原因 按需选择 经销商 主机厂专家 | C7: 了解候选清单、成交和流失的真实原因。 | D7: 经销商：客户通常会比较哪些车型？目标车型成交或流失的关键原因是什么？ 主机厂专家：用户研究或销售分析中，目标车型主要与谁竞争？胜负原因是什么？ | E7: 1. 分别举成交和流失案例 2. 价格、产品、品牌、渠道原因分开 3. 不要求媒体回忆订单 | F7: 触发：受访者为经销商，且能够依据近期客户接触、订单、门店记录或售后案例回答。 触发：受访者为主机厂专家，且本题属于其市场、产品、工程或渠道职责范围；不要求披露保密信息。 原追问0条：在“原追问审阅”按题卡编号筛选；详情保留在该表，不能把全部追问逐项念出。 | G7: 合并来源题卡：Q-M3.2-01、Q-M3.2-02、Q-M3.2-04、Q-M3.4-02、Q-M3.4-03、Q-M7.2-03、Q-M7.2-04。按受访角色与可验证证据重写，减少重复。 原编号题：70条；在“原题映射”按本题编号检索。 | H7: 同意
A8: B-SALE-03 | B8: B4 信息来源与传播影响 按需选择 经销商 媒体 主机厂专家 | C8: 了解哪些信息与内容实际影响购车判断。 | D8: 经销商：客户通常从哪里获取信息？哪些内容真正影响到店或购买？ 媒体：哪些媒体、平台和内容最影响受众对目标品类的判断？ 主机厂专家：用户研究中哪些信息来源最影响候选清单和购买决定？ | E8: 1. 信息触达与实际影响分开 2. 举一次改变判断的内容例子 3. 媒体回答传播和受众反馈，不回答订单 | F8: 触发：受访者为经销商，且能够依据近期客户接触、订单、门店记录或售后案例回答。 触发：受访者为媒体，且其报道、试驾、受众调研或公开资料覆盖本议题；不要求回答订单、成交或企业内部数据。 触发：受访者为主机厂专家，且本题属于其市场、产品、工程或渠道职责范围；不要求披露保密信息。 原追问0条：在“原追问审阅”按题卡编号筛选；详情保留在该表，不能把全部追问逐项念出。 | G8: 合并来源题卡：Q-M3.2-03、Q-M7.5-01、Q-M7.5-02。按受访角色与可验证证据重写，减少重复。 原编号题：15条；在“原题映射”按本题编号检索。 | H8: 同意
A9: B-SALE-04 | B9: B4 到店、试驾与服务影响 按需选择 经销商 主机厂专家 | C9: 识别看车流程中影响转化的关键环节。 | D9: 经销商：从进店、看车、试驾到报价，哪些环节最影响客户决定？ 主机厂专家：用户研究中，看车、试驾和销售服务的哪些环节最影响转化？ | E9: 1. 按时间顺序还原 2. 指出中断、犹豫和推进节点 3. 直接问总体规律，再用案例验证 | F9: 触发：受访者为经销商，且能够依据近期客户接触、订单、门店记录或售后案例回答。 触发：受访者为主机厂专家，且本题属于其市场、产品、工程或渠道职责范围；不要求披露保密信息。 原追问0条：在“原追问审阅”按题卡编号筛选；详情保留在该表，不能把全部追问逐项念出。 | G9: 合并来源题卡：Q-M3.3-01、Q-M3.3-02、Q-M3.3-03、Q-M3.3-04。按受访角色与可验证证据重写，减少重复。 原编号题：24条；在“原题映射”按本题编号检索。 | H9: 同意
A10: B-SALE-05 | B10: B4 顾虑与转化条件 核心信息 经销商 媒体 主机厂专家 | C10: 识别客户拒绝购买的顾虑及可改变决定的条件。 | D10: 经销商：客户最常见的顾虑是什么？满足哪些条件后才可能成交？ 媒体：公开讨论中，消费者对目标品牌或车型最常见的顾虑是什么？ 主机厂专家：研究中主要购买障碍和转化条件是什么？ | E10: 1. 顾虑、证据和解决办法分开 2. 区分可解决和结构性障碍 3. 新品牌进入条件单独记录 | F10: 触发：受访者为经销商，且能够依据近期客户接触、订单、门店记录或售后案例回答。 触发：受访者为媒体，且其报道、试驾、受众调研或公开资料覆盖本议题；不要求回答订单、成交或企业内部数据。 触发：受访者为主机厂专家，且本题属于其市场、产品、工程或渠道职责范围；不要求披露保密信息。 原追问0条：在“原追问审阅”按题卡编号筛选；详情保留在该表，不能把全部追问逐项念出。 | G10: 合并来源题卡：Q-M6.4-01、Q-M6.4-02、Q-M6.4-03、Q-M7.2-05。按受访角色与可验证证据重写，减少重复。 原编号题：16条；在“原题映射”按本题编号检索。 | H10: 同意
A11: B-SALE-06 | B11: B4 动力选择与顾虑 按需选择 经销商 媒体 主机厂专家 | C11: 了解不同动力形式的选择逻辑和拒绝原因。 | D11: 经销商：客户怎样在燃油、混动、插混和纯电之间选择？最大的顾虑是什么？ 媒体：受众和市场讨论中，不同动力形式的主要吸引点和顾虑是什么？ 主机厂专家：用户研究中动力选择的主要驱动、障碍和人群差异是什么？ | E11: 1. 先确认受访者熟悉的动力类型 2. 使用条件与价值判断分开 3. 给出相反选择的案例 | F11: 触发：受访者为经销商，且能够依据近期客户接触、订单、门店记录或售后案例回答。 触发：受访者为媒体，且其报道、试驾、受众调研或公开资料覆盖本议题；不要求回答订单、成交或企业内部数据。 触发：受访者为主机厂专家，且本题属于其市场、产品、工程或渠道职责范围；不要求披露保密信息。 原追问0条：在“原追问审阅”按题卡编号筛选；详情保留在该表，不能把全部追问逐项念出。 | G11: 合并来源题卡：Q-M4.1-01、Q-M4.1-02、Q-M4.1-03。按受访角色与可验证证据重写，减少重复。 原编号题：21条；在“原题映射”按本题编号检索。 | H11: 同意

Sheet 2B-05 产品需求与方案
A2: 2B-05 产品需求与方案
A3: 11张题卡。2B：渠道/专家的客户和市场证据。黄色列供你填写；核心信息已回答就不重复问。
A5: 题卡编号 | B5: 子模块与适用方法 | C5: 研究目的与边界 | D5: 主问：按对象选用 | E5: 核心追问：覆盖信息 | F5: 触发条件与观察任务 | G5: 归并调整与来源 | H5: 确认状态 | I5: 你的修改意见
A6: B-PROD-01 | B6: B5 总体产品需求 核心信息 经销商 媒体 主机厂专家 | C6: 先从总体层面了解客户对产品最重要的要求。 | D6: 经销商：客户对这类车最看重哪些产品表现？哪些问题最容易导致放弃？ 媒体：从试驾、报道或受众反馈看，这类车最重要的产品评价维度是什么？ 主机厂专家：用户研究或产品规划中，最重要的产品需求和否决项是什么？ | E6: 1. 先问总体，再按需要进入细项 2. 重要、满意和痛点分别记录 3. 避免把专业偏好当客户需要 | F6: 触发：受访者为经销商，且能够依据近期客户接触、订单、门店记录或售后案例回答。 触发：受访者为媒体，且其报道、试驾、受众调研或公开资料覆盖本议题；不要求回答订单、成交或企业内部数据。 触发：受访者为主机厂专家，且本题属于其市场、产品、工程或渠道职责范围；不要求披露保密信息。 原追问0条：在“原追问审阅”按题卡编号筛选；详情保留在该表，不能把全部追问逐项念出。 | G6: 合并来源题卡：Q-M2.3-01、Q-M2.6-01、Q-M2.6-02、Q-M5.7-01。按受访角色与可验证证据重写，减少重复。 原编号题：17条；在“原题映射”按本题编号检索。 | H6: 同意
A7: B-PROD-02 | B7: B5 乘坐、空间与装载 按需选择 经销商 媒体 主机厂专家 | C7: 了解乘坐舒适、座椅、空间和装载需求。 | D7: 经销商：客户对乘坐舒适、座椅、乘员空间和装载有什么要求？ 媒体：试驾和受众反馈中，乘坐、空间和装载的主要评价是什么？ 主机厂专家：用户研究中，乘坐、空间和装载的关键需求是什么？ | E7: 1. 从总体评价开始，需要时再问座位和物品 2. 说明乘员构成和具体任务 3. 区分需求与对某方案的评价 | F7: 触发：受访者为经销商，且能够依据近期客户接触、订单、门店记录或售后案例回答。 触发：受访者为媒体，且其报道、试驾、受众调研或公开资料覆盖本议题；不要求回答订单、成交或企业内部数据。 触发：受访者为主机厂专家，且本题属于其市场、产品、工程或渠道职责范围；不要求披露保密信息。 原追问0条：在“原追问审阅”按题卡编号筛选；详情保留在该表，不能把全部追问逐项念出。 | G7: 合并来源题卡：Q-M2.3-02、Q-M2.3-03、Q-M5.4-01、Q-M5.4-02、Q-M5.4-03、Q-M5.4-04、Q-M5.4-05、Q-M5.4-06、Q-M5.4-07、Q-M5.4-08。按受访角色与可验证证据重写，减少重复。 原编号题：31条；在“原题映射”按本题编号检索。 | H7: 同意
A8: B-PROD-03 | B8: B5 道路、底盘与气候适应 按需选择 经销商 媒体 主机厂专家 | C8: 了解当地道路、停车和气候对车辆的要求。 | D8: 经销商：当地客户对底盘、通过性、操控、停车和空调有什么具体要求？ 媒体：从道路试驾和报道看，车辆在当地道路与气候下需要满足什么？ 主机厂专家：产品在当地道路、停车和气候条件下需要怎样适配？ | E8: 1. 用具体道路和气候案例回答 2. 底盘、停车和空调分别记录 3. 不按国家标签推断 | F8: 触发：受访者为经销商，且能够依据近期客户接触、订单、门店记录或售后案例回答。 触发：受访者为媒体，且其报道、试驾、受众调研或公开资料覆盖本议题；不要求回答订单、成交或企业内部数据。 触发：受访者为主机厂专家，且本题属于其市场、产品、工程或渠道职责范围；不要求披露保密信息。 原追问0条：在“原追问审阅”按题卡编号筛选；详情保留在该表，不能把全部追问逐项念出。 | G8: 合并来源题卡：Q-M2.4-01、Q-M2.4-02、Q-M2.4-03、Q-M2.4-04、Q-M2.4-05、Q-M2.4-06、Q-M8.4-01、Q-M8.4-02。按受访角色与可验证证据重写，减少重复。 原编号题：29条；在“原题映射”按本题编号检索。 | H8: 同意
A9: B-PROD-04 | B9: B5 座舱、车机与互联 按需选择 经销商 媒体 主机厂专家 | C9: 了解客户对车机、语音、导航、手机互联和座舱体验的要求。 | D9: 经销商：客户对车机、语音、导航、手机互联和座舱功能有哪些要求或抱怨？ 媒体：从测评和受众反馈看，座舱与数字体验的主要优缺点是什么？ 主机厂专家：用户研究中座舱、车机与互联的关键需求是什么？ | E9: 1. 按实际使用任务说明 2. 便利、可靠、学习成本和分心风险分开 3. 当地语言和应用生态单独确认 | F9: 触发：受访者为经销商，且能够依据近期客户接触、订单、门店记录或售后案例回答。 触发：受访者为媒体，且其报道、试驾、受众调研或公开资料覆盖本议题；不要求回答订单、成交或企业内部数据。 触发：受访者为主机厂专家，且本题属于其市场、产品、工程或渠道职责范围；不要求披露保密信息。 原追问0条：在“原追问审阅”按题卡编号筛选；详情保留在该表，不能把全部追问逐项念出。 | G9: 合并来源题卡：Q-M2.5-01、Q-M2.5-02、Q-M2.5-03、Q-M2.5-04、Q-M2.5-05、Q-M2.5-06、Q-M2.5-07、Q-M2.5-08、Q-M5.5-01、Q-M5.5-02、Q-M5.5-03。按受访角色与可验证证据重写，减少重复。 原编号题：45条；在“原题映射”按本题编号检索。 | H9: 同意
A10: B-PROD-05 | B10: B5 补能与续航要求 按需选择 经销商 媒体 主机厂专家 | C10: 了解电动车客户的充电条件、续航底线和等待容忍度。 | D10: 经销商：对新能源客户，实际充电条件、续航底线和等待时间要求是什么？ 媒体：仅在做过电动车试驾或基础设施报道时：用户补能与续航讨论的核心问题是什么？ 主机厂专家：新能源用户研究中，充电条件、续航底线和时间要求是什么？ | E10: 1. 家充、单位充和公共充电分开 2. 实际经历与理想要求分开 3. 媒体不回答个人充电习惯 | F10: 触发：受访者为经销商，且能够依据近期客户接触、订单、门店记录或售后案例回答。 触发：受访者为媒体，且其报道、试驾、受众调研或公开资料覆盖本议题；不要求回答订单、成交或企业内部数据。 触发：受访者为主机厂专家，且本题属于其市场、产品、工程或渠道职责范围；不要求披露保密信息。 仅研究新能源或替代动力且受访者有相应证据时出现。 原追问0条：在“原追问审阅”按题卡编号筛选；详情保留在该表，不能把全部追问逐项念出。 | G10: 合并来源题卡：Q-M4.2-01、Q-M4.2-02、Q-M4.2-03、Q-M4.2-04、Q-M4.2-05、Q-M4.2-06、Q-M4.3-01、Q-M4.3-02、Q-M4.3-03。按受访角色与可验证证据重写，减少重复。 原编号题：42条；在“原题映射”按本题编号检索。 | H10: 同意
A11: B-PROD-06 | B11: B5 驾驶辅助信任边界 按需选择 经销商 媒体 主机厂专家 | C11: 了解客户愿意使用驾驶辅助的场景、顾虑和验证需求。 | D11: 经销商：客户在哪些场景愿意或不愿意使用驾驶辅助？需要什么证据才会信任？ 媒体：测评和舆论中，驾驶辅助最受关注的能力、风险和误解是什么？ 主机厂专家：用户研究中驾驶辅助的使用边界和信任条件是什么？ | E11: 1. 功能使用与品牌宣传认知分开 2. 具体道路和失效场景 3. 区分客户体验和技术验证 | F11: 触发：受访者为经销商，且能够依据近期客户接触、订单、门店记录或售后案例回答。 触发：受访者为媒体，且其报道、试驾、受众调研或公开资料覆盖本议题；不要求回答订单、成交或企业内部数据。 触发：受访者为主机厂专家，且本题属于其市场、产品、工程或渠道职责范围；不要求披露保密信息。 原追问0条：在“原追问审阅”按题卡编号筛选；详情保留在该表，不能把全部追问逐项念出。 | G11: 合并来源题卡：Q-M4.4-01、Q-M4.4-02、Q-M4.4-03、Q-M4.4-04。按受访角色与可验证证据重写，减少重复。 原编号题：16条；在“原题映射”按本题编号检索。 | H11: 同意
A12: B-PROD-07 | B12: B5 安全、耐久与质量 按需选择 经销商 媒体 主机厂专家 | C12: 了解客户对安全、质量、耐久和维修性的要求。 | D12: 经销商：客户最关心哪些安全、质量和耐久问题？什么问题会直接否决购买？ 媒体：测评和公开讨论中，安全、质量和耐久的主要关注是什么？ 主机厂专家：产品规划中安全、质量、耐久和维修性的关键门槛是什么？ | E12: 1. 主动安全与被动安全分开 2. 实际故障、担忧和标准分开 3. 避免未经验证的技术结论 | F12: 触发：受访者为经销商，且能够依据近期客户接触、订单、门店记录或售后案例回答。 触发：受访者为媒体，且其报道、试驾、受众调研或公开资料覆盖本议题；不要求回答订单、成交或企业内部数据。 触发：受访者为主机厂专家，且本题属于其市场、产品、工程或渠道职责范围；不要求披露保密信息。 原追问0条：在“原追问审阅”按题卡编号筛选；详情保留在该表，不能把全部追问逐项念出。 | G12: 合并来源题卡：Q-M4.5-01、Q-M4.5-02、Q-M4.5-03、Q-M4.5-04。按受访角色与可验证证据重写，减少重复。 原编号题：20条；在“原题映射”按本题编号检索。 | H12: 同意
A13: B-PROD-08 | B13: B5 产品概念总体评价 核心信息 经销商 媒体 主机厂专家 | C13: 评价产品概念的吸引力、差异和改进方向。 | D13: 经销商：看完产品概念，您认为它最能打动哪些客户？主要优势和短板是什么？ 媒体：从传播和市场理解看，这个概念最容易被怎样理解？哪些信息不清楚？ 主机厂专家：从产品与市场匹配看，这个概念的核心价值和主要缺口是什么？ | E13: 1. 先记录自发理解 2. 优势、短板和目标客户分开 3. 不假设存在未展示的备选方案 | F13: 触发：受访者为经销商，且能够依据近期客户接触、订单、门店记录或售后案例回答。 触发：受访者为媒体，且其报道、试驾、受众调研或公开资料覆盖本议题；不要求回答订单、成交或企业内部数据。 触发：受访者为主机厂专家，且本题属于其市场、产品、工程或渠道职责范围；不要求披露保密信息。 仅在项目已展示完整产品概念材料后触发。 原追问0条：在“原追问审阅”按题卡编号筛选；详情保留在该表，不能把全部追问逐项念出。 | G13: 合并来源题卡：Q-M5.1-01、Q-M5.1-02、Q-M5.1-03。按受访角色与可验证证据重写，减少重复。 原编号题：5条；在“原题映射”按本题编号检索。 | H13: 同意
A14: B-PROD-09 | B14: B5 外观与内饰方案 按需选择 经销商 媒体 主机厂专家 | C14: 评价车型轮廓、前后造型、内饰设计和材质。 | D14: 经销商：基于展示材料，车型轮廓、前脸、车尾和内饰哪些更容易被客户接受？ 媒体：从设计传播和受众反馈看，外观和内饰传达什么形象？ 主机厂专家：从产品定义看，外观和内饰方案的目标人群匹配度怎样？ | E14: 1. 使用“车型轮廓”而非“体态” 2. 整体评价后再问细节 3. 区分审美偏好和成交影响 | F14: 触发：受访者为经销商，且能够依据近期客户接触、订单、门店记录或售后案例回答。 触发：受访者为媒体，且其报道、试驾、受众调研或公开资料覆盖本议题；不要求回答订单、成交或企业内部数据。 触发：受访者为主机厂专家，且本题属于其市场、产品、工程或渠道职责范围；不要求披露保密信息。 仅展示可比较的外观或内饰材料后触发；不要求经销商准备示卡。 原追问0条：在“原追问审阅”按题卡编号筛选；详情保留在该表，不能把全部追问逐项念出。 | G14: 合并来源题卡：Q-M5.2-01、Q-M5.2-02、Q-M5.2-03、Q-M5.2-04、Q-M5.3-01、Q-M5.3-02、Q-M5.3-03。按受访角色与可验证证据重写，减少重复。 原编号题：37条；在“原题映射”按本题编号检索。 | H14: 同意
A15: B-PROD-10 | B15: B5 配置组合与取舍 核心信息 经销商 媒体 主机厂专家 | C15: 判断配置优先级、必选项和可删减项。 | D15: 经销商：哪些配置最能影响成交？哪些配置客户不愿付费或可以删减？ 媒体：哪些配置最有传播价值，哪些容易造成误解或低感知？ 主机厂专家：配置组合中哪些是目标用户必选项，哪些可按版本区分？ | E15: 1. 必须、加分、无感和反感分开 2. 愿意付费与口头喜欢分开 3. 高温地区问隔热和空调降温 | F15: 触发：受访者为经销商，且能够依据近期客户接触、订单、门店记录或售后案例回答。 触发：受访者为媒体，且其报道、试驾、受众调研或公开资料覆盖本议题；不要求回答订单、成交或企业内部数据。 触发：受访者为主机厂专家，且本题属于其市场、产品、工程或渠道职责范围；不要求披露保密信息。 评价具体配置时须先提供配置清单、功能边界和价格口径。 原追问0条：在“原追问审阅”按题卡编号筛选；详情保留在该表，不能把全部追问逐项念出。 | G15: 合并来源题卡：Q-M5.6-01、Q-M5.6-02、Q-M5.6-03、Q-M5.6-04、Q-M5.6-05、Q-M5.6-06、Q-M5.6-07、Q-M5.7-01、Q-M5.7-02、Q-M5.7-03、Q-M5.7-04。按受访角色与可验证证据重写，减少重复。 原编号题：41条；在“原题映射”按本题编号检索。 | H15: 同意
A16: B-PROD-11 | B16: B5 本地化与工程适配 按需选择 经销商 媒体 主机厂专家 | C16: 识别语言、数字生态、法规和工程适配要求。 | D16: 经销商：客户对本地语言、应用、支付、连接和售后诊断有哪些要求？ 媒体：从测评和报道看，哪些本地化问题最影响使用和口碑？ 主机厂专家：在语言、数字生态、法规和工程方面需要哪些本地化适配？ | E16: 1. 实际兼容问题与未来建议分开 2. 说明当地平台或法规来源 3. 不把单个应用偏好当市场需求 | F16: 触发：受访者为经销商，且能够依据近期客户接触、订单、门店记录或售后案例回答。 触发：受访者为媒体，且其报道、试驾、受众调研或公开资料覆盖本议题；不要求回答订单、成交或企业内部数据。 触发：受访者为主机厂专家，且本题属于其市场、产品、工程或渠道职责范围；不要求披露保密信息。 原追问0条：在“原追问审阅”按题卡编号筛选；详情保留在该表，不能把全部追问逐项念出。 | G16: 合并来源题卡：Q-M8.3-01、Q-M8.3-02、Q-M8.4-03、Q-M8.4-04。按受访角色与可验证证据重写，减少重复。 原编号题：5条；在“原题映射”按本题编号检索。 | H16: 同意

Sheet 2B-06 价格版型与盈利
A2: 2B-06 价格版型与盈利
A3: 4张题卡。2B：渠道/专家的客户和市场证据。黄色列供你填写；核心信息已回答就不重复问。
A5: 题卡编号 | B5: 子模块与适用方法 | C5: 研究目的与边界 | D5: 主问：按对象选用 | E5: 核心追问：覆盖信息 | F5: 触发条件与观察任务 | G5: 归并调整与来源 | H5: 确认状态 | I5: 你的修改意见
A6: B-PRICE-01 | B6: B6 客户预算与实际成交价 核心信息 经销商 主机厂专家 | C6: 了解预算形成、实付价格和价格弹性。 | D6: 经销商：客户预算通常怎样形成？实际成交价与最初预算相差多少，为什么？ 主机厂专家：用户研究或销售分析中，预算形成和价格弹性怎样？ | E6: 1. 统一币种、税费、优惠和配置口径 2. 报价、实付和预测分开 3. 可用区间回答 | F6: 触发：受访者为经销商，且能够依据近期客户接触、订单、门店记录或售后案例回答。 触发：受访者为主机厂专家，且本题属于其市场、产品、工程或渠道职责范围；不要求披露保密信息。 原追问0条：在“原追问审阅”按题卡编号筛选；详情保留在该表，不能把全部追问逐项念出。 | G6: 合并来源题卡：Q-M3.1-02、Q-M3.1-03、Q-M7.3-01。按受访角色与可验证证据重写，减少重复。 原编号题：10条；在“原题映射”按本题编号检索。 | H6: 同意
A7: B-PRICE-02 | B7: B6 支付与金融方案 按需选择 经销商 主机厂专家 | C7: 了解支付方式、金融接受度和关键条款。 | D7: 经销商：客户常用哪些支付或金融方式？哪些费用和条款最影响选择？ 主机厂专家：用户研究中，支付与金融方案的主要需求和障碍是什么？ | E7: 1. 首付、月供、期限、总成本和退出条件 2. 使用意愿与实际办理分开 3. 只提示已核验的当地金融产品 | F7: 触发：受访者为经销商，且能够依据近期客户接触、订单、门店记录或售后案例回答。 触发：受访者为主机厂专家，且本题属于其市场、产品、工程或渠道职责范围；不要求披露保密信息。 原追问0条：在“原追问审阅”按题卡编号筛选；详情保留在该表，不能把全部追问逐项念出。 | G7: 合并来源题卡：Q-M3.5-01、Q-M3.5-02、Q-M3.5-03、Q-M6.3-03。按受访角色与可验证证据重写，减少重复。 原编号题：8条；在“原题映射”按本题编号检索。 | H7: 同意
A8: B-PRICE-03 | B8: B6 价格、版型与残值 核心信息 经销商 媒体 主机厂专家 | C8: 判断版型价差、配置价值和残值保障的影响。 | D8: 经销商：客户怎样在不同版型之间选择？哪些价差合理？残值或回购保障会改变决定吗？ 媒体：从公开信息和受众讨论看，价格与版型设置是否容易理解？ 主机厂专家：价格、版型和残值方案怎样影响目标用户的价值判断？ | E8: 1. 价差对应的配置价值 2. 残值承诺的条件和可信度 3. 媒体只评价公开价格信息和理解度 | F8: 触发：受访者为经销商，且能够依据近期客户接触、订单、门店记录或售后案例回答。 触发：受访者为媒体，且其报道、试驾、受众调研或公开资料覆盖本议题；不要求回答订单、成交或企业内部数据。 触发：受访者为主机厂专家，且本题属于其市场、产品、工程或渠道职责范围；不要求披露保密信息。 仅在项目提供已核验的价格、配置和条款后评价。 原追问0条：在“原追问审阅”按题卡编号筛选；详情保留在该表，不能把全部追问逐项念出。 | G8: 合并来源题卡：Q-M3.4-05、Q-M6.3-01、Q-M6.3-02、Q-M6.3-04、Q-M7.3-02。按受访角色与可验证证据重写，减少重复。 原编号题：18条；在“原题映射”按本题编号检索。 | H8: 同意
A9: B-PRICE-04 | B9: B6 经销商盈利与资源投入 按需选择 经销商 主机厂专家 | C9: 评估经销商销售目标、毛利、返利和投入意愿。 | D9: 经销商：销售这类车的毛利、返利、库存和服务投入怎样？什么条件下门店愿意重点推动？ 主机厂专家：渠道策略中如何平衡销量、经销商收益和资源投入？ | E9: 1. 销量、毛利、返利和库存分别说明 2. 历史数据与目标预测分开 3. 允许用范围回答 | F9: 触发：受访者为经销商，且能够依据近期客户接触、订单、门店记录或售后案例回答。 触发：受访者为主机厂专家，且本题属于其市场、产品、工程或渠道职责范围；不要求披露保密信息。 仅对能够接触经营口径的经销商或渠道负责人提问；媒体不出现。 原追问0条：在“原追问审阅”按题卡编号筛选；详情保留在该表，不能把全部追问逐项念出。 | G9: 合并来源题卡：Q-M7.3-03、Q-M7.3-04。按受访角色与可验证证据重写，减少重复。 原编号题：6条；在“原题映射”按本题编号检索。 | H9: 同意

Sheet 2B-07 渠道营销与服务
A2: 2B-07 渠道营销与服务
A3: 4张题卡。2B：渠道/专家的客户和市场证据。黄色列供你填写；核心信息已回答就不重复问。
A5: 题卡编号 | B5: 子模块与适用方法 | C5: 研究目的与边界 | D5: 主问：按对象选用 | E5: 核心追问：覆盖信息 | F5: 触发条件与观察任务 | G5: 归并调整与来源 | H5: 确认状态 | I5: 你的修改意见
A6: B-CHAN-01 | B6: B7 渠道覆盖与购车便利 按需选择 经销商 媒体 主机厂专家 | C6: 了解网点、试驾、交付和服务覆盖的缺口。 | D6: 经销商：客户在哪些地区或环节最难看车、试驾、交付或维修？ 媒体：从报道和消费者反馈看，渠道与服务覆盖有哪些明显缺口？ 主机厂专家：渠道规划中网点、试驾、交付和服务的主要缺口是什么？ | E6: 1. 按地区和环节说明 2. 覆盖存在与服务质量分开 3. 给出具体案例或数据 | F6: 触发：受访者为经销商，且能够依据近期客户接触、订单、门店记录或售后案例回答。 触发：受访者为媒体，且其报道、试驾、受众调研或公开资料覆盖本议题；不要求回答订单、成交或企业内部数据。 触发：受访者为主机厂专家，且本题属于其市场、产品、工程或渠道职责范围；不要求披露保密信息。 原追问0条：在“原追问审阅”按题卡编号筛选；详情保留在该表，不能把全部追问逐项念出。 | G6: 合并来源题卡：Q-M7.4-01、Q-M7.4-02、Q-M7.4-03。按受访角色与可验证证据重写，减少重复。 原编号题：8条；在“原题映射”按本题编号检索。 | H6: 同意
A7: B-CHAN-02 | B7: B7 门店能力与销售支持 按需选择 经销商 主机厂专家 | C7: 了解门店展示、人员、试驾车和销售工具需求。 | D7: 经销商：门店要把这类车卖好，需要哪些人员、展车、试驾车和销售工具？ 主机厂专家：渠道端需要哪些培训、物料、试驾和运营支持？ | E7: 1. 当前能力与未来需求分开 2. 说明最影响转化的缺口 3. 媒体不出现 | F7: 触发：受访者为经销商，且能够依据近期客户接触、订单、门店记录或售后案例回答。 触发：受访者为主机厂专家，且本题属于其市场、产品、工程或渠道职责范围；不要求披露保密信息。 原追问0条：在“原追问审阅”按题卡编号筛选；详情保留在该表，不能把全部追问逐项念出。 | G7: 合并来源题卡：Q-M7.4-04、Q-M7.5-03。按受访角色与可验证证据重写，减少重复。 原编号题：6条；在“原题映射”按本题编号检索。 | H7: 同意
A8: B-CHAN-03 | B8: B7 售后成本与服务体验 按需选择 经销商 媒体 主机厂专家 | C8: 了解客户持有成本、售后痛点和服务改进机会。 | D8: 经销商：客户最在意哪些持有成本和售后问题？哪些问题最影响复购和口碑？ 媒体：公开讨论中，持有成本和售后服务的主要问题是什么？ 主机厂专家：用户研究和服务数据中，持有成本与售后痛点是什么？ | E8: 1. 燃料/电费、保险、保养和维修分开 2. 实际案例与担忧分开 3. 说明处理结果 | F8: 触发：受访者为经销商，且能够依据近期客户接触、订单、门店记录或售后案例回答。 触发：受访者为媒体，且其报道、试驾、受众调研或公开资料覆盖本议题；不要求回答订单、成交或企业内部数据。 触发：受访者为主机厂专家，且本题属于其市场、产品、工程或渠道职责范围；不要求披露保密信息。 原追问0条：在“原追问审阅”按题卡编号筛选；详情保留在该表，不能把全部追问逐项念出。 | G8: 合并来源题卡：Q-M2.7-02、Q-M2.7-03、Q-M2.7-04、Q-M8.5-01、Q-M8.5-02、Q-M8.5-03。按受访角色与可验证证据重写，减少重复。 原编号题：11条；在“原题映射”按本题编号检索。 | H8: 同意
A9: B-CHAN-04 | B9: B7 获客渠道与内容 核心信息 经销商 媒体 主机厂专家 | C9: 识别有效触达渠道、内容形式和转化链路。 | D9: 经销商：哪些渠道和内容最能带来有效线索和到店？ 媒体：哪些平台、内容形式和表达最能影响目标受众？ 主机厂专家：传播和获客中哪些渠道及内容最有效？依据是什么？ | E9: 1. 曝光、互动、线索、到店和成交分开 2. 媒体重点回答受众和传播反馈 3. 给出近期具体活动或内容案例 | F9: 触发：受访者为经销商，且能够依据近期客户接触、订单、门店记录或售后案例回答。 触发：受访者为媒体，且其报道、试驾、受众调研或公开资料覆盖本议题；不要求回答订单、成交或企业内部数据。 触发：受访者为主机厂专家，且本题属于其市场、产品、工程或渠道职责范围；不要求披露保密信息。 原追问0条：在“原追问审阅”按题卡编号筛选；详情保留在该表，不能把全部追问逐项念出。 | G9: 合并来源题卡：Q-M7.5-01、Q-M7.5-02、Q-M7.5-04、Q-M7.5-05、Q-M7.5-06。按受访角色与可验证证据重写，减少重复。 原编号题：15条；在“原题映射”按本题编号检索。 | H9: 同意

Sheet 2B-08 品牌机会与策略
A2: 2B-08 品牌机会与策略
A3: 5张题卡。2B：渠道/专家的客户和市场证据。黄色列供你填写；核心信息已回答就不重复问。
A5: 题卡编号 | B5: 子模块与适用方法 | C5: 研究目的与边界 | D5: 主问：按对象选用 | E5: 核心追问：覆盖信息 | F5: 触发条件与观察任务 | G5: 归并调整与来源 | H5: 确认状态 | I5: 你的修改意见
A6: B-BRAND-01 | B6: B8 品类意义与品牌形象 核心信息 经销商 媒体 主机厂专家 | C6: 理解目标品类和品牌在当地市场的意义与形象。 | D6: 经销商：客户怎样理解这类车和目标品牌？常用哪些词描述？ 媒体：公众和媒体怎样描述这类车和目标品牌？哪些印象最稳定？ 主机厂专家：品牌研究中，目标品类与品牌的核心形象是什么？ | E6: 1. 自发印象先于提示 2. 正面、负面和中性印象分开 3. 说明印象来源 | F6: 触发：受访者为经销商，且能够依据近期客户接触、订单、门店记录或售后案例回答。 触发：受访者为媒体，且其报道、试驾、受众调研或公开资料覆盖本议题；不要求回答订单、成交或企业内部数据。 触发：受访者为主机厂专家，且本题属于其市场、产品、工程或渠道职责范围；不要求披露保密信息。 原追问0条：在“原追问审阅”按题卡编号筛选；详情保留在该表，不能把全部追问逐项念出。 | G6: 合并来源题卡：Q-M1.4-01、Q-M1.4-02、Q-M1.4-03、Q-M6.1-01、Q-M6.1-02、Q-M6.1-03。按受访角色与可验证证据重写，减少重复。 原编号题：33条；在“原题映射”按本题编号检索。 | H6: 同意
A7: B-BRAND-02 | B7: B8 中国品牌优劣势 按需选择 经销商 媒体 主机厂专家 | C7: 了解当地市场对中国汽车品牌的优势、顾虑和进入门槛。 | D7: 经销商：客户怎么看中国汽车品牌？主要优势和顾虑是什么？ 媒体：当地媒体和公众如何讨论中国汽车品牌？哪些议题最影响认知？ 主机厂专家：中国品牌进入当地市场的主要机会、风险和能力缺口是什么？ | E7: 1. 品牌事实与国别印象分开 2. 用具体品牌或事件说明 3. 允许不同中国品牌表现不同 | F7: 触发：受访者为经销商，且能够依据近期客户接触、订单、门店记录或售后案例回答。 触发：受访者为媒体，且其报道、试驾、受众调研或公开资料覆盖本议题；不要求回答订单、成交或企业内部数据。 触发：受访者为主机厂专家，且本题属于其市场、产品、工程或渠道职责范围；不要求披露保密信息。 原追问0条：在“原追问审阅”按题卡编号筛选；详情保留在该表，不能把全部追问逐项念出。 | G7: 合并来源题卡：Q-M6.4-03、Q-M8.5-01、Q-M8.5-02。按受访角色与可验证证据重写，减少重复。 原编号题：13条；在“原题映射”按本题编号检索。 | H7: 同意
A8: B-BRAND-03 | B8: B8 品牌揭示与概念匹配 按需选择 经销商 媒体 主机厂专家 | C8: 评价品牌名称对产品概念判断的影响。 | D8: 经销商：知道品牌后，您对产品概念和目标客户的判断有什么变化？ 媒体：品牌揭示后，概念的传播含义和可信度发生什么变化？ 主机厂专家：品牌与产品概念是否匹配？哪些认知需要建立或修正？ | E8: 1. 保存揭示前评价 2. 记录变化和原因 3. 不由主持人口头暗示品牌水平 | F8: 触发：受访者为经销商，且能够依据近期客户接触、订单、门店记录或售后案例回答。 触发：受访者为媒体，且其报道、试驾、受众调研或公开资料覆盖本议题；不要求回答订单、成交或企业内部数据。 触发：受访者为主机厂专家，且本题属于其市场、产品、工程或渠道职责范围；不要求披露保密信息。 仅展示产品概念并完成品牌揭示后触发。 原追问0条：在“原追问审阅”按题卡编号筛选；详情保留在该表，不能把全部追问逐项念出。 | G8: 合并来源题卡：Q-M6.2-01、Q-M6.2-02。按受访角色与可验证证据重写，减少重复。 原编号题：3条；在“原题映射”按本题编号检索。 | H8: 同意
A9: B-BRAND-04 | B9: B8 卖点理解与传播 核心信息 经销商 媒体 主机厂专家 | C9: 检验卖点是否易懂、可信、有区分度并适合传播。 | D9: 经销商：这些卖点中，哪些客户容易理解并愿意相信？哪些难以成交？ 媒体：从传播角度，哪些卖点清楚、有新闻价值或容易被质疑？ 主机厂专家：哪些卖点最能支持定位和转化？需要什么证据？ | E9: 1. 先让受访者用自己的话解释 2. 理解、可信和吸引力分开 3. 媒体回答传播与受众反应，不回答成交率 | F9: 触发：受访者为经销商，且能够依据近期客户接触、订单、门店记录或售后案例回答。 触发：受访者为媒体，且其报道、试驾、受众调研或公开资料覆盖本议题；不要求回答订单、成交或企业内部数据。 触发：受访者为主机厂专家，且本题属于其市场、产品、工程或渠道职责范围；不要求披露保密信息。 仅在项目展示卖点文案和证据材料后触发。 原追问0条：在“原追问审阅”按题卡编号筛选；详情保留在该表，不能把全部追问逐项念出。 | G9: 合并来源题卡：Q-M6.5-01、Q-M6.5-02、Q-M6.5-03。按受访角色与可验证证据重写，减少重复。 原编号题：11条；在“原题映射”按本题编号检索。 | H9: 同意
A10: B-BRAND-05 | B10: B8 市场进入条件与风险 核心信息 经销商 媒体 主机厂专家 | C10: 识别品牌进入、交付、售后和持续运营的关键条件。 | D10: 经销商：一个新品牌要在当地被客户接受，需要先解决哪些渠道、交付和售后问题？ 媒体：从市场监督和公众信任角度，新品牌进入当地最大的风险是什么？ 主机厂专家：品牌长期运营需要满足哪些产品、渠道、服务和合规条件？ | E10: 1. 进入前条件与进入后运营分开 2. 风险、证据和缓解办法分开 3. 媒体语言聚焦公开信任与传播风险 | F10: 触发：受访者为经销商，且能够依据近期客户接触、订单、门店记录或售后案例回答。 触发：受访者为媒体，且其报道、试驾、受众调研或公开资料覆盖本议题；不要求回答订单、成交或企业内部数据。 触发：受访者为主机厂专家，且本题属于其市场、产品、工程或渠道职责范围；不要求披露保密信息。 原追问0条：在“原追问审阅”按题卡编号筛选；详情保留在该表，不能把全部追问逐项念出。 | G10: 合并来源题卡：Q-M8.5-01、Q-M8.5-02、Q-M8.5-03。按受访角色与可验证证据重写，减少重复。 原编号题：6条；在“原题映射”按本题编号检索。 | H10: 同意

Sheet 2B-09 商务与组织采购
A2: 2B-09 商务与组织采购
A3: 9张题卡。2B：商务与组织的真实采购和使用经历。黄色列供你填写；核心信息已回答就不重复问。
A5: 题卡编号 | B5: 子模块与适用方法 | C5: 研究目的与边界 | D5: 主问：按对象选用 | E5: 核心追问：覆盖信息 | F5: 触发条件与观察任务 | G5: 归并调整与来源 | H5: 确认状态 | I5: 你的修改意见
A6: B-ORG-01 | B6: B9 组织与车辆使用背景 核心信息 商务/组织 | C6: 建立组织业务、车辆用途和受访者职责背景。 | D6: 商务/组织：请介绍贵组织的业务、现有车辆及您的职责。车辆主要承担哪些任务？ | E6: 1. 组织规模和业务类型 2. 车辆数量、类型和主要任务 3. 受访者是否直接参与使用或采购 | F6: 触发：受访者为商务/组织车辆的采购决策者、车队管理者或实际使用负责人，并能讲述本组织真实经历。 原追问0条：在“原追问审阅”按题卡编号筛选；详情保留在该表，不能把全部追问逐项念出。 | G6: 合并来源题卡：Q-M1.1-01、Q-M1.2-01、Q-M1.3-01。按受访角色与可验证证据重写，减少重复。 原编号题：21条；在“原题映射”按本题编号检索。 | H6: 同意
A7: B-ORG-02 | B7: B9 车辆使用者与任务 按需选择 商务/组织 | C7: 了解驾驶者、乘员、货物和关键使用场景。 | D7: 商务/组织：车辆通常由谁驾驶、搭载谁或什么货物？哪些任务最关键？ | E7: 1. 日常高频和低频高后果任务 2. 乘员、货物、里程和道路条件 3. 车辆停运的业务后果 | F7: 触发：受访者为商务/组织车辆的采购决策者、车队管理者或实际使用负责人，并能讲述本组织真实经历。 原追问0条：在“原追问审阅”按题卡编号筛选；详情保留在该表，不能把全部追问逐项念出。 | G7: 合并来源题卡：Q-M1.3-02、Q-M2.1-01、Q-M2.2-01、Q-M2.3-01。按受访角色与可验证证据重写，减少重复。 原编号题：25条；在“原题映射”按本题编号检索。 | H7: 同意
A8: B-ORG-03 | B8: B9 组织采购决策流程 核心信息 商务/组织 | C8: 了解需求提出、预算、试用、审批和供应商选择。 | D8: 商务/组织：从提出需求到最终采购，通常由谁参与，经过哪些审批和试用环节？ | E8: 1. 使用者、采购、财务和批准者 2. 招标或供应商准入要求 3. 试用和技术验证要求 | F8: 触发：受访者为商务/组织车辆的采购决策者、车队管理者或实际使用负责人，并能讲述本组织真实经历。 原追问0条：在“原追问审阅”按题卡编号筛选；详情保留在该表，不能把全部追问逐项念出。 | G8: 合并来源题卡：Q-M1.3-03、Q-M3.3-01、Q-M3.3-02。按受访角色与可验证证据重写，减少重复。 原编号题：30条；在“原题映射”按本题编号检索。 | H8: 同意
A9: B-ORG-04 | B9: B9 采购考虑因素 核心信息 商务/组织 | C9: 明确组织选车的评价标准、权重和否决项。 | D9: 商务/组织：组织采购车辆时最看重哪些因素？请选出最重要的三项，并说明不能接受的底线。 | E9: 1. 业务适配、可靠性、成本、服务和品牌 2. 考虑因素先自由列出再排序 3. 合规或内部制度否决项 | F9: 触发：受访者为商务/组织车辆的采购决策者、车队管理者或实际使用负责人，并能讲述本组织真实经历。 原追问0条：在“原追问审阅”按题卡编号筛选；详情保留在该表，不能把全部追问逐项念出。 | G9: 合并来源题卡：Q-M3.4-01、Q-M3.4-04、Q-M5.7-01。按受访角色与可验证证据重写，减少重复。 原编号题：12条；在“原题映射”按本题编号检索。 | H9: 同意
A10: B-ORG-05 | B10: B9 预算与全生命周期成本 核心信息 商务/组织 | C10: 了解采购预算、使用成本、停运成本和残值。 | D10: 商务/组织：采购预算怎样确定？组织如何评估能源、保险、保养、维修、停运和残值等总成本？ | E10: 1. 统一币种、税费和期限 2. 一次性采购与全生命周期成本分开 3. 说明可支持调整预算的业务价值 | F10: 触发：受访者为商务/组织车辆的采购决策者、车队管理者或实际使用负责人，并能讲述本组织真实经历。 原追问0条：在“原追问审阅”按题卡编号筛选；详情保留在该表，不能把全部追问逐项念出。 | G10: 合并来源题卡：Q-M3.1-02、Q-M3.1-03、Q-M2.7-01、Q-M6.3-04。按受访角色与可验证证据重写，减少重复。 原编号题：12条；在“原题映射”按本题编号检索。 | H10: 同意
A11: B-ORG-06 | B11: B9 动力与补能条件 按需选择 商务/组织 | C11: 判断组织选择动力形式的运营条件和补能约束。 | D11: 商务/组织：组织怎样选择燃油、混动、插混或纯电？停车地点、充电设施、里程和排班会怎样影响选择？ | E11: 1. 每日里程和最长任务 2. 停车地点和安装条件 3. 补能时间对运营的影响 | F11: 触发：受访者为商务/组织车辆的采购决策者、车队管理者或实际使用负责人，并能讲述本组织真实经历。 仅研究新能源或替代动力时进入补能细节。 原追问0条：在“原追问审阅”按题卡编号筛选；详情保留在该表，不能把全部追问逐项念出。 | G11: 合并来源题卡：Q-M4.1-02、Q-M4.2-01、Q-M4.2-04、Q-M4.3-03。按受访角色与可验证证据重写，减少重复。 原编号题：24条；在“原题映射”按本题编号检索。 | H11: 同意
A12: B-ORG-07 | B12: B9 产品与配置要求 按需选择 商务/组织 | C12: 了解组织任务对空间、耐久、安全、隐私和配置的要求。 | D12: 商务/组织：从实际业务任务看，车辆在空间、承载、舒适、安全、耐久、隐私和配置上必须满足什么？ | E12: 1. 用具体任务和失败后果说明 2. 必须、加分和不需要分开 3. 接待、公务与营运用途分别记录 | F12: 触发：受访者为商务/组织车辆的采购决策者、车队管理者或实际使用负责人，并能讲述本组织真实经历。 原追问0条：在“原追问审阅”按题卡编号筛选；详情保留在该表，不能把全部追问逐项念出。 | G12: 合并来源题卡：Q-M2.3-03、Q-M4.5-01、Q-M5.4-01、Q-M5.6-04、Q-M5.6-05。按受访角色与可验证证据重写，减少重复。 原编号题：18条；在“原题映射”按本题编号检索。 | H12: 同意
A13: B-ORG-08 | B13: B9 品牌与服务要求 按需选择 商务/组织 | C13: 了解品牌、接待形象、服务网络和供应商能力的要求。 | D13: 商务/组织：品牌形象、客户接待、服务网络和供应商能力会怎样影响组织采购？ | E13: 1. 客户或合作方要求 2. 内部采购制度 3. 交付、维修和备件保障 | F13: 触发：受访者为商务/组织车辆的采购决策者、车队管理者或实际使用负责人，并能讲述本组织真实经历。 原追问0条：在“原追问审阅”按题卡编号筛选；详情保留在该表，不能把全部追问逐项念出。 | G13: 合并来源题卡：Q-M6.2-02、Q-M7.4-01、Q-M8.5-01。按受访角色与可验证证据重写，减少重复。 原编号题：6条；在“原题映射”按本题编号检索。 | H13: 同意
A14: B-ORG-09 | B14: B9 组织补贴与政策 核心信息 商务/组织 | C14: 了解补贴、税费、牌照和合规政策对组织采购的影响。 | D14: 商务/组织：贵组织知道并实际使用过哪些车辆补贴、税费减免、牌照或运营政策？这些政策怎样影响采购？ | E14: 1. 是否符合资格并实际申请 2. 对采购时间、数量、动力和预算的影响 3. 政策取消后的替代方案 | F14: 触发：受访者为商务/组织车辆的采购决策者、车队管理者或实际使用负责人，并能讲述本组织真实经历。 先问自发认知；只有项目组已核验政策名称、对象和有效期后才提示。 原追问0条：在“原追问审阅”按题卡编号筛选；详情保留在该表，不能把全部追问逐项念出。 | G14: 合并来源题卡：Q-M8.2-01、Q-M8.2-02。按受访角色与可验证证据重写，减少重复。 原编号题：5条；在“原题映射”按本题编号检索。 | H14: 同意

Sheet 原追问审阅
A2: 582条原追问审阅
A3: 原文全部保留。绑定为本轮编辑建议；跨题卡记录需分任务取用。旧参数与当地事实未作时效核验。
A5: 来源ID | B5: 建议关联题卡 | C5: 处理方式 | D5: 原追问原文 | E5: 调整后的追问或处理建议 | F5: 触发条件 | G5: 材料与事实待确认 | H5: 调整理由 | I5: 原始位置 | J5: 确认状态 | K5: 你的修改意见
A6: S01-R007 | B6: Q-M1.1-01 | C6: 保留并规范 | D6: 【主持人注意/追问：是否有子女，年龄；是否与老人同住？家庭结构是怎样的？】 | E6: 是否有子女，年龄；是否与老人同住？家庭结构是怎样的？ | F6: 相关经历或研究目标成立才追问；已回答不重复。 | G6: 无需国家或参数事实前提；仍需结合回答取用 | H6: 保留原有细节作为按回答展开的提示；先自由回答，不逐项念清单。 | I6: FGD-1. 人群画像，第7行 原父题候选：S01-R006 | J6: 待审阅
A7: S01-R009 | B7: Q-M1.1-02 | C7: 保留并规范 | D7: 【主持人注意/追问：户外运动/自驾游？购物/逛街？居家休闲？社交聚会？海滩活动？这些爱好是否与用车场景关联？有没有"憧憬场景"？】 | E7: 户外运动/自驾游？购物/逛街？居家休闲？社交聚会？海滩活动？这些爱好是否与用车场景关联？有没有"憧憬场景"？ | F7: 相关经历或研究目标成立才追问；已回答不重复。 | G7: 无需国家或参数事实前提；仍需结合回答取用 | H7: 保留原有细节作为按回答展开的提示；先自由回答，不逐项念清单。 | I7: FGD-1. 人群画像，第9行 原父题候选：S01-R008 | J7: 待审阅
A8: S01-R013 | B8: Q-M1.2-01 | C8: 保留并规范 | D8: 【主持人注意/追问：这辆车是家中第几辆车？其他车用途是什么？这辆车和家中其他车如何分工？】 | E8: 这辆车是家中第几辆车？其他车用途是什么？这辆车和家中其他车如何分工？ | F8: 相关经历或研究目标成立才追问；已回答不重复。 | G8: 无需国家或参数事实前提；仍需结合回答取用 | H8: 保留原有细节作为按回答展开的提示；先自由回答，不逐项念清单。 | I8: FGD-1. 人群画像，第13行 原父题候选：S01-R012 | J8: 待审阅
A9: S01-R015 | B9: Q-M1.3-01 Q-M1.3-03 | C9: 保留并规范 | D9: 【主持人注意/追问：是否作为家庭第二辆通勤专用车？太太/伴侣是否也会开？家中谁对这辆车的购买决策影响最大？】 | E9: 是否作为家庭第二辆通勤专用车？太太/伴侣是否也会开？家中谁对这辆车的购买决策影响最大？ | F9: 相关经历或研究目标成立才追问；已回答不重复。 | G9: 无需国家或参数事实前提；仍需结合回答取用 | H9: 保留原有细节作为按回答展开的提示；先自由回答，不逐项念清单。 | I9: FGD-1. 人群画像，第15行 原父题候选：S01-R014 | J9: 待审阅
A10: S01-R017 | B10: Q-M1.3-02 | C10: 保留并规范 | D10: 【主持人注意/追问：如果是满员的情况下，每个位置一般都是谁坐在那里？】 | E10: 如果是满员的情况下，每个位置一般都是谁坐在那里？ | F10: 相关经历或研究目标成立才追问；已回答不重复。 | G10: 无需国家或参数事实前提；仍需结合回答取用 | H10: 保留原有细节作为按回答展开的提示；先自由回答，不逐项念清单。 | I10: FGD-1. 人群画像，第17行 原父题候选：S01-R016 | J10: 待审阅
A11: S01-R019 | B11: Q-M4.1-01 | C11: 保留并规范 | D11: 【主持人注意/追问：预算限制？城市通勤便利性？增购代步需求？环保考量？停车优势？【调研国家】城市的拥堵和停车难是否是关键驱动？】 | E11: 预算限制？城市通勤便利性？增购代步需求？环保考量？停车优势？调研国家城市的拥堵和停车难是否是关键驱动？ | F11: 相关经历或研究目标成立才追问；已回答不重复。 | G11: 本地适用性、日期与事实前提待项目核验 | H11: 保留原有细节作为按回答展开的提示；先自由回答，不逐项念清单。 | I11: FGD-1. 人群画像，第19行 原父题候选：S01-R018 | J11: 待审阅
A12: S01-R021 | B12: Q-M3.1-01 Q-M8.2-01 | C12: 保留并规范 | D12: 【主持人注意/追问：预算限制？城市通勤便利性？增购代步需求？环保考量？停车优势？【调研城市】的拥堵和停车难是否是关键驱动？EV税收优惠（IPI/ICMS/IPVA）的影响？】 | E12: 预算限制？城市通勤便利性？增购代步需求？环保考量？停车优势？调研城市的拥堵和停车难是否是关键驱动？EV税收优惠（IPI/ICMS/IPVA）的影响？ | F12: 相关经历或研究目标成立才追问；已回答不重复。 | G12: 本地适用性、日期与事实前提待项目核验 | H12: 保留原有细节作为按回答展开的提示；先自由回答，不逐项念清单。 | I12: FGD-1. 人群画像，第21行 原父题候选：S01-R020 | J12: 待审阅
A13: S01-R023 | B13: Q-M4.1-02 Q-M4.2-06 | C13: 保留并规范 | D13: 【主持人注意/追问：预算限制？城市通勤便利性？对BEV的顾虑？充电不便？【调研国家】弹性燃料汽车（Flex-Fuel）的吸引力？品牌信任？保值率？【调研城市】的拥堵和停车难是否是关键驱动？】 | E13: 预算限制？城市通勤便利性？对BEV的顾虑？充电不便？调研国家弹性燃料汽车（Flex-Fuel）的吸引力？品牌信任？保值率？调研城市的拥堵和停车难是否是关键驱动？ | F13: 相关经历或研究目标成立才追问；已回答不重复。 | G13: 本地适用性、日期与事实前提待项目核验 | H13: 保留原有细节作为按回答展开的提示；先自由回答，不逐项念清单。 | I13: FGD-1. 人群画像，第23行 原父题候选：S01-R022 | J13: 待审阅
A14: S01-R025 | B14: Q-M1.4-01 | C14: 改写/拆分 | D14: 【主持人注意/追问：社会认知：代步车？年轻人/女性用车？环保先锋？在【调研国家】，开BEV小车是否有某种"身份标签"？开ICE小车呢？】 | E14: 您如何描述这类车的使用者、用途和形象？与其他类别相比，有哪些适合与不适合的地方？先自由表达，再按相关情境追问。 | F14: 相关经历或研究目标成立才追问；已回答不重复。 | G14: 本地适用性、日期与事实前提待项目核验 | H14: 删除年轻人/女性专用、保姆车、成功人士等先行标签。 | I14: FGD-1. 人群画像，第25行 原父题候选：S01-R024 | J14: 待审阅
A15: S01-R027 | B15: Q-M1.4-02 | C15: 保留并规范 | D15: 【主持人注意/追问：可爱？灵巧？科技？精致？皮实耐用？运动？如果只能保留一个，您保留哪个？为什么？】 | E15: 可爱？灵巧？科技？精致？皮实耐用？运动？如果只能保留一个，您保留哪个？为什么？ | F15: 相关经历或研究目标成立才追问；已回答不重复。 | G15: 无需国家或参数事实前提；仍需结合回答取用 | H15: 保留原有细节作为按回答展开的提示；先自由回答，不逐项念清单。 | I15: FGD-1. 人群画像，第27行 原父题候选：S01-R026 | J15: 待审阅
A16: S01-R029 | B16: Q-M4.2-04 | C16: 保留并规范 | D16: 【主持人注意/追问：是否有固定车位？公寓管理方（物业管理）对安装充电桩的态度？您是否有条件安装家充桩？如果不能安装，这是否是您放弃BEV的原因之一？】 | E16: 是否有固定车位？公寓管理方（物业管理）对安装充电桩的态度？您是否有条件安装家充桩？如果不能安装，这是否是您放弃BEV的原因之一？ | F16: 相关经历或研究目标成立才追问；已回答不重复。 | G16: 无需国家或参数事实前提；仍需结合回答取用 | H16: 保留原有细节作为按回答展开的提示；先自由回答，不逐项念清单。 | I16: FGD-1. 人群画像，第29行 原父题候选：S01-R028 | J16: 待审阅
A17: S01-R030 | B17: Q-M4.2-04 | C17: 改写/拆分 | D17: 【主持人注意/追问：是否有固定车位？公寓管理方（condo/Apt）对安装充电桩的态度？【调研国家】公寓占比较高，充电桩安装审批是关键障碍——您是否遇到过这个问题？】 | E17: 您的停车地点是否允许安装充电设施？已向谁确认、需要哪些审批、费用或供电改造？哪些还未知？ | F17: 相关经历或研究目标成立才追问；已回答不重复。 | G17: 本地适用性、日期与事实前提待项目核验 | H17: 删除公寓占比高和审批必然是障碍的市场假设。 | I17: FGD-1. 人群画像，第30行 原父题候选：S01-R028 | J17: 待审阅
... A587: S49-R014 | B587: Q-M8.5-03 | C587: 保留并规范 | D587: 【例如：高度本地化的高等级智能辅助驾驶能力、品牌自营的超级充电网络覆盖率、还是针对高净值人群量身定做的层级化尊享服务体系？】 | E587: 例如：高度本地化的高等级智能辅助驾驶能力、品牌自营的超级充电网络覆盖率、还是针对高净值人群量身定做的层级化尊享服务体系？ | F587: 相关经历或研究目标成立才追问；已回答不重复。 | G587: 无需国家或参数事实前提；仍需结合回答取用 | H587: 保留原有细节作为按回答展开的提示；先自由回答，不逐项念清单。 | I587: 主机厂-5. 核心风险预警与未来演进机会展望，第14行 原父题候选：S49-R013 | J587: 待审阅

Sheet 原题映射
A2: 703条原编号题去向
A3: 来源：访谈提纲模块问题汇总-2.xlsx。保留原文、工作表和行号；多目标题表示需要拆分研究任务。
A5: 来源ID | B5: 原工作表 | C5: 原题号 | D5: 原行号 | E5: 原题原文 | F5: 对应题卡 | G5: 处理方式 | H5: 调整理由 | I5: 原组别 | J5: 原备注
A6: S01-R006 | B6: FGD-1. 人群画像 | C6: Q1 | D6: 6 | E6: 请您简单介绍一下自己，比如年龄、职业，还有家里有哪些家庭成员？ | F6: Q-M1.1-01 | G6: 归并/改写 | H6: 逐题分配语义任务，同义主问归并，原文与组别保留供核对。 | J6: 三国同源
A7: S01-R008 | B7: FGD-1. 人群画像 | C7: Q2 | D7: 8 | E7: 兴趣爱好 – 留意兴趣爱好是否带上大件物品（如钓鱼竿，高尔夫球包，冲浪板） | F7: Q-M1.1-02 | G7: 归并/改写 | H7: 逐题分配语义任务，同义主问归并，原文与组别保留供核对。 | J7: 三国同源
A8: S01-R010 | B8: FGD-1. 人群画像 | C8: Q3 | D8: 10 | E8: 典型的工作日是怎么出行的？去哪里？平均里程？路况 | F8: Q-M2.1-01 | G8: 归并/改写 | H8: 逐题分配语义任务，同义主问归并，原文与组别保留供核对。 | J8: 三国同源
A9: S01-R011 | B9: FGD-1. 人群画像 | C9: Q4 | D9: 11 | E9: 典型的周末/假日是怎么出行的？去哪里？平均里程？路况 | F9: Q-M2.1-01 | G9: 归并/改写 | H9: 逐题分配语义任务，同义主问归并，原文与组别保留供核对。 | J9: 三国同源
A10: S01-R012 | B10: FGD-1. 人群画像 | C10: Q5 | D10: 12 | E10: 您家目前一共有几辆车？分别是什么品牌和车型？ | F10: Q-M1.2-01 | G10: 归并/改写 | H10: 逐题分配语义任务，同义主问归并，原文与组别保留供核对。 | J10: 三国同源
A11: S01-R014 | B11: FGD-1. 人群画像 | C11: Q6 | D11: 14 | E11: 这辆车主要是谁在开？其他家庭成员会开吗？ | F11: Q-M1.3-01 | G11: 归并/改写 | H11: 逐题分配语义任务，同义主问归并，原文与组别保留供核对。 | J11: 三国同源
A12: S01-R016 | B12: FGD-1. 人群画像 | C12: Q7 | D12: 16 | E12: 平时用车，车上通常坐几个人？是否经常出现3-4人以上同乘的情况？ | F12: Q-M1.3-02 | G12: 归并/改写 | H12: 逐题分配语义任务，同义主问归并，原文与组别保留供核对。 | J12: 三国同源
A13: S01-R018 | B13: FGD-1. 人群画像 | C13: Q8 | D13: 18 | E13: 当初为什么决定购买一辆纯电小车（小于4米），而不是更大的轿车/SUV，或者传统燃油车？ | F13: Q-M4.1-01 | G13: 归并/改写 | H13: 逐题分配语义任务，同义主问归并，原文与组别保留供核对。 | J13: 意大利+印尼同源；措辞有差异，见分国家版
A14: S01-R020 | B14: FGD-1. 人群画像 | C14: Q9 | D14: 20 | E14: 当初为什么决定购买一辆纯电小车（小于4米），而不是更大的轿车/SUV，或者传统燃油车？ | F14: Q-M4.1-01 | G14: 归并/改写 | H14: 逐题分配语义任务，同义主问归并，原文与组别保留供核对。 | I14: BEV组 | J14: 仅巴西
A15: S01-R022 | B15: FGD-1. 人群画像 | C15: Q10 | D15: 22 | E15: 当初为什么决定购买一辆4米燃油小车，而不是纯电车或更大的车型？ | F15: Q-M4.1-02 | G15: 归并/改写 | H15: 逐题分配语义任务，同义主问归并，原文与组别保留供核对。 | I15: ICE组 | J15: 仅巴西
A16: S01-R024 | B16: FGD-1. 人群画像 | C16: Q11 | D16: 24 | E16: 在您的社交圈中，驾驶这类纯电小车的人多吗？他们对这一车型有怎样的看法？ | F16: Q-M1.4-03 | G16: 归并/改写 | H16: 逐题分配语义任务，同义主问归并，原文与组别保留供核对。 | J16: 三国同源
A17: S01-R026 | B17: FGD-1. 人群画像 | C17: Q12 | D17: 26 | E17: 您认为一辆理想的A00级纯电小车应该给人什么感觉？请用三个关键词形容？ | F17: Q-M1.4-02 | G17: 归并/改写 | H17: 逐题分配语义任务，同义主问归并，原文与组别保留供核对。 | J17: 三国同源
A18: S01-R028 | B18: FGD-1. 人群画像 | C18: Q13 | D18: 28 | E18: 请问您的住宅是以下哪种类型？（独栋/联排/公寓/其他）是否有固定车位？ | F18: Q-M4.2-04 | G18: 归并/改写 | H18: 逐题分配语义任务，同义主问归并，原文与组别保留供核对。 | J18: 三国同源
A19: S01-R031 | B19: FGD-1. 人群画像 | C19: Q14 | D19: 31 | E19: 请您回忆一下，当初是什么具体的事件或变化，让您产生了"需要买这辆车"的想法？ | F19: Q-M3.1-01 | G19: 归并/改写 | H19: 逐题分配语义任务，同义主问归并，原文与组别保留供核对。 | J19: 三国同源
A20: S01-R034 | B20: FGD-1. 人群画像 | C20: Q15 | D20: 34 | E20: 这辆车是您家庭新增的一辆车（增购），还是替换了原来的一辆车（换购），还是您的第一辆车（首购）？ | F20: Q-M1.2-02 | G20: 归并/改写 | H20: 逐题分配语义任务，同义主问归并，原文与组别保留供核对。 | J20: 三国同源
A21: S02-R006 | B21: FGD-2. 使用场景 | C21: Q1 | D21: 6 | E21: 请描述您一周内使用这辆车的典型场景。 | F21: Q-M2.1-01 | G21: 归并/改写 | H21: 逐题分配语义任务，同义主问归并，原文与组别保留供核对。 | J21: 三国同源
A22: S02-R008 | B22: FGD-2. 使用场景 | C22: Q2 | D22: 8 | E22: 最常用的使用场景是什么？每次行驶的大致里程和时长是多少？ | F22: Q-M2.1-02 | G22: 归并/改写 | H22: 逐题分配语义任务，同义主问归并，原文与组别保留供核对。 | J22: 三国同源
A23: S02-R010 | B23: FGD-2. 使用场景 | C23: Q3 | D23: 10 | E23: 出行时一半是什么样的路况？多大可能经过非铺装路面？ | F23: Q-M2.4-02 | G23: 归并/改写 | H23: 逐题分配语义任务，同义主问归并，原文与组别保留供核对。 | J23: 仅巴西
A24: S02-R012 | B24: FGD-2. 使用场景 | C24: Q4 | D24: 12 | E24: 是否有多人同乘（满载或接近满载）一起出行的经历？通常前往哪里？后排坐谁？身高体重？ | F24: Q-M2.2-02 | G24: 归并/改写 | H24: 逐题分配语义任务，同义主问归并，原文与组别保留供核对。 | J24: 三国同源
A25: S02-R014 | B25: FGD-2. 使用场景 | C25: Q5 | D25: 14 | E25: 偶尔需要跑相对较远的路程（如超过1小时车程）时，您会如何规划？是否会有里程顾虑？ | F25: Q-M2.2-03 | G25: 归并/改写 | H25: 逐题分配语义任务，同义主问归并，原文与组别保留供核对。 | J25: 三国同源
A26: S02-R017 | B26: FGD-2. 使用场景 | C26: Q6 | D26: 17 | E26: 后备箱空间日常够用吗？后排座椅放倒功能是否常用？ | F26: Q-M2.3-01 | G26: 归并/改写 | H26: 逐题分配语义任务，同义主问归并，原文与组别保留供核对。 | J26: 三国同源
A27: S02-R020 | B27: FGD-2. 使用场景 | C27: Q7 | D27: 20 | E27: 您开车时最常用的车机功能TOP3是什么？ | F27: Q-M2.5-01 | G27: 归并/改写 | H27: 逐题分配语义任务，同义主问归并，原文与组别保留供核对。 | J27: 三国同源
... A54: S05-R019 | B54: FGD-4. 购车考虑因素 | C54: Q6 | D54: 19 | E54: 是否对比过离地间隙？ | F54: Q-M4.5-04 | G54: 归并/改写 | H54: 逐题分配语义任务，同义主问归并，原文与组别保留供核对。 | J54: 仅巴西
A55: S05-R020 | B55: FGD-4. 购车考虑因素 | C55: Q7 | D55: 20 | E55: 最终为什么选择了现在这辆？请说出最重要的3个原因。 | F55: Q-M3.4-02 | G55: 归并/改写 | H55: 逐题分配语义任务，同义主问归并，原文与组别保留供核对。 | I55: BEV组 | J55: 仅巴西
A56: S05-R022 | B56: FGD-4. 购车考虑因素 | C56: Q8 | D56: 22 | E56: 最终为什么选择了燃油车而不是纯电车？请说出最重要的3个原因。 | F56: Q-M4.1-02 | G56: 归并/改写 | H56: 逐题分配语义任务，同义主问归并，原文与组别保留供核对。 | I56: ICE组 | J56: 仅巴西
A57: S05-R024 | B57: FGD-4. 购车考虑因素 | C57: Q9 | D57: 24 | E57: 在对比过程中，是否有哪辆车让您心动但最终放弃了？为什么放弃？ | F57: Q-M3.4-03 | G57: 归并/改写 | H57: 逐题分配语义任务，同义主问归并，原文与组别保留供核对。 | J57: 三国同源
A58: S05-R026 | B58: FGD-4. 购车考虑因素 | C58: Q10 | D58: 26 | E58: 您是从什么渠道了解到这辆车的？ | F58: Q-M3.2-03 | G58: 归并/改写 | H58: 逐题分配语义任务，同义主问归并，原文与组别保留供核对。 | J58: 三国同源
A59: S05-R030 | B59: FGD-4. 购车考虑因素 | C59: Q11 | D59: 30 | E59: 当时去店里看实车或者试驾的时候，重点体验了哪些地方？ | F59: Q-M3.3-02 | G59: 归并/改写 | H59: 逐题分配语义任务，同义主问归并，原文与组别保留供核对。 | J59: 三国同源
A60: S05-R032 | B60: FGD-4. 购车考虑因素 | C60: Q12 | D60: 32 | E60: 从有购车想法到最终下单，花了多长时间？从有想法到去dealer花了多少时间？从第一次去dealer到下单花了多久？下单到提车花了多久？ | F60: Q-M3.3-01 | G60: 归并/改写 | H60: 逐题分配语义任务，同义主问归并，原文与组别保留供核对。 | J60: 三国同源
A61: S05-R033 | B61: FGD-4. 购车考虑因素 | C61: Q13 | D61: 33 | E61: 如何选择dealer？Dealer数量多少是一个考量因素吗？ | F61: Q-M3.3-03 | G61: 归并/改写 | H61: 逐题分配语义任务，同义主问归并，原文与组别保留供核对。 | J61: 三国同源
A62: S05-R038 | B62: FGD-4. 购车考虑因素 | C62: Q14 | D62: 38 | E62: 请描述那辆让您心动却最终没有选择BEV的具体原因——心动在哪里、放弃的"一票否决"因素到底是什么？ | F62: Q-M4.1-02 | G62: 归并/改写 | H62: 逐题分配语义任务，同义主问归并，原文与组别保留供核对。 | J62: 仅印尼
A63: S05-R039 | B63: FGD-4. 购车考虑因素 | C63: Q15 | D63: 39 | E63: 您目前在考虑这辆ICE车之前，先考虑过哪些车型？请列出您的候选清单。 | F63: Q-M3.2-01 | G63: 归并/改写 | H63: 逐题分配语义任务，同义主问归并，原文与组别保留供核对。 | I63: ICE 车主：购车考虑过程与BEV放弃原因 | J63: 仅意大利
A64: S05-R041 | B64: FGD-4. 购车考虑因素 | C64: Q16 | D64: 41 | E64: 这些候选车型中，当时排在第一位的是哪款BEV？为什么？ | F64: Q-M3.2-02 | G64: 归并/改写 | H64: 逐题分配语义任务，同义主问归并，原文与组别保留供核对。 | I64: ICE 车主：购车考虑过程与BEV放弃原因 | J64: 仅意大利
A65: S05-R043 | B65: FGD-4. 购车考虑因素 | C65: Q17 | D65: 43 | E65: 请描述那辆让您心动却最终没有选择BEV的具体原因——心动在哪里、放弃的"一票否决"因素到底是什么？ | F65: Q-M4.1-02 | G65: 归并/改写 | H65: 逐题分配语义任务，同义主问归并，原文与组别保留供核对。 | I65: ICE 车主：购车考虑过程与BEV放弃原因 | J65: 仅意大利
A66: S05-R044 | B66: FGD-4. 购车考虑因素 | C66: Q18 | D66: 44 | E66: 您目前在考虑这辆ICE车之前，先考虑过哪些车型？请列出您的候选清单。 | F66: Q-M3.2-01 | G66: 归并/改写 | H66: 逐题分配语义任务，同义主问归并，原文与组别保留供核对。 | I66: ICE 车主：购车考虑过程与BEV放弃原因（仅FGD2 ICE组使用此模块） | J66: 仅巴西
A67: S05-R046 | B67: FGD-4. 购车考虑因素 | C67: Q19 | D67: 46 | E67: 这些候选车型中，当时排在第一位的是哪款BEV？为什么？ | F67: Q-M3.2-02 | G67: 归并/改写 | H67: 逐题分配语义任务，同义主问归并，原文与组别保留供核对。 | I67: ICE 车主：购车考虑过程与BEV放弃原因（仅FGD2 ICE组使用此模块） | J67: 仅巴西
A68: S05-R048 | B68: FGD-4. 购车考虑因素 | C68: Q20 | D68: 48 | E68: 请描述那辆让您心动却最终没有选择BEV的具体原因——心动在哪里、放弃的"一票否决"因素到底是什么？ | F68: Q-M4.1-02 | G68: 归并/改写 | H68: 逐题分配语义任务，同义主问归并，原文与组别保留供核对。 | I68: ICE 车主：购车考虑过程与BEV放弃原因（仅FGD2 ICE组使用此模块） | J68: 仅巴西
A69: S05-R050 | B69: FGD-4. 购车考虑因素 | C69: Q21 | D69: 50 | E69: 如果现在有一辆中国品牌的4米纯电小车，配置好、价格有竞争力，并且解决了您当时放弃BEV的"一票否决"因素，您会考虑购买吗？ | F69: Q-M6.4-01 | G69: 归并/改写 | H69: 逐题分配语义任务，同义主问归并，原文与组别保留供核对。 | I69: ICE 车主：购车考虑过程与BEV放弃原因（仅FGD2 ICE组使用此模块） | J69: 仅巴西
A70: S05-R051 | B70: FGD-4. 购车考虑因素 | C70: Q22 | D70: 51 | E70: 当初购买这辆车时，您选择的是哪种支付方式？全款、贷款、还是联合购车基金？为什么选择这种方案？ | F70: Q-M3.5-01 | G70: 归并/改写 | H70: 逐题分配语义任务，同义主问归并，原文与组别保留供核对。 | J70: 三国同源；措辞有差异，见分国家版
A71: S05-R053 | B71: FGD-4. 购车考虑因素 | C71: Q23 | D71: 53 | E71: 您身边买车的朋友/家人，大部分选择哪种支付方式？在【调研国家】，贷款购车和长租（Noleggio a lungo termine）哪种更主流？ | F71: Q-M3.5-02 | G71: 归并/改写 | H71: 逐题分配语义任务，同义主问归并，原文与组别保留供核对。 | J71: 三国同源；措辞有差异，见分国家版
A72: S05-R055 | B72: FGD-4. 购车考虑因素 | C72: Q24 | D72: 55 | E72: 对于4米纯电小车（如S-Car），您更倾向于全款购买、贷款购买、还是联合购车基金？为什么？ | F72: Q-M3.5-03 | G72: 归并/改写 | H72: 逐题分配语义任务，同义主问归并，原文与组别保留供核对。 | J72: 三国同源；措辞有差异，见分国家版
A73: S05-R057 | B73: FGD-4. 购车考虑因素 | C73: Q25 | D73: 57 | E73: 如果一辆四米纯电小车的月供/月租在当地主流小车月租价格区间内（含保险和保养），您觉得这个价位是否有吸引力？ | F73: Q-M6.3-03 | G73: 归并/改写 | H73: 逐题分配语义任务，同义主问归并，原文与组别保留供核对。 | J73: 三国同源；措辞有差异，见分国家版
A74: S05-R059 | B74: FGD-4. 购车考虑因素 | C74: Q26 | D74: 59 | E74: 如果厂家提供"残值保障/三年后回购"方案，是否会增加您的购买信心？ | F74: Q-M6.3-04 | G74: 归并/改写 | H74: 逐题分配语义任务，同义主问归并，原文与组别保留供核对。 | J74: 三国同源
A75: S06-R006 | B75: FGD-5. 产品评价 | C75: Q1 | D75: 6 | E75: 您对BYD Seagull/Dolphin Surf这款车怎么看？最大的优点和缺点分别是什么？ | F75: Q-M3.2-04 | G75: 归并/改写 | H75: 逐题分配语义任务，同义主问归并，原文与组别保留供核对。 | J75: 意大利+印尼同源
A76: S06-R008 | B76: FGD-5. 产品评价 | C76: Q2 | D76: 8 | E76: 观察其他的对标竞品用户，你们的车【比亚迪 Seagull (BYD Atto 1), 吉利 Geometry EX2, 五菱 Binguo EV (缤果), VinFast VF5, 奇瑞 QQ3 EV】，最大的优点和缺点分别是什么？ | F76: Q-M3.2-04 | G76: 归并/改写 | H76: 逐题分配语义任务，同义主问归并，原文与组别保留供核对。 | J76: 仅印尼
A77: S06-R010 | B77: FGD-5. 产品评价 | C77: Q3 | D77: 10 | E77: 您是否了解或体验过其他A00级纯电小车（如Renault 5、Citroen e-C3、Fiat Grande Panda）？印象如何？ | F77: Q-M3.2-04 | G77: 归并/改写 | H77: 逐题分配语义任务，同义主问归并，原文与组别保留供核对。 | J77: 仅意大利
A78: S06-R017 | B78: FGD-5. 产品评价 | C78: Q4 | D78: 17 | E78: 您对BYD Dolphin Mini这款车怎么看？最大的优点和缺点分别是什么？ | F78: Q-M3.2-04 | G78: 归并/改写 | H78: 逐题分配语义任务，同义主问归并，原文与组别保留供核对。 | I78: BEV组 | J78: 仅巴西
A79: S06-R019 | B79: FGD-5. 产品评价 | C79: Q5 | D79: 19 | E79: 观察其他的对标竞品用户，你们的车【BYD Dolphin Mini, Geely Geometry EX2, Renault Kwid E-Tech, Chevrolet Spark EUV, GWM Ora 03】，最大的优点和缺点分别是什么？ | F79: Q-M3.2-04 | G79: 归并/改写 | H79: 逐题分配语义任务，同义主问归并，原文与组别保留供核对。 | I79: BEV组 | J79: 仅巴西
A80: S06-R020 | B80: FGD-5. 产品评价 | C80: Q6 | D80: 20 | E80: 您对试驾/比较过的BEV车型（如BYD Dolphin Mini, Renault Kwid E-Tech等）怎么看？最大的优点和缺点分别是什么？ | F80: Q-M3.2-04 | G80: 归并/改写 | H80: 逐题分配语义任务，同义主问归并，原文与组别保留供核对。 | I80: ICE组 | J80: 仅巴西
A81: S06-R022 | B81: FGD-5. 产品评价 | C81: Q7 | D81: 22 | E81: 您是否了解或体验过其他纯电小车？印象如何？ | F81: Q-M3.2-04 | G81: 归并/改写 | H81: 逐题分配语义任务，同义主问归并，原文与组别保留供核对。 | I81: ICE组 | J81: 仅巴西
A82: S06-R023 | B82: FGD-5. 产品评价 | C82: Q8 | D82: 23 | E82: 您是否了解或体验过其他纯电小车（如当地主流纯电车型）？印象如何？ | F82: Q-M3.2-04 | G82: 归并/改写 | H82: 逐题分配语义任务，同义主问归并，原文与组别保留供核对。 | J82: 巴西+印尼同源；措辞有差异，见分国家版
A83: S06-R030 | B83: FGD-5. 产品评价 | C83: Q9 | D83: 30 | E83: 对于一辆A00级纯电小车，您认为多少续航里程才算够用？在什么使用场景下会感到续航不够？ | F83: Q-M4.3-01 | G83: 归并/改写 | H83: 逐题分配语义任务，同义主问归并，原文与组别保留供核对。 | J83: 三国同源
A84: S06-R032 | B84: FGD-5. 产品评价 | C84: Q10 | D84: 32 | E84: 如果同一款车在300km续航和400km续航之间选择，其他方面都一样，您会选哪个？ | F84: Q-M4.3-03 | G84: 归并/改写 | H84: 逐题分配语义任务，同义主问归并，原文与组别保留供核对。 | J84: 三国同源
A85: S06-R033 | B85: FGD-5. 产品评价 | C85: Q11 | D85: 33 | E85: 如果400km版本比300km版本贵€1,300（约【调研国家】当地差价），您是否愿意购买400km版本？ | F85: Q-M4.3-03 | G85: 归并/改写 | H85: 逐题分配语义任务，同义主问归并，原文与组别保留供核对。 | J85: 仅意大利
A86: S06-R035 | B86: FGD-5. 产品评价 | C86: Q12 | D86: 35 | E86: 如果400km版本比300km版本贵相当于约300km版价格的8-10%溢价，您是否愿意购买400km版本？ | F86: Q-M4.3-03 | G86: 归并/改写 | H86: 逐题分配语义任务，同义主问归并，原文与组别保留供核对。 | J86: 巴西+印尼同源
A87: S06-R037 | B87: FGD-5. 产品评价 | C87: Q13 | D87: 37 | E87: 日常用车中，您理想的充电频率和单次充电时长是怎样的？什么样的补能条件会让您完全没有里程焦虑？ | F87: Q-M4.3-02 | G87: 归并/改写 | H87: 逐题分配语义任务，同义主问归并，原文与组别保留供核对。 | J87: 三国同源
A88: S06-R039 | B88: FGD-5. 产品评价 | C88: Q14 | D88: 39 | E88: 您一般多久充一次电？主要在家充还是公共充电桩？比例大约是多少？ | F88: Q-M4.2-01 | G88: 归并/改写 | H88: 逐题分配语义任务，同义主问归并，原文与组别保留供核对。 | J88: 意大利+印尼同源
A89: S06-R041 | B89: FGD-5. 产品评价 | C89: Q15 | D89: 41 | E89: 您用过快充吗？频率如何？快充对电池寿命的担忧大吗？ | F89: Q-M4.2-02 | G89: 归并/改写 | H89: 逐题分配语义任务，同义主问归并，原文与组别保留供核对。 | J89: 意大利+印尼同源
A90: S06-R043 | B90: FGD-5. 产品评价 | C90: Q16 | D90: 43 | E90: 你们在平时充电的过程中有发生什么不好的体验的事情吗？有发生过过热或者充电时间久，或者有没有出现过什么故障呢？ | F90: Q-M4.2-03 | G90: 归并/改写 | H90: 逐题分配语义任务，同义主问归并，原文与组别保留供核对。 | J90: 仅印尼
A91: S06-R044 | B91: FGD-5. 产品评价 | C91: Q17 | D91: 44 | E91: 您一般多久充一次电？主要在家充还是公共充电桩？比例大约是多少？ | F91: Q-M4.2-01 | G91: 归并/改写 | H91: 逐题分配语义任务，同义主问归并，原文与组别保留供核对。 | I91: BEV组 | J91: 仅巴西
A92: S06-R046 | B92: FGD-5. 产品评价 | C92: Q18 | D92: 46 | E92: 您用过快充吗？频率如何？快充对电池寿命的担忧大吗？ | F92: Q-M4.2-02 | G92: 归并/改写 | H92: 逐题分配语义任务，同义主问归并，原文与组别保留供核对。 | I92: BEV组 | J92: 仅巴西
A93: S06-R048 | B93: FGD-5. 产品评价 | C93: Q19 | D93: 48 | E93: 你们在平时充电的过程中有发生什么不好的体验的事情吗？有发生过过热或者充电时间久，或者有没有出现过什么故障呢？ | F93: Q-M4.2-03 | G93: 归并/改写 | H93: 逐题分配语义任务，同义主问归并，原文与组别保留供核对。 | I93: BEV组 | J93: 仅巴西
A94: S06-R049 | B94: FGD-5. 产品评价 | C94: Q20 | D94: 49 | E94: 如果未来换BEV，您对充电有什么顾虑？您觉得什么样的充电条件才能让您放心选择BEV？ | F94: Q-M4.2-04 Q-M6.4-01 | G94: 拆分研究任务 | H94: 按研究任务显式对应；共用主问，保留来源对象与证据差异；多目标时拆分。 | I94: ICE组 | J94: 仅巴西
A95: S06-R050 | B95: FGD-5. 产品评价 | C95: Q21 | D95: 50 | E95: 以下本地生活/出行类App，您认为哪些最需要与车机深度集成？ | F95: Q-M8.3-01 | G95: 归并/改写 | H95: 逐题分配语义任务，同义主问归并，原文与组别保留供核对。 | J95: 三国同源
A96: S06-R054 | B96: FGD-5. 产品评价 | C96: Q22 | D96: 54 | E96: 对于一辆小尺寸纯电小车，您认为车机屏幕应该是简洁的单屏方案，还是更丰富的多屏/联屏方案？为什么？ | F96: Q-M5.5-01 | G96: 归并/改写 | H96: 逐题分配语义任务，同义主问归并，原文与组别保留供核对。 | J96: 三国同源
A97: S06-R056 | B97: FGD-5. 产品评价 | C97: Q23 | D97: 56 | E97: 您对智能驾驶辅助（自动跟车/车道保持/自动泊车等）的了解程度如何？目前是否在用？ | F97: Q-M4.4-01 | G97: 归并/改写 | H97: 逐题分配语义任务，同义主问归并，原文与组别保留供核对。 | J97: 三国同源
A98: S06-R058 | B98: FGD-5. 产品评价 | C98: Q24 | D98: 58 | E98: 在一辆A00级小车上，以下智能驾驶功能中您最看重哪项？（自动泊车/车道保持/自动跟车/自动变道）是否有您认为"可以没有"的功能？ | F98: Q-M4.4-02 | G98: 归并/改写 | H98: 逐题分配语义任务，同义主问归并，原文与组别保留供核对。 | J98: 三国同源
A99: S06-R060 | B99: FGD-5. 产品评价 | C99: Q25 | D99: 60 | E99: 如果一辆A00小车配备自动泊车等高阶智驾功能，您认为是否值得多花钱？愿意多花多少？ | F99: Q-M5.6-06 | G99: 归并/改写 | H99: 逐题分配语义任务，同义主问归并，原文与组别保留供核对。 | J99: 三国同源
A100: S06-R062 | B100: FGD-5. 产品评价 | C100: Q26 | D100: 62 | E100: 有出门郊游/海滩的习惯吗？一辆电车能够在郊游的时候给一些电子设备供电（咖啡壶），你觉得这类V2L的功能是否值钱？愿意额外付多少？ | F100: Q-M5.6-03 | G100: 归并/改写 | H100: 逐题分配语义任务，同义主问归并，原文与组别保留供核对。 | J100: 巴西+印尼同源
A101: S06-R064 | B101: FGD-5. 产品评价 | C101: Q27 | D101: 64 | E101: 您当初购买这辆车花了多少钱（落地价）？是否觉得偏贵？ | F101: Q-M3.1-03 | G101: 归并/改写 | H101: 逐题分配语义任务，同义主问归并，原文与组别保留供核对。 | J101: 三国同源
A102: S06-R068 | B102: FGD-5. 产品评价 | C102: Q28 | D102: 68 | E102: 如果有一辆中国品牌的A00级纯电小车，配置和续航优于当前主流竞品，您认为合理价格应该是多少？ | F102: Q-M6.3-01 | G102: 归并/改写 | H102: 逐题分配语义任务，同义主问归并，原文与组别保留供核对。 | J102: 三国同源
A103: S06-R070 | B103: FGD-5. 产品评价 | C103: Q29 | D103: 70 | E103: 购买这类小车时，安全配置对您有多重要？排在决策因素的第几位？ | F103: Q-M4.5-01 | G103: 归并/改写 | H103: 逐题分配语义任务，同义主问归并，原文与组别保留供核对。 | J103: 三国同源
A104: S06-R073 | B104: FGD-5. 产品评价 | C104: Q30 | D104: 73 | E104: 请对以下安全功能的重要性进行排序：气囊、倒车影像、360全景影像、盲区监测、自动紧急制动、行车记录仪。 | F104: Q-M5.7-03 | G104: 归并/改写 | H104: 逐题分配语义任务，同义主问归并，原文与组别保留供核对。 | J104: 三国同源
A105: S06-R075 | B105: FGD-5. 产品评价 | C105: Q31 | D105: 75 | E105: 您是否关注车辆的碰撞测试成绩（如Euro NCAP或ASEAN NCAP）？这会影响您的购买决策吗？ | F105: Q-M4.5-01 | G105: 归并/改写 | H105: 逐题分配语义任务，同义主问归并，原文与组别保留供核对。 | J105: 三国同源；措辞有差异，见分国家版
A106: S06-R083 | B106: FGD-5. 产品评价 | C106: Q32 | D106: 83 | E106: 现在的车是什么颜色的？当时是否考虑过其他颜色？为什么选择这个颜色？对黑色是否有担心吸热？怎么看待鲜艳的颜色？如蓝色，黄色等 | F106: Q-M5.3-03 | G106: 归并/改写 | H106: 逐题分配语义任务，同义主问归并，原文与组别保留供核对。 | J106: 仅巴西
... A142: S10-R018 | B142: IHV-3. 购买旅程 | C142: Q11 | D142: 18 | E142: 核心竞品：当时核心备选清单里有哪几款车？（是否有跨品类对比？ICE与BEV是否跨动力类型对比？）最终未选择的备选车辆，主要在哪些特定方面未契合您的要求？ | F142: Q-M3.2-01 Q-M3.4-03 | G142: 拆分研究任务 | H142: 按研究任务显式对应；共用主问，保留来源对象与证据差异；多目标时拆分。 | J142: 三国同源；措辞有差异，见分国家版
A143: S10-R019 | B143: IHV-3. 购买旅程 | C143: Q12 | D143: 19 | E143: 动力筛选机制：在缩小备选名单的过程中，纯电（BEV）和ICE/混动，在您的决策树中处于哪个层级？ | F143: Q-M4.1-01 | G143: 归并/改写 | H143: 逐题分配语义任务，同义主问归并，原文与组别保留供核对。 | I143: 分支A：BEV车主（BYD Seagull / Renault 5） | J143: 仅意大利
A144: S10-R020 | B144: IHV-3. 购买旅程 | C144: Q13 | D144: 20 | E144: BEV选择确认：在完全没有燃油版本可选的情况下，您对纯电动力的接受度和顾虑分别是什么？最终为什么选择了BEV而非ICE？ | F144: Q-M4.1-01 | G144: 归并/改写 | H144: 逐题分配语义任务，同义主问归并，原文与组别保留供核对。 | I144: 分支A：BEV车主（BYD Seagull / Renault 5） | J144: 仅意大利
A145: S10-R021 | B145: IHV-3. 购买旅程 | C145: Q14 | D145: 21 | E145: 纯电续航多少公里您感到满意？日常通勤半径与续航匹配度如何？ | F145: Q-M4.3-01 | G145: 归并/改写 | H145: 逐题分配语义任务，同义主问归并，原文与组别保留供核对。 | I145: 分支A：BEV车主（BYD Seagull / Renault 5） | J145: 仅意大利
A146: S10-R022 | B146: IHV-3. 购买旅程 | C146: Q15 | D146: 22 | E146: 【关于家充桩】您目前的交流充电桩（AC桩）功率大约是多少？（7kW/11kW/22kW）安装过程顺利吗？物业管理审批流程如何？ | F146: Q-M4.2-04 | G146: 归并/改写 | H146: 逐题分配语义任务，同义主问归并，原文与组别保留供核对。 | I146: 分支A：BEV车主（BYD Seagull / Renault 5） | J146: 仅意大利
A147: S10-R023 | B147: IHV-3. 购买旅程 | C147: Q16 | D147: 23 | E147: 您对智能驾驶辅助（自动跟车/车道保持/自动泊车等）了解多少？目前在用吗？最看重哪项？最不需要哪项？ | F147: Q-M4.4-01 | G147: 归并/改写 | H147: 逐题分配语义任务，同义主问归并，原文与组别保留供核对。 | I147: 分支A：BEV车主（BYD Seagull / Renault 5） | J147: 仅意大利
A148: S10-R024 | B148: IHV-3. 购买旅程 | C148: Q17 | D148: 24 | E148: 动力筛选机制：在缩小备选名单的过程中，纯电（BEV）和ICE/混动，在您的决策树中处于哪个层级？ | F148: Q-M4.1-01 | G148: 归并/改写 | H148: 逐题分配语义任务，同义主问归并，原文与组别保留供核对。 | I148: 分支B：ICE车主（FGD2参与者） | J148: 仅意大利
A149: S10-R025 | B149: IHV-3. 购买旅程 | C149: Q18 | D149: 25 | E149: 顾虑评估：在BEV车型的评估环节，是哪些具体的使用场景或物理条件未能满足您的行车预期？最终放弃BEV的核心原因是什么？ | F149: Q-M4.1-02 | G149: 归并/改写 | H149: 逐题分配语义任务，同义主问归并，原文与组别保留供核对。 | I149: 分支B：ICE车主（FGD2参与者） | J149: 仅意大利
A150: S10-R026 | B150: IHV-3. 购买旅程 | C150: Q19 | D150: 26 | E150: 转BEV条件评估：如果以下条件逐一改善，哪个改善后最可能让您未来转向BEV？（家充桩解决了 / 续航提升到400km+ / 公共充电网络完善 / BEV价格与ICE持平 / 品牌信任增强 / Euro NCAP五星认证） | F150: Q-M6.4-01 | G150: 归并/改写 | H150: 逐题分配语义任务，同义主问归并，原文与组别保留供核对。 | I150: 分支B：ICE车主（FGD2参与者） | J150: 仅意大利
A151: S10-R027 | B151: IHV-3. 购买旅程 | C151: Q20 | D151: 27 | E151: 纯电续航多少公里您才能感到满意，理由是什么？ | F151: Q-M4.3-01 | G151: 归并/改写 | H151: 逐题分配语义任务，同义主问归并，原文与组别保留供核对。 | I151: 分支B：ICE车主（FGD2参与者） | J151: 仅意大利
A152: S10-R028 | B152: IHV-3. 购买旅程 | C152: Q21 | D152: 28 | E152: 您对智能驾驶辅助了解多少？最看重哪项？最不需要哪项？ | F152: Q-M4.4-02 | G152: 归并/改写 | H152: 逐题分配语义任务，同义主问归并，原文与组别保留供核对。 | I152: 分支B：ICE车主（FGD2参与者） | J152: 仅意大利
A153: S10-R029 | B153: IHV-3. 购买旅程 | C153: Q22 | D153: 29 | E153: 决策临界点：对比那台让您犹豫最久的竞品车型，哪些因素让您决定了这个品牌？最终选择了哪个配置级别？为什么？最有吸引力的配置是什么？ | F153: Q-M3.4-02 Q-M3.4-05 | G153: 拆分研究任务 | H153: 按研究任务显式对应；共用主问，保留来源对象与证据差异；多目标时拆分。 | J153: 仅意大利
A154: S10-R030 | B154: IHV-3. 购买旅程 | C154: Q23 | D154: 30 | E154: 您最后选择了哪个颜色？为什么选择这个颜色？这个颜色给你什么样的感觉？ | F154: Q-M5.3-03 | G154: 归并/改写 | H154: 逐题分配语义任务，同义主问归并，原文与组别保留供核对。 | J154: 仅意大利
A155: S10-R031 | B155: IHV-3. 购买旅程 | C155: Q24 | D155: 31 | E155: 动力筛选机制：在缩小备选名单的过程中，纯电（BEV）、插电混动（PHEV）及传统燃油技术，在您的决策树中处于哪个层级？（如：是首先排除特定动力形式，还是先选车型再看动力？） | F155: Q-M4.1-01 | G155: 归并/改写 | H155: 逐题分配语义任务，同义主问归并，原文与组别保留供核对。 | J155: 巴西+印尼同源
A156: S10-R032 | B156: IHV-3. 购买旅程 | C156: Q25 | D156: 32 | E156: 纯电续航多少公里能感到满意，理由是什么？ | F156: Q-M4.3-01 | G156: 归并/改写 | H156: 逐题分配语义任务，同义主问归并，原文与组别保留供核对。 | J156: 仅印尼
A157: S10-R034 | B157: IHV-3. 购买旅程 | C157: Q26 | D157: 34 | E157: 平时怎么充电？家里充电，还是在外充电？ | F157: Q-M4.2-01 | G157: 归并/改写 | H157: 逐题分配语义任务，同义主问归并，原文与组别保留供核对。 | J157: 仅印尼
A158: S10-R035 | B158: IHV-3. 购买旅程 | C158: Q27 | D158: 35 | E158: 在炎热地区充电方面有没有什么抱怨？比如充电时间久或者有没有出现过什么故障的等等 | F158: Q-M4.2-03 | G158: 归并/改写 | H158: 逐题分配语义任务，同义主问归并，原文与组别保留供核对。 | J158: 仅印尼
A159: S10-R036 | B159: IHV-3. 购买旅程 | C159: Q28 | D159: 36 | E159: 关于家里的交流慢充桩（AC桩），您在实际使用或了解中，是否关注过7kW与11kW在充电效率上的体验差异？ | F159: Q-M4.2-05 | G159: 归并/改写 | H159: 逐题分配语义任务，同义主问归并，原文与组别保留供核对。 | J159: 仅印尼
A160: S10-R038 | B160: IHV-3. 购买旅程 | C160: Q29 | D160: 38 | E160: 纯电续航多少公里能感到满意，理由是什么？ | F160: Q-M4.3-01 | G160: 归并/改写 | H160: 逐题分配语义任务，同义主问归并，原文与组别保留供核对。 | I160: BEV车主 | J160: 仅巴西
A161: S10-R040 | B161: IHV-3. 购买旅程 | C161: Q30 | D161: 40 | E161: 平时怎么充电？家里充电，还是在外充电？ | F161: Q-M4.2-01 | G161: 归并/改写 | H161: 逐题分配语义任务，同义主问归并，原文与组别保留供核对。 | I161: BEV车主 | J161: 仅巴西
A162: S10-R042 | B162: IHV-3. 购买旅程 | C162: Q31 | D162: 42 | E162: 关于家里的交流慢充桩（AC桩），您在实际使用或了解中，是否关注过7kW与11kW在充电效率上的体验差异？ | F162: Q-M4.2-05 | G162: 归并/改写 | H162: 逐题分配语义任务，同义主问归并，原文与组别保留供核对。 | I162: BEV车主 | J162: 仅巴西
A163: S10-R046 | B163: IHV-3. 购买旅程 | C163: Q32 | D163: 46 | E163: 您对智能驾驶辅助（自动跟车/车道保持/自动泊车等）了解多少？目前在用吗？ | F163: Q-M4.4-01 | G163: 归并/改写 | H163: 逐题分配语义任务，同义主问归并，原文与组别保留供核对。 | J163: 巴西+印尼同源
...

Sheet 历史项目材料
A2: 135条历史材料记录
A3: 保留规格、示卡及参考表；题卡关系来自原顺序候选，待核对。不得直接作为当前产品能力或当地政策事实。
A5: 材料ID | B5: 来源ID | C5: 原顺序候选题卡 | D5: 历史材料原文 | E5: 使用条件 | F5: 确认状态 | G5: 你的修改意见
A6: MAT-S04-R013 | B6: S04-R013 | C6: Q-M2.7-03 | D6: 续航与补能焦虑 ｜ 购车成本与性价比 | E6: 历史项目材料；参数、效果和价格均待核验 | F6: 待项目材料
A7: MAT-S04-R014 | B7: S04-R014 | C7: Q-M2.7-03 | D7: 表显续航虚标，实际里程大幅缩水 高温/雨季/低温环境续航衰减严重 高速行驶掉电速度过快 满载/开空调后续航折损明显 电池长期使用后容量衰减快 ｜ 车辆基础售价偏高 当地税费、上牌附加成本高 同价位燃油小车配置更高、空间更大 优惠政策少，落地价超出预期 低配基础款缺失刚需功能，高配溢价过高 | E7: 历史项目材料；参数、效果和价格均待核验 | F7: 待项目材料
A8: MAT-S04-R015 | B8: S04-R015 | C8: Q-M2.7-03 | D8: 车内空间与装载实用性 ｜ 充电效率与补能便利性 | E8: 历史项目材料；参数、效果和价格均待核验 | F8: 待项目材料
A9: MAT-S04-R016 | B9: S04-R016 | C9: Q-M2.7-03 | D9: 车辆基础配置缺失 ｜ 车机系统本地化适配 | E9: 历史项目材料；参数、效果和价格均待核验 | F9: 待项目材料
A10: MAT-S04-R017 | B10: S04-R017 | C10: Q-M2.7-03 | D10: 缺少本地路况适配的底盘/悬挂配置 无倒车影像、雷达等基础驾驶辅助 座椅无通风/加热，热带乘坐不适 灯光、雨刮等基础实用功能减配 无快速门窗、手机无线充电等便利配置 ｜ 车机本地语言（葡萄牙语）翻译不完善、翻译生硬 本地道路导航地图更新滞后、路线不准 不支持本地主流支付（Pix）、音乐、社交软件 语音识别不适应本地口音，识别准确率低 车机网络信号差，卡顿、黑屏频发 | E10: 历史项目材料；参数、效果和价格均待核验 | F10: 待项目材料
A11: MAT-S04-R018 | B11: S04-R018 | C11: Q-M2.7-03 | D11: 行驶操控与乘坐舒适性 ｜ 用车长期养护成本 | E11: 历史项目材料；参数、效果和价格均待核验 | F11: 待项目材料
A12: MAT-S04-R019 | B12: S04-R019 | C12: Q-M2.7-03 | D12: 高速行驶车身发飘，稳定性差 底盘减震偏硬，颠簸路面滤震差 高速风噪、胎噪明显，隔音差 转向手感沉重/虚位大，城区驾驶累 空调制冷/制热速度慢，温控不均匀 ｜ 电车保险保费远高于同级别燃油车 电池更换价格高昂，更换成本接近半台车 常规保养项目收费贵，保养周期短 易损配件更换价格高于本地燃油车型 | E12: 历史项目材料；参数、效果和价格均待核验 | F12: 待项目材料
A13: MAT-S04-R020 | B13: S04-R020 | C13: Q-M2.7-03 | D13: 售后、维保与保值 ｜ | E13: 历史项目材料；参数、效果和价格均待核验 | F13: 待项目材料
A14: MAT-S04-R021 | B14: S04-R021 | C14: Q-M2.7-03 | D14: 本地线下售后网点数量少、距离远 维修等待周期长，配件备货不足 维修技师不熟悉中国品牌电车，维修效率低 二手电车流通渠道少，转手折价严重 担忧电池故障后无完善质保方案 本地门店电池检测、更换服务不完善 ｜ | E14: 历史项目材料；参数、效果和价格均待核验 | F14: 待项目材料
A15: MAT-S04-R022 | B15: S04-R022 | C15: Q-M2.7-03 | D15: 后排腿部空间局促，成人乘坐压抑 后备箱储物容积小，大件物品放不下 车内储物格数量少、尺寸不合理 后排座椅无法完全放平，拓展能力差 车门开口小，上下车/搬取物品不方便 ｜ 公共快充充电功率低，充满耗时久 公共充电桩故障多、经常无法使用 家用公寓无法安装私人充电桩 乡镇、城际、外岛缺少充电网点 跨区域充电服务商APP不互通，操作繁琐 充电桩接口和车辆不兼容，充电失败 | E15: 历史项目材料；参数、效果和价格均待核验 | F15: 待项目材料
A16: MAT-S11-R033 | B16: S11-R033 | D16: 类别 ｜ 是否重要 ｜ 是否会有溢价 | E16: 历史项目材料；参数、效果和价格均待核验 | F16: 待项目材料
A17: MAT-S11-R034 | B17: S11-R034 | D17: 安全侧气囊（侧气帘） ｜ ｜ | E17: 历史项目材料；参数、效果和价格均待核验 | F17: 待项目材料
A18: MAT-S11-R035 | B18: S11-R035 | D18: 全景影像 ｜ ｜ | E18: 历史项目材料；参数、效果和价格均待核验 | F18: 待项目材料
A19: MAT-S11-R036 | B19: S11-R036 | D19: 一键式启动按钮（无需掏钥匙，随身带智能钥匙踩刹车按钮就能启动汽车） ｜ ｜ | E19: 历史项目材料；参数、效果和价格均待核验 | F19: 待项目材料
A20: MAT-S11-R037 | B20: S11-R037 | D20: 氛围灯 ｜ ｜ | E20: 历史项目材料；参数、效果和价格均待核验 | F20: 待项目材料
A21: MAT-S11-R038 | B21: S11-R038 | D21: 副驾电动调节 ｜ ｜ | E21: 历史项目材料；参数、效果和价格均待核验 | F21: 待项目材料
A22: MAT-S11-R039 | B22: S11-R039 | D22: 拖车钩 ｜ ｜ | E22: 历史项目材料；参数、效果和价格均待核验 | F22: 待项目材料
A23: MAT-S11-R040 | B23: S11-R040 | D23: 前排座椅通风 ｜ ｜ | E23: 历史项目材料；参数、效果和价格均待核验 | F23: 待项目材料
A24: MAT-S11-R041 | B24: S11-R041 | D24: 在线谷歌导航 ｜ ｜ | E24: 历史项目材料；参数、效果和价格均待核验 | F24: 待项目材料
A25: MAT-S11-R042 | B25: S11-R042 | D25: 在线生态APP（含音乐、天气、游戏、视频等APP类如youtube、spotify、Amazon music、angry bird等APP下载） ｜ ｜ | E25: 历史项目材料；参数、效果和价格均待核验 | F25: 待项目材料
A26: MAT-S11-R043 | B26: S11-R043 | D26: 后雨刮 ｜ ｜ | E26: 历史项目材料；参数、效果和价格均待核验 | F26: 待项目材料
A27: MAT-S11-R045 | B27: S11-R045 | D27: 前备箱50L防污好清理——独立于车内的大储物空间，可冲洗排污，可用于海滩游玩、存放生鲜、独立充电设备等 | E27: 历史项目材料；参数、效果和价格均待核验 | F27: 待项目材料
... A31: MAT-S11-R049 | B31: S11-R049 | D31: 11kW双向车载充电机——11KW三相交流充电，40度电A级车充满电仅4.5h（VS普通家用单相7KW满电需要6.5小时） | E31: 历史项目材料；参数、效果和价格均待核验 | F31: 待项目材料
A32: MAT-S11-R053 | B32: S11-R053 | C32: Q-M6.5-02 | D32: 配置项 ｜ 是否重要 ｜ 是否会有溢价 | E32: 历史项目材料；参数、效果和价格均待核验 | F32: 待项目材料
A33: MAT-S11-R054 | B33: S11-R054 | C33: Q-M6.5-02 | D33: 安全侧气囊（侧气帘） ｜ ｜ | E33: 历史项目材料；参数、效果和价格均待核验 | F33: 待项目材料
A34: MAT-S11-R055 | B34: S11-R055 | C34: Q-M6.5-02 | D34: 全景影像 ｜ ｜ | E34: 历史项目材料；参数、效果和价格均待核验 | F34: 待项目材料
A35: MAT-S11-R056 | B35: S11-R056 | C35: Q-M6.5-02 | D35: 一键式启动按钮（无需掏钥匙，随身带智能钥匙踩刹车按钮就能启动汽车） ｜ ｜ | E35: 历史项目材料；参数、效果和价格均待核验 | F35: 待项目材料
A36: MAT-S11-R057 | B36: S11-R057 | C36: Q-M6.5-02 | D36: 氛围灯 ｜ ｜ | E36: 历史项目材料；参数、效果和价格均待核验 | F36: 待项目材料
A37: MAT-S11-R058 | B37: S11-R058 | C37: Q-M6.5-02 | D37: 副驾电动调节 ｜ ｜ | E37: 历史项目材料；参数、效果和价格均待核验 | F37: 待项目材料
A38: MAT-S11-R059 | B38: S11-R059 | C38: Q-M6.5-02 | D38: 拖车钩 ｜ ｜ | E38: 历史项目材料；参数、效果和价格均待核验 | F38: 待项目材料
A39: MAT-S11-R060 | B39: S11-R060 | C39: Q-M6.5-02 | D39: 前排座椅通风 ｜ ｜ | E39: 历史项目材料；参数、效果和价格均待核验 | F39: 待项目材料
A40: MAT-S11-R061 | B40: S11-R061 | C40: Q-M6.5-02 | D40: 在线谷歌导航 ｜ ｜ | E40: 历史项目材料；参数、效果和价格均待核验 | F40: 待项目材料
A41: MAT-S11-R062 | B41: S11-R062 | C41: Q-M6.5-02 | D41: 在线生态APP（含音乐、天气、游戏、视频等APP类如YouTube、Spotify、Amazon Music、Angry Bird等APP下载） ｜ ｜ | E41: 历史项目材料；参数、效果和价格均待核验 | F41: 待项目材料
A42: MAT-S11-R063 | B42: S11-R063 | C42: Q-M6.5-02 | D42: 后雨刮 ｜ ｜ | E42: 历史项目材料；参数、效果和价格均待核验 | F42: 待项目材料
A43: MAT-S11-R064 | B43: S11-R064 | C43: Q-M6.5-02 | D43: 卖点 ｜ 描述 | E43: 历史项目材料；参数、效果和价格均待核验 | F43: 待项目材料
... A70: MAT-S19-R036 | B70: S19-R036 | C70: Q-M5.1-03 | D70: 核心卖点 ｜ 科技动感SUV，标配 17 寸轮毂；后排座椅 6:4放倒，乘坐空间宽裕；前备箱 + 375L 后备厢 + 承重 75KG 行李架；本地化调校多连杆底盘，满载离地间隙145通过性优异，方向盘四向调节 | E70: 历史项目材料；参数、效果和价格均待核验 | F70: 待项目材料
A71: MAT-S26-R022 | B71: S26-R022 | D71: 配置 ｜ 基础版 ｜ 豪华版 ｜ 顶奢版 | E71: 历史项目材料；参数、效果和价格均待核验 | F71: 待项目材料
A72: MAT-S26-R023 | B72: S26-R023 | D72: 两驱(一个电机) ｜ √ ｜ ｜ | E72: 历史项目材料；参数、效果和价格均待核验 | F72: 待项目材料
A73: MAT-S26-R024 | B73: S26-R024 | D73: 四驱(前后各一个电机) ｜ ｜ √ ｜ | E73: 历史项目材料；参数、效果和价格均待核验 | F73: 待项目材料
A74: MAT-S26-R025 | B74: S26-R025 | D74: 前电动门(驾驶员/副驾驶) ｜ ｜ √ ｜ √ | E74: 历史项目材料；参数、效果和价格均待核验 | F74: 待项目材料
A75: MAT-S26-R026 | B75: S26-R026 | D75: REEV的纯电续航550km ｜ ｜ √ ｜ √ | E75: 历史项目材料；参数、效果和价格均待核验 | F75: 待项目材料
A76: MAT-S26-R027 | B76: S26-R027 | D76: 二排豪华座椅：包含零重力功能、坐垫倾角电调、电动小腿托、头枕上下电调、头枕音响、22点位座椅坐垫按摩、180度旋转功能 ｜ ｜ √ ｜ √ | E76: 历史项目材料；参数、效果和价格均待核验 | F76: 待项目材料
A77: MAT-S26-R028 | B77: S26-R028 | D77: 30个/50个豪华品牌扬声器(顶级品牌) ｜ ｜ √ ｜ √ | E77: 历史项目材料；参数、效果和价格均待核验 | F77: 待项目材料
A78: MAT-S26-R029 | B78: S26-R029 | D78: 豪华双色车身 ｜ ｜ ｜ √ | E78: 历史项目材料；参数、效果和价格均待核验 | F78: 待项目材料
A79: MAT-S26-R030 | B79: S26-R030 | D79: 行政中岛(二排两个座椅中间，带冰箱，折叠桌板，平板支架扩展坞、密码箱) ｜ ｜ ｜ √ | E79: 历史项目材料；参数、效果和价格均待核验 | F79: 待项目材料
A80: MAT-S26-R037 | B80: S26-R037 | C80: Q-M6.3-02 | D80: 配置 ｜ 基础版 ｜ 豪华版 ｜ 顶奢版 | E80: 历史项目材料；参数、效果和价格均待核验 | F80: 待项目材料
A81: MAT-S26-R038 | B81: S26-R038 | C81: Q-M6.3-02 | D81: 两驱(一个电机) ｜ √ ｜ ｜ | E81: 历史项目材料；参数、效果和价格均待核验 | F81: 待项目材料
A82: MAT-S26-R039 | B82: S26-R039 | C82: Q-M6.3-02 | D82: 四驱(前后各一个电机) ｜ ｜ √ ｜ | E82: 历史项目材料；参数、效果和价格均待核验 | F82: 待项目材料
A83: MAT-S26-R040 | B83: S26-R040 | C83: Q-M6.3-02 | D83: 前电动门(驾驶员/副驾驶) ｜ ｜ √ ｜ √ | E83: 历史项目材料；参数、效果和价格均待核验 | F83: 待项目材料
A84: MAT-S26-R041 | B84: S26-R041 | C84: Q-M6.3-02 | D84: REEV的纯电续航550km ｜ ｜ √ ｜ √ | E84: 历史项目材料；参数、效果和价格均待核验 | F84: 待项目材料
A85: MAT-S26-R042 | B85: S26-R042 | C85: Q-M6.3-02 | D85: 二排豪华座椅：包含零重力功能、坐垫倾角电调、电动小腿托、头枕上下电调、头枕音响、22点位座椅坐垫按摩、180度旋转功能 ｜ ｜ √ ｜ √ | E85: 历史项目材料；参数、效果和价格均待核验 | F85: 待项目材料
A86: MAT-S26-R043 | B86: S26-R043 | C86: Q-M6.3-02 | D86: 30个/50个豪华品牌扬声器(顶级品牌) ｜ ｜ √ ｜ √ | E86: 历史项目材料；参数、效果和价格均待核验 | F86: 待项目材料
A87: MAT-S26-R044 | B87: S26-R044 | C87: Q-M6.3-02 | D87: 豪华双色车身 ｜ ｜ ｜ √ | E87: 历史项目材料；参数、效果和价格均待核验 | F87: 待项目材料
A88: MAT-S26-R045 | B88: S26-R045 | C88: Q-M6.3-02 | D88: 行政中岛(二排两个座椅中间，带冰箱，折叠桌板，平板支架扩展坞、密码箱) ｜ ｜ ｜ √ | E88: 历史项目材料；参数、效果和价格均待核验 | F88: 待项目材料
A89: MAT-S38-R008 | B89: S38-R008 | C89: Q-M5.6-01 | D89: 类别 ｜ 主要配置项 ｜ 评价 | E89: 历史项目材料；参数、效果和价格均待核验 | F89: 待项目材料
A90: MAT-S38-R009 | B90: S38-R009 | C90: Q-M5.6-01 | D90: 舒适配置 ｜ 空调制冷（制冷速度、后排制冷效果、分区控制能力） ｜ | E90: 历史项目材料；参数、效果和价格均待核验 | F90: 待项目材料
A91: MAT-S38-R010 | B91: S38-R010 | C91: Q-M5.6-01 | D91: 舒适配置 ｜ 防晒隔热玻璃 ｜ | E91: 历史项目材料；参数、效果和价格均待核验 | F91: 待项目材料
... A140: MAT-S43-R041 | B140: S43-R041 | C140: Q-M7.3-04 | D140: 行政中岛(二排两个座椅中间，带冰箱，折叠桌板，平板支架扩展坞、密码箱) ｜ ｜ ｜ √ | E140: 历史项目材料；参数、效果和价格均待核验 | F140: 待项目材料

Sheet 原主持说明
A2: 原过渡与主持说明
A3: 表格类来源已放在“历史项目材料”。此处保留其余原始过渡和主持说明，不自动拼接到访谈正文。
A5: 来源ID | B5: 类型 | C5: 工作表与行号 | D5: 原文 | E5: 父题候选
A6: S06-R011 | B6: 过渡话术 | C6: FGD-5. 产品评价，第11行 | D6: 【过渡话术】刚才我们从用车和购车角度聊了很多，接下来我们想从产品本身出发，聊聊您对未来4米纯电小车的期望。 | E6: 无可靠父题
A7: S06-R012 | B7: 主持说明 | C7: FGD-5. 产品评价，第12行 | D7: 展示本品+3款竞品外造型图，每车快速获取第一印象。看到这辆车第一感觉是什么，用三到五个形容词来描述。然后判断这辆车是偏硬朗还是偏圆润、偏紧凑还是偏大体量，再问什么样的人会开这辆车，以及最喜欢和最不喜欢的地方分别是什么。 | E7: 无可靠父题
A8: S06-R013 | B8: 主持说明 | C8: FGD-5. 产品评价，第13行 | D8: 全部看完后进入集中对比环节。逐项追问哪款看起来最硬朗、哪款最实用、哪款最中性、哪款最有品质感或最贵，每项追问为什么，记录板书记录最集中的答案。最后让每人用一句话表态，如果选一款外观，最愿意买哪款。 | E8: 无可靠父题
A9: S06-R014 | B9: 主持说明 | C9: FGD-5. 产品评价，第14行 | D9: 展示本品+3款竞品内饰。看到这个内饰第一感觉是什么，三个形容词概括，然后判断是偏简洁还是偏复杂、偏科技还是偏传统、偏硬朗还是偏柔和。再追问有没有品质感，哪些细节让你有或没有这种感觉。 | E9: 无可靠父题
A10: S06-R015 | B10: 主持说明 | C10: FGD-5. 产品评价，第15行 | D10: 内饰全部看完后用2分钟讨论，让大家举手投票更喜欢哪种，然后指名阐述原因。接着追问哪种看起来更简洁、哪种更有科技感、哪种更硬朗利落，每项追问为什么。 | E10: 无可靠父题
A11: S06-R016 | B11: 主持说明 | C11: FGD-5. 产品评价，第16行 | D11: 最后请每人用一句话描述理想中的车应该长什么样。然后主持人直接抛出S11的预设风格方向——"如果一辆车外观是硬朗中性、内饰是简洁科技，你会感兴趣吗？为什么？"作为全场收尾，快速验证预设风格的接受度。 | E11: 无可靠父题
A12: S06-R024 | B12: 过渡话术 | C12: FGD-5. 产品评价，第24行 | D12: 【过渡话术】刚才我们从用车和购车角度聊了很多，接下来我们想从产品本身出发，聊聊您对未来4米纯电小车的期望。 | E12: 无可靠父题
A13: S06-R025 | B13: 主持说明 | C13: FGD-5. 产品评价，第25行 | D13: 展示本品+3款竞品外造型图，每车快速获取第一印象。看到这辆车第一感觉是什么，用三到五个形容词来描述。然后判断这辆车是偏硬朗还是偏圆润、偏紧凑还是偏大体量，再问什么样的人会开这辆车，以及最喜欢和最不喜欢的地方分别是什么。 | E13: 无可靠父题
A14: S06-R026 | B14: 主持说明 | C14: FGD-5. 产品评价，第26行 | D14: 全部看完后进入集中对比环节。逐项追问哪款看起来最硬朗、哪款最实用、哪款最中性、哪款最有品质感或最贵，每项追问为什么，记录板书记录最集中的答案。最后让每人用一句话表态，如果选一款外观，最愿意买哪款。 | E14: 无可靠父题
A15: S06-R027 | B15: 主持说明 | C15: FGD-5. 产品评价，第27行 | D15: 展示本品+3款竞品内饰。看到这个内饰第一感觉是什么，三个形容词概括，然后判断是偏简洁还是偏复杂、偏科技还是偏传统、偏硬朗还是偏柔和。再追问有没有品质感，哪些细节让你有或没有这种感觉。 | E15: 无可靠父题
A16: S06-R028 | B16: 主持说明 | C16: FGD-5. 产品评价，第28行 | D16: 内饰全部看完后用2分钟讨论，让大家举手投票更喜欢哪种，然后指名阐述原因。接着追问哪种看起来更简洁、哪种更有科技感、哪种更硬朗利落，每项追问为什么。 | E16: 无可靠父题
... A79: S49-R007 | B79: 过渡话术 | C79: 主机厂-5. 核心风险预警与未来演进机会展望，第7行 | D79: （访谈逻辑：总结出海规避风险点，并探讨产品未来的长期防线。） | E79: 无可靠父题

Sheet 本轮修改记录
A2: 本轮修改记录
A3: 保留你上一版填写的确认状态和意见。2B合并后的题卡重新待审；已删除或合并的旧题仍可在这里追溯。
A5: 对象 | B5: 原工作表 | C5: 原题卡编号 | D5: 原确认状态 | E5: 你的修改意见 | F5: 本轮处理
A6: 2C | B6: 2C-00 执行话术 | C6: Q-E0-01 | D6: 同意 | F6: 保留原审阅状态
A7: 2C | B7: 2C-00 执行话术 | C7: Q-E0-02 | D7: 同意 | F7: 保留原审阅状态
A8: 2C | B8: 2C-00 执行话术 | C8: Q-E0-03 | D8: 同意 | F8: 保留原审阅状态
A9: 2C | B9: 2C-01 生活与车辆背景 | C9: Q-M1.1-01 | D9: 需修改 | E9: 商务/组织是2B | F9: 已纳入本轮修改
A10: 2C | B10: 2C-01 生活与车辆背景 | C10: Q-M1.1-03 | D10: 建议删除 | E10: 看不懂，并且这个和汽车的项目关联有点远 | F10: 已纳入本轮修改
A11: 2C | B11: 2C-01 生活与车辆背景 | C11: Q-M1.1-04 | D11: 同意 | F11: 保留原审阅状态
A12: 2C | B12: 2C-01 生活与车辆背景 | C12: Q-M1.1-05 | D12: 同意 | F12: 保留原审阅状态
A13: 2C | B13: 2C-02 场景与体验 | C13: Q-M2.1-01 | D13: 同意 | F13: 保留原审阅状态
A14: 2C | B14: 2C-02 场景与体验 | C14: Q-M2.1-02 | D14: 同意 | F14: 保留原审阅状态
A15: 2C | B15: 2C-02 场景与体验 | C15: Q-M2.1-03 | D15: 同意 | F15: 保留原审阅状态
A16: 2C | B16: 2C-02 场景与体验 | C16: Q-M2.2-01 | D16: 同意 | F16: 保留原审阅状态
A17: 2C | B17: 2C-02 场景与体验 | C17: Q-M2.2-02 | D17: 同意 | F17: 保留原审阅状态
A18: 2C | B18: 2C-02 场景与体验 | C18: Q-M2.2-03 | D18: 同意 | F18: 保留原审阅状态
A19: 2C | B19: 2C-02 场景与体验 | C19: Q-M2.2-04 | D19: 同意 | F19: 保留原审阅状态
A20: 2C | B20: 2C-02 场景与体验 | C20: Q-M2.3-01 | D20: 同意 | F20: 保留原审阅状态
A21: 2C | B21: 2C-02 场景与体验 | C21: Q-M2.3-02 | D21: 同意 | F21: 保留原审阅状态
A22: 2C | B22: 2C-02 场景与体验 | C22: Q-M2.3-03 | D22: 同意 | F22: 保留原审阅状态
... A33: 2C | B33: 2C-02 场景与体验 | C33: Q-M2.5-05 | D33: 同意 | F33: 保留原审阅状态
A34: 2C | B34: 2C-02 场景与体验 | C34: Q-M2.5-06 | D34: 需修改 | E34: 题目看不懂 | F34: 已纳入本轮修改
A35: 2C | B35: 2C-02 场景与体验 | C35: Q-M2.5-07 | D35: 同意 | F35: 保留原审阅状态
A36: 2C | B36: 2C-02 场景与体验 | C36: Q-M2.5-08 | D36: 同意 | F36: 保留原审阅状态
A37: 2C | B37: 2C-02 场景与体验 | C37: Q-M2.6-01 | D37: 同意 | F37: 保留原审阅状态
A38: 2C | B38: 2C-02 场景与体验 | C38: Q-M2.6-02 | D38: 同意 | F38: 保留原审阅状态
A39: 2C | B39: 2C-02 场景与体验 | C39: Q-M2.6-03 | D39: 同意 | F39: 保留原审阅状态
A40: 2C | B40: 2C-02 场景与体验 | C40: Q-M2.6-04 | D40: 同意 | F40: 保留原审阅状态
A41: 2C | B41: 2C-02 场景与体验 | C41: Q-M2.7-01 | D41: 同意 | F41: 保留原审阅状态
A42: 2C | B42: 2C-02 场景与体验 | C42: Q-M2.7-02 | D42: 同意 | F42: 保留原审阅状态
A43: 2C | B43: 2C-02 场景与体验 | C43: Q-M2.7-03 | D43: 同意 | F43: 保留原审阅状态
A44: 2C | B44: 2C-02 场景与体验 | C44: Q-M2.7-04 | D44: 同意 | F44: 保留原审阅状态
A45: 2C | B45: 2C-02 场景与体验 | C45: Q-M8.1-01 | D45: 同意 | F45: 保留原审阅状态
A46: 2C | B46: 2C-02 场景与体验 | C46: Q-M8.3-01 | D46: 同意 | F46: 保留原审阅状态
A47: 2C | B47: 2C-02 场景与体验 | C47: Q-M8.3-02 | D47: 同意 | F47: 保留原审阅状态
A48: 2C | B48: 2C-02 场景与体验 | C48: Q-M2.6-05 | D48: 需修改 | E48: 汽车氛围有点表述不清楚 | F48: 已纳入本轮修改
A49: 2C | B49: 2C-03 购买旅程 | C49: Q-M3.1-01 | D49: 需修改 | E49: 上一辆车是什么车，用了多久，这信息可能要增加 | F49: 已纳入本轮修改
A50: 2C | B50: 2C-03 购买旅程 | C50: Q-M3.1-02 | D50: 同意 | F50: 保留原审阅状态
A51: 2C | B51: 2C-03 购买旅程 | C51: Q-M3.1-03 | D51: 同意 | F51: 保留原审阅状态
A52: 2C | B52: 2C-03 购买旅程 | C52: Q-M3.2-01 | D52: 同意 | F52: 保留原审阅状态
A53: 2C | B53: 2C-03 购买旅程 | C53: Q-M3.2-02 | D53: 同意 | F53: 保留原审阅状态
A54: 2C | B54: 2C-03 购买旅程 | C54: Q-M3.2-03 | D54: 同意 | F54: 保留原审阅状态
A55: 2C | B55: 2C-03 购买旅程 | C55: Q-M3.2-04 | D55: 同意 | F55: 保留原审阅状态
A56: 2C | B56: 2C-03 购买旅程 | C56: Q-M3.3-01 | D56: 同意 | F56: 保留原审阅状态
A57: 2C | B57: 2C-03 购买旅程 | C57: Q-M3.3-02 | D57: 同意 | F57: 保留原审阅状态
A58: 2C | B58: 2C-03 购买旅程 | C58: Q-M3.3-03 | D58: 同意 | F58: 保留原审阅状态
A59: 2C | B59: 2C-03 购买旅程 | C59: Q-M3.3-04 | D59: 同意 | F59: 保留原审阅状态
A60: 2C | B60: 2C-03 购买旅程 | C60: Q-M3.4-01 | D60: 同意 | F60: 保留原审阅状态
A61: 2C | B61: 2C-03 购买旅程 | C61: Q-M3.4-02 | D61: 同意 | F61: 保留原审阅状态
... A70: 2C | B70: 2C-03 购买旅程 | C70: Q-M8.2-01 | D70: 同意 | F70: 保留原审阅状态
A71: 2C | B71: 2C-03 购买旅程 | C71: Q-M8.2-02 | D71: 需修改 | E71: 看不懂 | F71: 已纳入本轮修改
A72: 2C | B72: 2C-04 动力与补能 | C72: Q-M4.1-01 | D72: 需修改 | E72: 要先问他，你知道哪些动力形式 | F72: 已纳入本轮修改
A73: 2C | B73: 2C-04 动力与补能 | C73: Q-M4.1-02 | D73: 同意 | F73: 保留原审阅状态
A74: 2C | B74: 2C-04 动力与补能 | C74: Q-M4.1-03 | D74: 同意 | F74: 保留原审阅状态
A75: 2C | B75: 2C-04 动力与补能 | C75: Q-M4.2-01 | D75: 需修改 | E75: 请你描述下你充电的i习惯（20%一看到就充电），充电的频率（每天），充电的场所（家or公司）？最近一次是怎样的？。。。要重新组织下语言，总体上是否方便 | F75: 已纳入本轮修改
A76: 2C | B76: 2C-04 动力与补能 | C76: Q-M4.2-02 | D76: 同意 | F76: 保留原审阅状态
A77: 2C | B77: 2C-04 动力与补能 | C77: Q-M4.2-03 | D77: 同意 | F77: 保留原审阅状态
A78: 2C | B78: 2C-04 动力与补能 | C78: Q-M4.2-04 | D78: 需修改 | E78: 您家、公司这些日常停车的地方是否可以安装充电桩？ | F78: 已纳入本轮修改
A79: 2C | B79: 2C-04 动力与补能 | C79: Q-M4.2-05 | D79: 同意 | F79: 保留原审阅状态
A80: 2C | B80: 2C-04 动力与补能 | C80: Q-M4.2-06 | D80: 同意 | F80: 保留原审阅状态
A81: 2C | B81: 2C-04 动力与补能 | C81: Q-M4.3-01 | D81: 同意 | F81: 保留原审阅状态
A82: 2C | B82: 2C-04 动力与补能 | C82: Q-M4.3-02 | D82: 需修改 | E82: 你充电一定要冲到满吗？一般情况下冲到多少？90% 100%。。。这样问比较好，改一下 | F82: 已纳入本轮修改
A83: 2C | B83: 2C-04 动力与补能 | C83: Q-M4.3-03 | D83: 需修改 | E83: 看不懂；我觉得可以问续航多少是底线之类的 | F83: 已纳入本轮修改
A84: 2C | B84: 2C-04 动力与补能 | C84: Q-M4.4-01 | D84: 同意 | F84: 保留原审阅状态
A85: 2C | B85: 2C-04 动力与补能 | C85: Q-M4.4-02 | D85: 同意 | F85: 保留原审阅状态
A86: 2C | B86: 2C-04 动力与补能 | C86: Q-M4.4-03 | D86: 同意 | F86: 保留原审阅状态
A87: 2C | B87: 2C-04 动力与补能 | C87: Q-M4.4-04 | D87: 同意 | F87: 保留原审阅状态
A88: 2C | B88: 2C-04 动力与补能 | C88: Q-M4.5-01 | D88: 同意 | F88: 保留原审阅状态
A89: 2C | B89: 2C-04 动力与补能 | C89: Q-M4.5-02 | D89: 同意 | F89: 保留原审阅状态
A90: 2C | B90: 2C-04 动力与补能 | C90: Q-M4.5-03 | D90: 同意 | F90: 保留原审阅状态
A91: 2C | B91: 2C-04 动力与补能 | C91: Q-M4.5-04 | D91: 同意 | F91: 保留原审阅状态
A92: 2C | B92: 2C-05 产品与配置 | C92: Q-M5.1-01 | D92: 需修改 | E92: 需要有产品概念才会这题，如果没有的话这题不出现，那么需要在哪里有trigger | F92: 已纳入本轮修改
A93: 2C | B93: 2C-05 产品与配置 | C93: Q-M5.1-02 | D93: 需修改 | E93: 需要有产品概念才会这题，如果没有的话这题不出现，那么需要在哪里有trigger | F93: 已纳入本轮修改
A94: 2C | B94: 2C-05 产品与配置 | C94: Q-M5.1-03 | D94: 需修改 | E94: 备选方案？这个没有出现过，所以问题不对 | F94: 已纳入本轮修改
A95: 2C | B95: 2C-05 产品与配置 | C95: Q-M5.2-01 | D95: 需修改 | E95: 体态不是这么说的，应该叫：车型轮廓 | F95: 已纳入本轮修改
A96: 2C | B96: 2C-05 产品与配置 | C96: Q-M5.2-02 | D96: 同意 | F96: 保留原审阅状态
A97: 2C | B97: 2C-05 产品与配置 | C97: Q-M5.2-03 | D97: 同意 | F97: 保留原审阅状态
A98: 2C | B98: 2C-05 产品与配置 | C98: Q-M5.2-04 | D98: 同意 | E98: 看不懂？这个题目很奇怪 | F98: 已纳入本轮修改
A99: 2C | B99: 2C-05 产品与配置 | C99: Q-M5.3-01 | D99: 同意 | E99: 用形容词来形容，你会怎么说 | F99: 已纳入本轮修改
A100: 2C | B100: 2C-05 产品与配置 | C100: Q-M5.3-02 | D100: 同意 | F100: 保留原审阅状态
A101: 2C | B101: 2C-05 产品与配置 | C101: Q-M5.3-03 | D101: 同意 | F101: 保留原审阅状态
A102: 2C | B102: 2C-05 产品与配置 | C102: Q-M5.4-01 | D102: 同意 | F102: 保留原审阅状态
A103: 2C | B103: 2C-05 产品与配置 | C103: Q-M5.4-02 | D103: 同意 | F103: 保留原审阅状态
A104: 2C | B104: 2C-05 产品与配置 | C104: Q-M5.4-03 | D104: 同意 | F104: 保留原审阅状态
A105: 2C | B105: 2C-05 产品与配置 | C105: Q-M5.4-04 | D105: 同意 | F105: 保留原审阅状态
A106: 2C | B106: 2C-05 产品与配置 | C106: Q-M5.4-05 | D106: 同意 | F106: 保留原审阅状态
A107: 2C | B107: 2C-05 产品与配置 | C107: Q-M5.4-06 | D107: 同意 | F107: 保留原审阅状态
A108: 2C | B108: 2C-05 产品与配置 | C108: Q-M5.4-07 | D108: 同意 | F108: 保留原审阅状态
A109: 2C | B109: 2C-05 产品与配置 | C109: Q-M5.4-08 | D109: 同意 | F109: 保留原审阅状态
A110: 2C | B110: 2C-05 产品与配置 | C110: Q-M5.5-01 | D110: 同意 | F110: 保留原审阅状态
A111: 2C | B111: 2C-05 产品与配置 | C111: Q-M5.5-02 | D111: 同意 | F111: 保留原审阅状态
... A122: 2C | B122: 2C-05 产品与配置 | C122: Q-M5.7-04 | D122: 同意 | F122: 保留原审阅状态
A123: 2C | B123: 2C-05 产品与配置 | C123: Q-M5.6-07 | D123: 需修改 | E123: 热舒适？这么说吗？这里是隔热吧， | F123: 已纳入本轮修改
A124: 2C | B124: 2C-06 品牌与购买条件 | C124: Q-M6.1-01 | D124: 同意 | F124: 保留原审阅状态
A125: 2C | B125: 2C-06 品牌与购买条件 | C125: Q-M6.1-02 | D125: 同意 | F125: 保留原审阅状态
A126: 2C | B126: 2C-06 品牌与购买条件 | C126: Q-M6.1-03 | D126: 同意 | F126: 保留原审阅状态
A127: 2C | B127: 2C-06 品牌与购买条件 | C127: Q-M6.2-01 | D127: 同意 | F127: 保留原审阅状态
A128: 2C | B128: 2C-06 品牌与购买条件 | C128: Q-M6.2-02 | D128: 同意 | F128: 保留原审阅状态
A129: 2C | B129: 2C-06 品牌与购买条件 | C129: Q-M6.3-01 | D129: 同意 | F129: 保留原审阅状态
A130: 2C | B130: 2C-06 品牌与购买条件 | C130: Q-M6.3-02 | D130: 同意 | F130: 保留原审阅状态
...
